Workbook

Sheet README
A1: Book A Sloth: India SEO Execution System
A2: Prepared 2026-10-10 for bookasloth.com. Market: India. Language: English (plus Hindi where noted).
A4: DATA SOURCES
A5: 1. Semrush 'Organic Positions' exports (India database) supplied by the user: calendly.com (359 rows, 2026-09-10), topmate.io (1,425 rows, 2026-09-10), setmore.com (2,216 rows, 2026-09-11). Volumes and KD in this workbook come only from these files.
A6: 2. Live India SERP checks (TinyFish search, location=IN, lang=en) for about 150 queries on 2026-10-10. A single non-personalised snapshot that approximates Google India; it does not capture the local pack, People Also Ask or AI Overviews.
A7: 3. Crawl of bookasloth.com sitemaps on 2026-10-10: 126 pages, 98 blog posts, 49 profession pages, 73 host profiles, 47 service pages.
A8: 4. Competitor site reviews (Zoho Bookings, Cal.com, Topmate, SuperProfile, TagMango, Exly, Graphy, Appointy, Setmore, SimplyBook, Instamojo, Razorpay, Practo) on 2026-10-10.
A10: WHAT IS NOT IN HERE
A11: No Google Search Console, GA4 or paid-tool access was available, so Book A Sloth's own impressions and rankings are unknown beyond the SERP checks (not in the top 20 for any of about 150 checked queries; about #13 for 'buffer time meaning').
A12: Keywords marked 'Unverified' have no volume or KD from any tool. They came from SERP research and forum phrasing. Validate them before treating any score as final.
A13: Competitor exports are top-N position lists, not full keyword universes. Calendly's India export covers only about 2k est. visits, so treat it as a sample.
A15: HOW TO READ THE SCORES
... A23: Blue text in the Scoring tab = editable inputs (weights, factor ratings).

Sheet Scoring
A1: Cluster scoring (weights are editable)
D2: Demand | E2: Feasibility | F2: Relevance | G2: Gap | H2: AI | I2: Sum (must be 100%)
A3: Weights → | D3: 0.25 | E3: 0.25 | F3: 0.25 | G3: 0.15 | H3: 0.1 | I3: =SUM(D3:H3)
A5: Cluster | B5: Name | C5: Pillar URL | D5: Demand (1-5) | E5: Feasibility (1-5) | F5: Relevance (1-5) | G5: Gap (1-5) | H5: AI (1-5) | I5: Score (0-100) | J5: Tier | K5: Data quality | L5: Evidence | M5: Product pages
A6: A | B6: India pricing, alternatives & comparisons | C6: /compare/best-appointment-booking-apps-india | D6: 3 | E6: 4 | F6: 5 | G6: 5 | H6: 5 | I6: =ROUND(($D$3*D6+$E$3*E6+$F$3*F6+$G$3*G6+$H$3*H6)/5*100,0) | J6: =IF(I6>=75,"Tier 1",IF(I6>=65,"Tier 2",IF(I6>=55,"Tier 3","Exclude"))) | K6: Provisional: few verified volumes; SERP evidence strong | L6: Every top-10 result for 'calendly pricing in india' quotes USD. 'topmate alternative' and 'calendly alternative india' top-10s are held by tiny .in startups (mintlink.in, ownstreet.in, zyncro.in, calenq.ai). Bottom-of-funnel and on-product. | M6: /pricing, /compare, /earnings-calculator, /features/payments
A7: B | B7: Getting paid: UPI, payment links, advance payments & GST | C7: /blog/collect-payments-from-clients-india | D7: 3 | E7: 3 | F7: 5 | G7: 4 | H7: 4 | I7: =ROUND(($D$3*D7+$E$3*E7+$F$3*F7+$G$3*G7+$H$3*H7)/5*100,0) | J7: =IF(I7>=75,"Tier 1",IF(I7>=65,"Tier 2",IF(I7>=55,"Tier 3","Exclude"))) | K7: Provisional: volumes unverified | L7: Calendly supports only Stripe/PayPal for paid events. Cal.com and Setmore users type UPI IDs into their booking pages by hand. 'Calendly razorpay integration' results are all connector pages. Razorpay's own blog covers payments but not booking. Book A Sloth's core differentiator. | M7: /features/payments, /tools/gst-calculator, /glossary/upi, /glossary/advance-payment
A8: C | B8: Client message templates (WhatsApp, SMS, Hindi) | C8: /templates | D8: 4 | E8: 4 | F8: 4 | G8: 5 | H8: 3 | I8: =ROUND(($D$3*D8+$E$3*E8+$F$3*F8+$G$3*G8+$H$3*H8)/5*100,0) | J8: =IF(I8>=75,"Tier 1",IF(I8>=65,"Tier 2",IF(I8>=55,"Tier 3","Exclude"))) | K8: Partly verified (Semrush IN) | L8: Copy-paste template pages win. Small and new Indian sites (meekhata.in, riffit.in, chatmitra, fastfee.in) rank top 10. Hindi template SERPs are filled with translate.google proxies of English pages. Setmore ranks #1-#7 for WhatsApp away-message terms at KD 12-20. | M8: /features/notifications, /glossary/whatsapp-reminder
A9: D | B9: No-shows, cancellations & booking policies | C9: /blog/how-to-reduce-no-shows | D9: 2 | E9: 3 | F9: 5 | G9: 4 | H9: 4 | I9: =ROUND(($D$3*D9+$E$3*E9+$F$3*F9+$G$3*G9+$H$3*H9)/5*100,0) | J9: =IF(I9>=75,"Tier 1",IF(I9>=65,"Tier 2",IF(I9>=55,"Tier 3","Exclude"))) | K9: Provisional: volumes unverified | L9: Policy-template SERPs include a real clinic's policy page and a Facebook post. No result gives ₹ examples or uses prepaid UPI to enforce the policy. The existing no-show cost calculator gives a tool hook. | M9: /tools/no-show-cost-calculator, /features/notifications, /features/payments, /glossary/no-show, /glossary/cancellation-policy
A10: E | B10: Interview & meeting message templates (traffic cluster) | C10: /blog/interview-calling-message | D10: 5 | E10: 4 | F10: 2 | G10: 3 | H10: 2 | I10: =ROUND(($D$3*D10+$E$3*E10+$F$3*F10+$G$3*G10+$H$3*H10)/5*100,0) | J10: =IF(I10>=75,"Tier 1",IF(I10>=65,"Tier 2",IF(I10>=55,"Tier 3","Exclude"))) | K10: Verified (Semrush IN, Sep 2026) | L10: Biggest verified demand: 110k/mo, KD 17-18. Calendly ranks only #29-34. The #1 result is a thin HRMS post, and a 1-day-old page is already ranking. Low buyer fit: HR recruiters are not the core ICP. Pages already exist, so the work is refresh only, not expansion. | M10: /features/booking-pages, /features/notifications
A11: F | B11: Scheduling concepts & glossary | C11: /glossary | D11: 4 | E11: 4 | F11: 3 | G11: 3 | H11: 5 | I11: =ROUND(($D$3*D11+$E$3*E11+$F$3*F11+$G$3*G11+$H$3*H11)/5*100,0) | J11: =IF(I11>=75,"Tier 1",IF(I11>=65,"Tier 2",IF(I11>=55,"Tier 3","Exclude"))) | K11: Verified (Semrush IN) | L11: Calendly's community and help pages rank for definitional queries (buffer time 1,300/KD20, placeholder meeting, 24/7 availability). /blog/scheduling-terms-glossary already sits at about #13 after 7 days. The 'please share anything that will help prepare for our meeting' SERP (2,400/KD21) is almost all forums and Q&A sites. Definitions are the most-cited format in AI answers. | M11: /features/availability, /features/google-calendar, /glossary/*
A12: G | B12: Start & grow an independent practice in India (playbooks + pricing guides) | C12: /blog/start-independent-practice-india | D12: 3 | E12: 3 | F12: 5 | G12: 4 | H12: 4 | I12: =ROUND(($D$3*D12+$E$3*E12+$F$3*F12+$G$3*G12+$H$3*H12)/5*100,0) | J12: =IF(I12>=75,"Tier 1",IF(I12>=65,"Tier 2",IF(I12>=55,"Tier 3","Exclude"))) | K12: Provisional: volumes unverified | L12: Practice-setup and pricing questions from Indian coaches, therapists, tutors and trainers. Book A Sloth can add original pricing data from its own bookings. Competitor guides are stale (Instamojo 2024, Exly 2021-23, Appointy 2023-24). | M12: /for/*, /be-a-sloth, /pricing, /earnings-calculator
A13: H | B13: Industry booking-software landing pages (/for/*) | C13: /appointment-booking-software | D13: 3 | E13: 2 | F13: 5 | G13: 3 | H13: 2 | I13: =ROUND(($D$3*D13+$E$3*E13+$F$3*F13+$G$3*G13+$H$3*H13)/5*100,0) | J13: =IF(I13>=75,"Tier 1",IF(I13>=65,"Tier 2",IF(I13>=55,"Tier 3","Exclude"))) | K13: Partly verified | L13: Head terms are held by Zoho, Setmore, Square and app stores, and many 'X app' queries are consumer intent. Winnable gaps: turf booking software (weak SERP), barber/makeup artist app (Setmore ranks at KD 19-20), therapists (no /for/ page yet), clinic booking software india (several small Indian sites). | M13: /for/*, /appointment-booking-software
A14: I | B14: Local marketplace pages (host profiles + profession × city) | C14: /services | D14: 4 | E14: 3 | F14: 4 | G14: 3 | H14: 1 | I14: =ROUND(($D$3*D14+$E$3*E14+$F$3*F14+$G$3*G14+$H$3*H14)/5*100,0) | J14: =IF(I14>=75,"Tier 1",IF(I14>=65,"Tier 2",IF(I14>=55,"Tier 3","Exclude"))) | K14: Verified examples (Semrush IN) + live SERP checks | L14: 100 local keywords (37,450/mo combined) where Setmore customer pages and Topmate profiles rank at median KD 15-30. Live check: amritaspa.setmore.com is #3 for 'spa in malviya nagar'. therapyroute ranks #5 for 'therapist in nagpur' with only 6 listings. Only worth doing where real host supply exists. | M14: /explore, /services/{profession}, host profiles
A15: L | B15: Booking-link how-tos (Instagram, Google, website) | C15: /blog/booking-link-instagram-bio | D15: 3 | E15: 3 | F15: 5 | G15: 3 | H15: 3 | I15: =ROUND(($D$3*D15+$E$3*E15+$F$3*F15+$G$3*G15+$H$3*H15)/5*100,0) | J15: =IF(I15>=75,"Tier 1",IF(I15>=65,"Tier 2",IF(I15>=55,"Tier 3","Exclude"))) | K15: Partly verified | L15: 'booking link for instagram' is ranked by how-to posts from Reservio (Jun 2026) and lovingbooking (Jul 2026), with no India version. Setmore ranks #3 for 'booking button' (210/KD23) with a Google Business Profile post. | M15: /features/booking-pages, /features/google-calendar
A16: K | B16: Expert & creator monetisation | C16: /blog/how-to-make-money-from-home-india | D16: 3 | E16: 3 | F16: 3 | G16: 2 | H16: 2 | I16: =ROUND(($D$3*D16+$E$3*E16+$F$3*F16+$G$3*G16+$H$3*H16)/5*100,0) | J16: =IF(I16>=75,"Tier 1",IF(I16>=65,"Tier 2",IF(I16>=55,"Tier 3","Exclude"))) | K16: Verified (Semrush IN) | L16: Topmate's homepage ranks #1 for 'how to make money from home in india' (480/KD14). Most of Topmate's blog traffic is Instagram-growth content with no buyer value. Keep the existing posts fresh; don't expand. | M16: /be-a-sloth, /features/digital-products
A17: X | B17: Excluded themes | D17: 2 | E17: 2 | F17: 1 | G17: 1 | H17: 1 | I17: =ROUND(($D$3*D17+$E$3*E17+$F$3*F17+$G$3*G17+$H$3*H17)/5*100,0) | J17: =IF(I17>=75,"Tier 1",IF(I17>=65,"Tier 2",IF(I17>=55,"Tier 3","Exclude"))) | K17: n/a | L17: Instagram follower/likes growth (Topmate's top 25k visits), HR onboarding welcome messages, student planners, Salesforce/sales ops, vaccine slots, dental/coaching ERP head terms, lawyer/CA city pages, 'superprofile alternative' (searchers want Instagram DM automation), off-ICP 'digital marketing for X' posts.
A19: Score formula: ROUND(Σ weight × factor ÷ 5 × 100). The same formula scores every page in the Article Plan tab, using these weight cells.

Sheet Article Plan
A1: Publish order | B1: First 30? | C1: Week | D1: ID | E1: Cluster | F1: Role | G1: Action | H1: Title | I1: Recommended URL | J1: Primary keyword | K1: Volume (IN) | L1: KD | M1: Supporting keywords | N1: Intent | O1: Funnel | P1: Demand | Q1: Feasibility | R1: Relevance | S1: Gap | T1: AI | U1: Score | V1: Tier | W1: Decision | X1: Angle / how it differs | Y1: SERP evidence (2026-10-10) | Z1: Product page | AA1: Links to | AB1: Research / assets
A2: 1 | B2: Yes | C2: 1 | D2: A2 | E2: A: India pricing, alternatives & comparisons | F2: Support | G2: New | H2: Calendly Pricing in India (2026): Plans in ₹, GST, Card Forex & the Free Plan Limits | I2: /compare/calendly-pricing-india | J2: calendly pricing in india | K2: Unverified | L2: n/a | M2: is calendly free, calendly free plan limits, calendly price in rupees, calendly razorpay | N2: Commercial | O2: Consideration | P2: 3 | Q2: 4 | R2: 5 | S2: 5 | T2: 5 | U2: =ROUND((Scoring!$D$3*P2+Scoring!$E$3*Q2+Scoring!$F$3*R2+Scoring!$G$3*S2+Scoring!$H$3*T2)/5*100,0) | V2: =IF(U2>=75,"Tier 1",IF(U2>=65,"Tier 2",IF(U2>=55,"Tier 3","Exclude"))) | W2: Publish now | X2: The only page that answers in INR: each USD plan converted at a dated rate, plus 18% GST (reverse charge for businesses), plus the ~3.5% card forex markup. Explains that Calendly takes payments only via Stripe/PayPal, so it has no UPI. Ends with a total-cost table. | Y2: All 10 results quote USD: calendly ×3, zoho, koalendar, withorb, cloudeagle, capterra.in, zeeg, tidycal. | Z2: /pricing, /earnings-calculator | AA2: A3, A1, A9, /pricing | AB2: Calendly pricing screenshot, RBI reference rate with date, a card forex markup source
A3: 2 | B3: Yes | C3: 1 | D3: C1 | E3: C: Client message templates (WhatsApp, SMS, Hindi) | F3: Support | G3: Refresh | H3: WhatsApp Appointment Reminder Templates: 30+ Messages for Clinics, Salons, Tutors & Coaches (English + Hindi) | I3: /blog/appointment-reminder-templates | J3: whatsapp reminder message for appointment | K3: Unverified | L3: n/a | M3: appointment reminder message, whatsapp reminder, doctor appointment message, salon appointment reminder message, daily text reminders | N3: Informational | O3: Consideration | P3: 4 | Q3: 3 | R3: 5 | S3: 4 | T3: 3 | U3: =ROUND((Scoring!$D$3*P3+Scoring!$E$3*Q3+Scoring!$F$3*R3+Scoring!$G$3*S3+Scoring!$H$3*T3)/5*100,0) | V3: =IF(U3>=75,"Tier 1",IF(U3>=65,"Tier 2",IF(U3>=55,"Tier 3","Exclude"))) | W3: Publish now | X3: Go from about 10 to 30+ templates: per-trade sets (doctor with token/OPD timing, salon festive and bridal, tutor, coach), Hindi, a reminder-timing table, and a workflow for the free WhatsApp Business app vs automation. | Y3: chati.ai (#1, about 900 words, 30 one-liners), wati and aisensy rank. Calendly community is #9 for 'whatsapp reminder' (590/KD24). Book A Sloth is not in the top 20. | Z3: /features/notifications | AA3: C0, C2, D1, /glossary/whatsapp-reminder, /features/notifications | AB3: Hindi copy check by a native speaker
A4: 3 | B4: Yes | C4: 1 | D4: C0 | E4: C: Client message templates (WhatsApp, SMS, Hindi) | F4: Pillar | G4: New | H4: Free Message Templates for Service Businesses in India (WhatsApp, SMS, Email, Hindi) | I4: /templates | J4: whatsapp message templates for business | K4: Unverified | L4: n/a | M4: business message templates, client message templates, whatsapp templates for clinic | N4: Informational | O4: Awareness | P4: 3 | Q4: 3 | R4: 4 | S4: 4 | T4: 3 | U4: =ROUND((Scoring!$D$3*P4+Scoring!$E$3*Q4+Scoring!$F$3*R4+Scoring!$G$3*S4+Scoring!$H$3*T4)/5*100,0) | V4: =IF(U4>=75,"Tier 1",IF(U4>=65,"Tier 2",IF(U4>=55,"Tier 3","Exclude"))) | W4: Publish now | X4: A hub that indexes every template page by job (confirm, remind, reschedule, cancel, get paid, thank, review) and by profession. No URL moves: existing /blog template posts stay where they are. | Y4: Hub page. It earns rankings mainly through internal links. | Z4: /features/notifications | AA4: C1, C2, C3, C4, C5, C6, C7, C8, C12, B6, E1, E3 | AB4: Hub design
A5: 4 | B5: Yes | C5: 2 | D5: A3 | E5: A: India pricing, alternatives & comparisons | F5: Comparison | G5: Consolidate | H5: Calendly Alternative for India: Get Booked and Paid via UPI (Migration Guide) | I5: /compare/calendly-alternative-india | J5: calendly alternative india | K5: Unverified | L5: n/a | M5: calendly alternative, calendly alternatives free, free calendly alternative, calendly upi | N5: Commercial | O5: Conversion | P5: 3 | Q5: 4 | R5: 5 | S5: 4 | T5: 4 | U5: =ROUND((Scoring!$D$3*P5+Scoring!$E$3*Q5+Scoring!$F$3*R5+Scoring!$G$3*S5+Scoring!$H$3*T5)/5*100,0) | V5: =IF(U5>=75,"Tier 1",IF(U5>=65,"Tier 2",IF(U5>=55,"Tier 3","Exclude"))) | W5: Publish now | X5: Merge /lp/calendly-alternative into this page. Add proof the identical 'UPI+GST' competitor pages lack: a feature matrix, a 5-step migration walkthrough with screenshots, ₹ cost maths, and a dated 'last updated'. | Y5: zoho, capterra.in, zyncro.in, swiq.services, calenq.ai and bookyourcalendar.com rank: tiny Indian startups with exact-match pages. Reddit is #5 for the global 'calendly alternative'. | Z5: /features/payments, /pricing | AA5: A2, A1, B1, /pricing | AB5: Migration screenshots; a 301 or noindex decision for the /lp page
A6: 5 | B6: Yes | C6: 2 | D6: A9 | E6: A: India pricing, alternatives & comparisons | F6: Support | G6: New | H6: Can You Take UPI Payments on Calendly? (And 3 Workarounds Indian Professionals Use) | I6: /blog/calendly-upi-payments | J6: calendly upi payment | K6: Unverified | L6: n/a | M6: calendly razorpay integration, calendly paid events india, calendly payment india | N6: Informational | O6: Consideration | P6: 2 | Q6: 4 | R6: 5 | S6: 5 | T6: 5 | U6: =ROUND((Scoring!$D$3*P6+Scoring!$E$3*Q6+Scoring!$F$3*R6+Scoring!$G$3*S6+Scoring!$H$3*T6)/5*100,0) | V6: =IF(U6>=75,"Tier 1",IF(U6>=65,"Tier 2",IF(U6>=55,"Tier 3","Exclude"))) | W6: Publish now | X6: Answer first: not natively (Stripe/PayPal only). Then compare the Zapier/Pabbly/Integrately connectors with a manual UPI-ID workflow and a native-UPI booking tool, covering cost, failure points and refunds. | Y6: 'calendly razorpay integration' returns only connector pages (Zoho Flow, Integrately, Pabbly, Zapier, Albato) plus a dev.to post on 'the Razorpay gap'. | Z6: /features/payments | AA6: A2, A3, B1, B2 | AB6: Test a Zapier flow; screenshots
A7: 6 | B7: Yes | C7: 2 | D7: F1 | E7: F: Scheduling concepts & glossary | F7: Pillar | G7: Consolidate | H7: Scheduling Glossary: 40+ Booking Terms Explained (with Indian Examples) | I7: /glossary | J7: buffer time meaning | K7: 1300 | L7: 20 | M7: buffer day, placeholder meeting meaning, 24 7 availability, lead time meaning, scheduling terms | N7: Informational | O7: Awareness | P7: 4 | Q7: 4 | R7: 3 | S7: 3 | T7: 5 | U7: =ROUND((Scoring!$D$3*P7+Scoring!$E$3*Q7+Scoring!$F$3*R7+Scoring!$G$3*S7+Scoring!$H$3*T7)/5*100,0) | V7: =IF(U7>=75,"Tier 1",IF(U7>=65,"Tier 2",IF(U7>=55,"Tier 3","Exclude"))) | W7: Publish now | X7: Make /glossary the single home for definitions. 301 /blog/scheduling-terms-glossary into /glossary/buffer-time, carrying its content. Expand every entry to 250-500 words with a 1-sentence answer box, an example and a 'related terms' block, and add DefinedTerm schema. | Y7: /blog/scheduling-terms-glossary is about #13 for 'buffer time meaning' (1,300/KD20). Calendly help ranks #18. | Z7: /features/availability | AA7: F4, D3, /features/availability | AB7: 301 map; schema
A8: 7 | B8: Yes | C8: 3 | D8: F2 | E8: F: Scheduling concepts & glossary | F8: Support | G8: New | H8: 'Please Share Anything That Will Help Prepare for Our Meeting': What to Write (30 Examples) | I8: /blog/please-share-anything-that-will-help-prepare-for-our-meeting | J8: please share anything that will help prepare for our meeting | K8: 2400 | L8: 21 | M8: what to write in meeting notes before call, booking form notes examples, what to write when booking a consultation | N8: Informational | O8: Awareness | P8: 4 | Q8: 5 | R8: 3 | S8: 5 | T8: 4 | U8: =ROUND((Scoring!$D$3*P8+Scoring!$E$3*Q8+Scoring!$F$3*R8+Scoring!$G$3*S8+Scoring!$H$3*T8)/5*100,0) | V8: =IF(U8>=75,"Tier 1",IF(U8>=65,"Tier 2",IF(U8>=55,"Tier 3","Exclude"))) | W8: Publish now | X8: Example answers by situation (job interview, sales demo, therapy intake, consultant call). Then flip to the host side: which intake questions to ask instead. | Y8: Almost all forums and Q&A (reddit r/recruiting, community.calendly, brainly, chegg). Calendly community ranks #3 (2,400/KD21). | Z8: /glossary/intake-form, /features/booking-pages | AA8: F3, C7, /glossary/intake-form
A9: 8 | B9: Yes | C9: 3 | D9: A4 | E9: A: India pricing, alternatives & comparisons | F9: Support | G9: New | H9: Topmate Commission & Fees Explained (2026): What You Actually Keep per ₹1,000 | I9: /compare/topmate-commission | J9: topmate commission | K9: Unverified | L9: n/a | M9: topmate charges, topmate pricing, topmate fees, topmate payout | N9: Commercial | O9: Consideration | P9: 2 | Q9: 4 | R9: 5 | S9: 5 | T9: 5 | U9: =ROUND((Scoring!$D$3*P9+Scoring!$E$3*Q9+Scoring!$F$3*R9+Scoring!$G$3*S9+Scoring!$H$3*T9)/5*100,0) | V9: =IF(U9>=75,"Tier 1",IF(U9>=65,"Tier 2",IF(U9>=55,"Tier 3","Exclude"))) | W9: Publish now | X9: A worked example: 10% own-link and 20% marketplace fee (per topmate.io), plus the payment gateway fee, plus GST on the fee. Embeds a calculator (see A11). Factual and neutral, with sources. | Y9: The top 10 includes topmate's own pages, linkedin, an eximpe blog, medium, reddit and swadeshiapps. Small explainer sites rank. | Z9: /earnings-calculator, /pricing | AA9: A5, A11, /glossary/commission, /glossary/platform-fee | AB9: Topmate pricing page capture (dated); calculator
A10: 9 | B10: Yes | C10: 3 | D10: A11 | E10: A: India pricing, alternatives & comparisons | F10: Tool | G10: Refresh | H10: Booking Platform Fee Calculator (Topmate, Calendly, SuperProfile, Book A Sloth) | I10: /earnings-calculator | J10: booking platform fee calculator | K10: Unverified | L10: n/a | M10: topmate fee calculator, commission calculator for creators | N10: Commercial | O10: Consideration | P10: 2 | Q10: 4 | R10: 5 | S10: 4 | T10: 4 | U10: =ROUND((Scoring!$D$3*P10+Scoring!$E$3*Q10+Scoring!$F$3*R10+Scoring!$G$3*S10+Scoring!$H$3*T10)/5*100,0) | V10: =IF(U10>=75,"Tier 1",IF(U10>=65,"Tier 2",IF(U10>=55,"Tier 3","Exclude"))) | W10: Publish now | X10: Extend the existing /earnings-calculator to compare platforms side by side, and link it from A2, A4 and A5. A calculator is a citable, linkable asset. | Y10: No calculator ranks for these fee queries. | Z10: /pricing | AA10: A4, A5, A2 | AB10: Dev work: fee inputs per platform with dated sources
A11: 10 | B11: Yes | C11: 3 | D11: F4 | E11: F: Scheduling concepts & glossary | F11: Glossary | G11: New | H11: New glossary entries: placeholder meeting, recurring meeting, soft booking, direct booking, preferred time, 24/7 availability, internal vs external meeting | I11: /glossary/{term} | J11: placeholder meeting | K11: 170 | L11: 20 | M11: placeholder meeting meaning, recurring meeting, soft booking, direct booking, preferred time, internal meeting | N11: Informational | O11: Awareness | P11: 3 | Q11: 4 | R11: 3 | S11: 3 | T11: 5 | U11: =ROUND((Scoring!$D$3*P11+Scoring!$E$3*Q11+Scoring!$F$3*R11+Scoring!$G$3*S11+Scoring!$H$3*T11)/5*100,0) | V11: =IF(U11>=75,"Tier 1",IF(U11>=65,"Tier 2",IF(U11>=55,"Tier 3","Exclude"))) | W11: Publish now | X11: Short definitional entries, each targeting a verified low-KD term, all under /glossary. One URL per term, no blog duplicates. | Y11: Calendly community and help pages rank for these (placeholder 390/KD24, recurring 210/KD19, soft booking 210/KD16, direct booking 210/KD20). | Z11: /features/availability | AA11: F1
A12: 11 | B12: Yes | C12: 4 | D12: A5 | E12: A: India pricing, alternatives & comparisons | F12: Comparison | G12: Consolidate | H12: Topmate Alternative for Consultants, Therapists & Coaches (0% Commission) | I12: /compare/topmate-alternative | J12: topmate alternative | K12: Unverified | L12: n/a | M12: topmate alternatives, topmate vs book a sloth, topmate competitors | N12: Commercial | O12: Conversion | P12: 3 | Q12: 4 | R12: 5 | S12: 4 | T12: 4 | U12: =ROUND((Scoring!$D$3*P12+Scoring!$E$3*Q12+Scoring!$F$3*R12+Scoring!$G$3*S12+Scoring!$H$3*T12)/5*100,0) | V12: =IF(U12>=75,"Tier 1",IF(U12>=65,"Tier 2",IF(U12>=55,"Tier 3","Exclude"))) | W12: Publish now | X12: 301 /blog/topmate-alternative and /lp/topmate-vs-bookasloth here. Aim it at professionals (therapists, consultants) rather than creators. Include a ₹ fee comparison and a profile-migration walkthrough. | Y12: adplist, mintlink.in (19 Aug 2026), an x.com tweet, virtup, ownstreet.in and kreato.co.in rank. Tiny Indian sites dominate. | Z12: /pricing, /features/booking-pages | AA12: A4, A10, A1, /earnings-calculator | AB12: Fee comparison table; 301 map
A13: 12 | B13: Yes | C13: 4 | D13: B1 | E13: B: Getting paid: UPI, payment links, advance payments & GST | F13: Pillar | G13: New | H13: How to Collect Payments from Clients in India: UPI, Payment Links & Advance Booking (2026 Guide) | I13: /blog/collect-payments-from-clients-india | J13: how to collect payment from clients online india | K13: Unverified | L13: n/a | M13: how to accept upi payments for business, payment link for freelancers, how to take online consultation fees, accept payment without website | N13: Informational | O13: Consideration | P13: 3 | Q13: 4 | R13: 5 | S13: 4 | T13: 4 | U13: =ROUND((Scoring!$D$3*P13+Scoring!$E$3*Q13+Scoring!$F$3*R13+Scoring!$G$3*S13+Scoring!$H$3*T13)/5*100,0) | V13: =IF(U13>=75,"Tier 1",IF(U13>=65,"Tier 2",IF(U13>=55,"Tier 3","Exclude"))) | W13: Publish now | X13: Compares UPI ID/QR, payment links, gateway checkout and pay-at-booking on fees, auto-confirmation, refunds and GST invoices. Includes a decision table by profession. Razorpay's blog covers payment links but never booking. | Y13: Fintech blogs (Razorpay, Cashfree, Instamojo) and Quora threads rank. Instamojo titles still say 2024. | Z13: /features/payments | AA13: B2, B3, B4, B6, A9, /glossary/upi, /glossary/payment-gateway | AB13: Fee table with sources (Razorpay, Cashfree, PhonePe PG); screenshots of the Book A Sloth pay-at-booking flow
A14: 13 | B14: Yes | C14: 4 | D14: B6 | E14: B: Getting paid: UPI, payment links, advance payments & GST | F14: Support | G14: Refresh | H14: How to Ask a Client for Payment Politely (Email, WhatsApp & Call Scripts) | I14: /blog/how-to-ask-client-for-payment-politely | J14: how to ask client for payment | K14: 720 | L14: 15 | M14: how to ask client for payment politely, payment follow up email, polite payment reminder email | N14: Informational | O14: Awareness | P14: 3 | Q14: 3 | R14: 4 | S14: 3 | T14: 3 | U14: =ROUND((Scoring!$D$3*P14+Scoring!$E$3*Q14+Scoring!$F$3*R14+Scoring!$G$3*S14+Scoring!$H$3*T14)/5*100,0) | V14: =IF(U14>=75,"Tier 1",IF(U14>=65,"Tier 2",IF(U14>=55,"Tier 3","Exclude"))) | W14: Publish now | X14: Add a phone script, a 'pause work' template and the MSME Act 45-day payment rule. It is already the only India-specific result. | Y14: #1 is neat.com (2022, US). Calendly community ranks #15 for 'how to ask client for payment' (720/KD15). Book A Sloth is not in the top 20. | Z14: /features/payments | AA14: C4, B1, B2 | AB14: MSME Act section reference
A15: 14 | B15: Yes | C15: 5 | D15: C4 | E15: C: Client message templates (WhatsApp, SMS, Hindi) | F15: Support | G15: New | H15: Payment Reminder Messages for Clients: WhatsApp & Email Templates (Polite to Firm) | I15: /blog/payment-reminder-message | J15: payment reminder message | K15: Unverified | L15: n/a | M15: payment reminder message for client, payment due reminder whatsapp, overdue payment message | N15: Informational | O15: Consideration | P15: 3 | Q15: 4 | R15: 5 | S15: 4 | T15: 3 | U15: =ROUND((Scoring!$D$3*P15+Scoring!$E$3*Q15+Scoring!$F$3*R15+Scoring!$G$3*S15+Scoring!$H$3*T15)/5*100,0) | V15: =IF(U15>=75,"Tier 1",IF(U15>=65,"Tier 2",IF(U15>=55,"Tier 3","Exclude"))) | W15: Publish now | X15: Sequenced templates (before due, due day, +3, +7, final), each with a UPI link line. Separate from B6 because its SERP is template pages, not how-to guides. | Y15: meekhata.in (small Indian site) is #1 and riffit.in #6. | Z15: /features/payments | AA15: B6, C5, C12, B1
A16: 15 | B16: Yes | C16: 5 | D16: C13 | E16: C: Client message templates (WhatsApp, SMS, Hindi) | F16: Sub-pillar | G16: New | H16: How to Manage Appointments on WhatsApp (and When a Booking Link Saves You Hours) | I16: /blog/manage-appointments-on-whatsapp | J16: how to manage appointments on whatsapp | K16: Unverified | L16: n/a | M16: whatsapp appointment booking, online booking vs whatsapp booking, whatsapp booking system for clinic, whatsapp business for doctors, does whatsapp have appointment booking | N16: Informational | O16: Consideration | P16: 3 | Q16: 3 | R16: 5 | S16: 5 | T16: 4 | U16: =ROUND((Scoring!$D$3*P16+Scoring!$E$3*Q16+Scoring!$F$3*R16+Scoring!$G$3*S16+Scoring!$H$3*T16)/5*100,0) | V16: =IF(U16>=75,"Tier 1",IF(U16>=65,"Tier 2",IF(U16>=55,"Tier 3","Exclude"))) | W16: Publish now | X16: An honest comparison of manual WhatsApp, a WhatsApp API bot and a booking link plus WhatsApp reminders, with time and no-show costs. Includes the hidden costs of the WhatsApp Business API (per-conversation pricing). | Y16: WhatsApp API vendors dominate (infobip, gallabox, aisensy, respond.io). A Reddit r/indianstartups thread on WhatsApp scheduling ranks #5. | Z16: /features/notifications, /features/booking-pages | AA16: C1, C6, D1, A1 | AB16: Book A Sloth host interview or case study
A17: 16 | B17: Yes | C17: 5 | D17: E1 | E17: E: Interview & meeting message templates (traffic cluster) | F17: Pillar | G17: Refresh | H17: Interview Calling Message: 25+ Templates (WhatsApp, SMS, Email, Hindi) | I17: /blog/interview-calling-message | J17: interview calling message | K17: 110000 | L17: 18 | M17: interview call message, interview invitation message, message for interview call, interview invitation sms, interview mail format, invitation for interview text message | N17: Informational | O17: Awareness | P17: 5 | Q17: 4 | R17: 2 | S17: 3 | T17: 2 | U17: =ROUND((Scoring!$D$3*P17+Scoring!$E$3*Q17+Scoring!$F$3*R17+Scoring!$G$3*S17+Scoring!$H$3*T17)/5*100,0) | V17: =IF(U17>=75,"Tier 1",IF(U17>=65,"Tier 2",IF(U17>=55,"Tier 3","Exclude"))) | W17: Publish now | X17: Add a Hindi/Hinglish WhatsApp version, a walk-in template with a documents list (Aadhaar, photos), a reminder template, and a 'book your slot' link template that shows the product in use. | Y17: savvyhrms (#1, thin), in.indeed, homerun and hyring rank; prajjo.com is 1 day old. Calendly ranks #29-34. Book A Sloth is not in the top 20. | Z17: /features/booking-pages | AA17: E2, E5, C1
A18: 17 | B18: Yes | C18: 6 | D18: G1 | E18: G: Start & grow an independent practice in India (playbooks + pricing guides) | F18: Pillar | G18: New | H18: How Much to Charge for a Consultation in India (2026): ₹ Rates by Profession | I18: /blog/consultation-fees-india | J18: how much to charge for consultation india | K18: Unverified | L18: n/a | M18: consultation charges in india, online consultation fees, how much to charge per hour consultant india, consultation fee kitna lena chahiye | N18: Informational | O18: Consideration | P18: 3 | Q18: 5 | R18: 5 | S18: 5 | T18: 5 | U18: =ROUND((Scoring!$D$3*P18+Scoring!$E$3*Q18+Scoring!$F$3*R18+Scoring!$G$3*S18+Scoring!$H$3*T18)/5*100,0) | V18: =IF(U18>=75,"Tier 1",IF(U18>=65,"Tier 2",IF(U18>=55,"Tier 3","Exclude"))) | W18: Publish now | X18: Original research: the median listed price per profession on Book A Sloth plus a small host survey, shown with ranges, sample sizes and the date. This is the cluster's most citable asset (an India Service Pricing Index). Refresh every quarter. | Y18: Dominated by UGC: Facebook ×2, Instagram, Reddit ×2, Quora ×2. Rated High feasibility. | Z18: /pricing, /earnings-calculator | AA18: G3, G6, G8, G9, G4c, A11 | AB18: Book A Sloth listings data export (n by profession; publish only professions with n≥20)
A19: 18 | B19: Yes | C19: 6 | D19: G3 | E19: G: Start & grow an independent practice in India (playbooks + pricing guides) | F19: Support | G19: New | H19: How Much Should a Personal Trainer Charge in India? Session, Monthly & Online Rate Card | I19: /blog/personal-trainer-charges-india | J19: how much do personal trainers charge in india | K19: Unverified | L19: n/a | M19: personal trainer fees per month india, online personal trainer charges, personal trainer price per session delhi | N19: Informational | O19: Consideration | P19: 2 | Q19: 5 | R19: 5 | S19: 5 | T19: 4 | U19: =ROUND((Scoring!$D$3*P19+Scoring!$E$3*Q19+Scoring!$F$3*R19+Scoring!$G$3*S19+Scoring!$H$3*T19)/5*100,0) | V19: =IF(U19>=75,"Tier 1",IF(U19>=65,"Tier 2",IF(U19>=55,"Tier 3","Exclude"))) | W19: Publish now | X19: The trainer's side of a query dominated by client-side Reddit and Quora answers. City tiers, package maths and UPI subscriptions. | Y19: Reddit ×2 and Quora ×3 dominate. Rated High feasibility. | Z19: /for/fitness | AA19: G1, /blog/how-to-become-freelance-personal-trainer, /for/fitness | AB19: Book A Sloth trainer price data
A20: 19 | B20: Yes | C20: 6 | D20: C6 | E20: C: Client message templates (WhatsApp, SMS, Hindi) | F20: Support | G20: New | H20: WhatsApp Business Away Message: 40 Templates + How to Set It Up (Holidays, After-Hours, Busy) | I20: /blog/whatsapp-business-away-message | J20: away message for business | K20: 480 | L20: 12 | M20: away message whatsapp, best away message for whatsapp business, away message for business whatsapp, away from whatsapp, whatsapp business away message | N20: Informational | O20: Awareness | P20: 3 | Q20: 4 | R20: 4 | S20: 4 | T20: 3 | U20: =ROUND((Scoring!$D$3*P20+Scoring!$E$3*Q20+Scoring!$F$3*R20+Scoring!$G$3*S20+Scoring!$H$3*T20)/5*100,0) | V20: =IF(U20>=75,"Tier 1",IF(U20>=65,"Tier 2",IF(U20>=55,"Tier 3","Exclude"))) | W20: Publish now | X20: Setup steps plus templates by trade and by Indian holiday (Diwali, Sunday closed), each ending with a booking link so the away message keeps taking bookings. | Y20: faq.whatsapp, getkanal, kommunicate and trengo rank. Setmore's blog ranks #1 for 'away message whatsapp' (320/KD20) and #7 for 'away message for business' (480/KD12). | Z20: /features/booking-pages | AA20: C13, C0, L1 | AB20: Setup screenshots
A21: 20 | B21: Yes | C21: 7 | D21: B2 | E21: B: Getting paid: UPI, payment links, advance payments & GST | F21: Support | G21: New | H21: How to Take Advance Payment for Appointments (Without Chasing UPI Screenshots) | I21: /blog/advance-payment-for-appointments | J21: advance payment for appointment | K21: Unverified | L21: n/a | M21: booking deposit, prepaid appointments, advance booking payment, how to take booking amount | N21: Informational | O21: Consideration | P21: 2 | Q21: 4 | R21: 5 | S21: 5 | T21: 4 | U21: =ROUND((Scoring!$D$3*P21+Scoring!$E$3*Q21+Scoring!$F$3*R21+Scoring!$G$3*S21+Scoring!$H$3*T21)/5*100,0) | V21: =IF(U21>=75,"Tier 1",IF(U21>=65,"Tier 2",IF(U21>=55,"Tier 3","Exclude"))) | W21: Publish now | X21: Covers deposit vs full prepay, how much to charge by profession, policy wording and refunds. Link to the build-in-public story /blog/advance-payments-without-the-screenshot-dance as first-hand proof. | Y21: Not checked; no strong ranking page was observed for related queries. | Z21: /features/payments | AA21: B1, D2, D1, /glossary/advance-payment | AB21: Book A Sloth data: no-show rate prepaid vs unpaid (if sample allows)
A22: 21 | B22: Yes | C22: 7 | D22: D2 | E22: D: No-shows, cancellations & booking policies | F22: Template | G22: New | H22: Cancellation & No-Show Policy Templates for Appointments (₹ Examples for Clinics, Coaches & Salons) | I22: /templates/cancellation-policy | J22: cancellation policy for appointments | K22: Unverified | L22: n/a | M22: no show policy template, late cancellation fee, cancellation policy template, refund policy for coaching | N22: Informational | O22: Consideration | P22: 2 | Q22: 4 | R22: 5 | S22: 4 | T22: 4 | U22: =ROUND((Scoring!$D$3*P22+Scoring!$E$3*Q22+Scoring!$F$3*R22+Scoring!$G$3*S22+Scoring!$H$3*T22)/5*100,0) | V22: =IF(U22>=75,"Tier 1",IF(U22>=65,"Tier 2",IF(U22>=55,"Tier 3","Exclude"))) | W22: Publish now | X22: One page for both SERPs (no-show and cancellation policy results overlap: koalendar, acuity and appointmentreminder rank for both). Copy-ready policies with ₹ fees, per-trade versions, and how prepaid UPI enforces them. | Y22: trilife.in (a real Indian clinic policy page) and a Facebook post rank. thebadtherapist.coach ranks for 'no show policy template'. | Z22: /features/payments | AA22: D1, B2, C3, /glossary/cancellation-policy | AB22: Consumer-law note for refunds
A23: 22 | B23: Yes | C23: 7 | D23: C3 | E23: C: Client message templates (WhatsApp, SMS, Hindi) | F23: Support | G23: New | H23: Appointment Cancellation & Reschedule Messages: Templates for Businesses and Clients | I23: /blog/appointment-cancellation-reschedule-message | J23: appointment cancellation message | K23: Unverified | L23: n/a | M23: reschedule meeting message, reschedule appointment, cancel appointment, rebook appointment, reschedule meeting | N23: Informational | O23: Consideration | P23: 3 | Q23: 4 | R23: 5 | S23: 4 | T23: 3 | U23: =ROUND((Scoring!$D$3*P23+Scoring!$E$3*Q23+Scoring!$F$3*R23+Scoring!$G$3*S23+Scoring!$H$3*T23)/5*100,0) | V23: =IF(U23>=75,"Tier 1",IF(U23>=65,"Tier 2",IF(U23>=55,"Tier 3","Exclude"))) | W23: Publish now | X23: Covers both sides (business-initiated and client-initiated), refund/UPI wording, short WhatsApp versions, and rescheduling via link. | Y23: The SERP is scattered, with help pages ranking (medfar, findyourally). Setmore support ranks #12 for 'reschedule appointment' (1,000/KD25). | Z23: /features/notifications | AA23: D2, C2, /glossary/reschedule
A24: 23 | B24: Yes | C24: 8 | D24: D1 | E24: D: No-shows, cancellations & booking policies | F24: Pillar | G24: New | H24: How to Reduce No-Shows: A Playbook for Indian Clinics, Coaches, Tutors & Salons | I24: /blog/how-to-reduce-no-shows | J24: how to reduce no shows | K24: Unverified | L24: n/a | M24: how to reduce no shows in clinic, no show appointments, reduce missed appointments, patient no show | N24: Informational | O24: Consideration | P24: 2 | Q24: 3 | R24: 5 | S24: 4 | T24: 4 | U24: =ROUND((Scoring!$D$3*P24+Scoring!$E$3*Q24+Scoring!$F$3*R24+Scoring!$G$3*S24+Scoring!$H$3*T24)/5*100,0) | V24: =IF(U24>=75,"Tier 1",IF(U24>=65,"Tier 2",IF(U24>=55,"Tier 3","Exclude"))) | W24: Publish now | X24: Original data: Book A Sloth no-show rate by reminder type and prepaid vs unpaid. Includes a cost calculator embed, a reminder cadence and policy wording. | Y24: Not fully checked. US SaaS blogs are expected to dominate; this page differentiates on India data. | Z24: /tools/no-show-cost-calculator, /features/notifications | AA24: D2, C1, B2, /tools/no-show-cost-calculator, /glossary/no-show | AB24: Book A Sloth data pull: no-show rates (min sample n≥200 bookings)
A25: 24 | B25: Yes | C25: 8 | D25: G0 | E25: G: Start & grow an independent practice in India (playbooks + pricing guides) | F25: Pillar | G25: New | H25: How to Start an Online Consultation Practice in India (Coaches, Therapists, Tutors, Trainers): Setup, Pricing, Payments & Rules | I25: /blog/start-online-consultation-practice-india | J25: how to start online consultation business | K25: Unverified | L25: n/a | M25: how to start coaching business in india, start online coaching india, how to start consulting business in india, 1:1 coaching business india | N25: Informational | O25: Awareness | P25: 3 | Q25: 4 | R25: 5 | S25: 4 | T25: 4 | U25: =ROUND((Scoring!$D$3*P25+Scoring!$E$3*Q25+Scoring!$F$3*R25+Scoring!$G$3*S25+Scoring!$H$3*T25)/5*100,0) | V25: =IF(U25>=75,"Tier 1",IF(U25>=65,"Tier 2",IF(U25>=55,"Tier 3","Exclude"))) | W25: Publish now | X25: A 1:1 practitioner version of a SERP that reads 'coaching' as tuition institutes. Steps: offer, ₹ pricing, booking page, UPI collection, GST threshold, WhatsApp reminders, policies. Links out to every profession playbook. | Y25: Quora ×2, Reddit ×2, linkedin pulse and registerkaro rank; generic or US-based results. Rated High feasibility. | Z25: /be-a-sloth, /features/booking-pages | AA25: G1, G2, G4, G5, G6, B1, D2 | AB25: Host interviews (2-3 quotes)
A26: 25 | B26: Yes | C26: 8 | D26: C5 | E26: C: Client message templates (WhatsApp, SMS, Hindi) | F26: Support | G26: New | H26: Tuition Fee Reminder Messages for Tutors & Coaching Classes (Hindi + English) | I26: /blog/tuition-fee-reminder-message | J26: tuition fee reminder message | K26: Unverified | L26: n/a | M26: fee reminder message, fee reminder message in hindi, monthly fee reminder for students | N26: Informational | O26: Consideration | P26: 3 | Q26: 5 | R26: 4 | S26: 4 | T26: 3 | U26: =ROUND((Scoring!$D$3*P26+Scoring!$E$3*Q26+Scoring!$F$3*R26+Scoring!$G$3*S26+Scoring!$H$3*T26)/5*100,0) | V26: =IF(U26>=75,"Tier 1",IF(U26>=65,"Tier 2",IF(U26>=55,"Tier 3","Exclude"))) | W26: Publish now | X26: Private tutor and coaching-class angle (the SERP is school-focused): monthly batch fees, UPI QR, parent-friendly Hindi. | Y26: Q&A sites (askfilo, brainly.in) and small Indian sites (fastfee.in, shreetripada) rank. Rated High feasibility. | Z26: /for/tutors | AA26: C4, /for/tutors, G4
A27: 26 | B27: Yes | C27: 9 | D27: G2 | E27: G: Start & grow an independent practice in India (playbooks + pricing guides) | F27: Support | G27: New | H27: How to Start a Private Practice as a Psychologist or Counsellor in India (Operations Guide) | I27: /blog/start-private-practice-psychologist-india | J27: how to start private practice psychologist india | K27: Unverified | L27: n/a | M27: how to start a counselling practice in india, how to get clients as a new psychologist in india, therapist fees in india, do counsellors need shop and establishment licence | N27: Informational | O27: Consideration | P27: 2 | Q27: 4 | R27: 5 | S27: 5 | T27: 4 | U27: =ROUND((Scoring!$D$3*P27+Scoring!$E$3*Q27+Scoring!$F$3*R27+Scoring!$G$3*S27+Scoring!$H$3*T27)/5*100,0) | V27: =IF(U27>=75,"Tier 1",IF(U27>=65,"Tier 2",IF(U27>=55,"Tier 3","Exclude"))) | W27: Publish now | X27: Covers the operations that qualification-focused pages skip: intake forms, confidential booking, fee collection, WhatsApp boundaries, cancellation policy, RCI note. | Y27: Reddit r/Psychology_India ×2, LinkedIn ×2, shoolini, lifehetu. Rated High feasibility. | Z27: /for/therapists | AA27: H5, F3, D2, G1 | AB27: Reviewed by a practising RCI-registered psychologist
A28: 27 | B28: Yes | C28: 9 | D28: H5 | E28: H: Industry booking-software landing pages (/for/*) | F28: Landing | G28: New | H28: Booking & Payments for Psychologists and Therapists in India (Private, Prepaid Sessions) | I28: /for/therapists | J28: therapist booking software india | K28: Unverified | L28: n/a | M28: practice management for therapists india, online counselling booking, psychologist appointment software | N28: Commercial | O28: Conversion | P28: 2 | Q28: 3 | R28: 5 | S28: 4 | T28: 3 | U28: =ROUND((Scoring!$D$3*P28+Scoring!$E$3*Q28+Scoring!$F$3*R28+Scoring!$G$3*S28+Scoring!$H$3*T28)/5*100,0) | V28: =IF(U28>=75,"Tier 1",IF(U28>=65,"Tier 2",IF(U28>=55,"Tier 3","Exclude"))) | W28: Publish now | X28: A core ICP with no /for page today. Covers privacy, intake forms, prepaid sessions, recurring weekly slots and video links. | Y28: Small Indian sites rank (protherapy.in, practipal.in, psychdesk.in, therasoft.in). | Z28: /for/therapists | AA28: F3, D2, G2 | AB28: RCI-registration and privacy copy reviewed
A29: 28 | B29: Yes | C29: 9 | D29: G4 | E29: G: Start & grow an independent practice in India (playbooks + pricing guides) | F29: Support | G29: New | H29: How to Start Online Tuition in India (2026): Fees, Batches, UPI Collection & Parent Reminders | I29: /blog/how-to-start-online-tuition | J29: how to start online tuition | K29: Unverified | L29: n/a | M29: how to start online tuition from home, online tuition business india, online tuition classes setup | N29: Informational | O29: Consideration | P29: 3 | Q29: 4 | R29: 5 | S29: 4 | T29: 3 | U29: =ROUND((Scoring!$D$3*P29+Scoring!$E$3*Q29+Scoring!$F$3*R29+Scoring!$G$3*S29+Scoring!$H$3*T29)/5*100,0) | V29: =IF(U29>=75,"Tier 1",IF(U29>=65,"Tier 2",IF(U29>=55,"Tier 3","Exclude"))) | W29: Publish now | X29: Current results date from 2021-2023. Covers batches, a demo-class booking link, monthly UPI fees, a fee-reminder cadence and parent WhatsApp etiquette. | Y29: YouTube, urbantution, razorpay learn (2021), Quora, mydukaan (2023). Rated High feasibility. | Z29: /for/tutors | AA29: C5, G4b, G4c, H8
A30: 29 | B30: Yes | C30: 10 | D30: G6 | E30: G: Start & grow an independent practice in India (playbooks + pricing guides) | F30: Support | G30: New | H30: How to Price Coaching Services in India (₹ Packages, Retainers & UPI Subscriptions) | I30: /blog/how-to-price-coaching-services-india | J30: how to price coaching services | K30: Unverified | L30: n/a | M30: life coach fees in india, how much do life coaches charge in india, coaching packages pricing, career coach fees india | N30: Informational | O30: Consideration | P30: 2 | Q30: 4 | R30: 5 | S30: 5 | T30: 4 | U30: =ROUND((Scoring!$D$3*P30+Scoring!$E$3*Q30+Scoring!$F$3*R30+Scoring!$G$3*S30+Scoring!$H$3*T30)/5*100,0) | V30: =IF(U30>=75,"Tier 1",IF(U30>=65,"Tier 2",IF(U30>=55,"Tier 3","Exclude"))) | W30: Publish now | X30: Every ranking page quotes USD. Rupee benchmarks, package design and the effective hourly rate after platform fees. | Y30: instituteofcoaching, coactive, paperbell (all US). Rated High feasibility with an India modifier. | Z30: /for/life-coaches | AA30: G1, G7, A11 | AB30: Coach pricing data
A31: 30 | B31: Yes | C31: 10 | D31: L1 | E31: L: Booking-link how-tos (Instagram, Google, website) | F31: Pillar | G31: New | H31: How to Add a Booking Link to Your Instagram Bio (and Get Paid Before the Session) | I31: /blog/booking-link-instagram-bio | J31: booking link for instagram | K31: Unverified | L31: n/a | M31: instagram booking button, how to add book now button on instagram, link in bio for coaches, link in bio that takes payments | N31: Informational | O31: Consideration | P31: 3 | Q31: 4 | R31: 5 | S31: 4 | T31: 3 | U31: =ROUND((Scoring!$D$3*P31+Scoring!$E$3*Q31+Scoring!$F$3*R31+Scoring!$G$3*S31+Scoring!$H$3*T31)/5*100,0) | V31: =IF(U31>=75,"Tier 1",IF(U31>=65,"Tier 2",IF(U31>=55,"Tier 3","Exclude"))) | W31: Publish now | X31: An Indian version with screenshots: bio link, Instagram's 'Book' action button, a WhatsApp handoff and UPI prepay. | Y31: setmore, help.instagram, square, koalendar, linktr.ee, reservio (Jun 2026) and lovingbooking (Jul 2026) rank: small how-to posts. | Z31: /features/booking-pages | AA31: L3, C6, A1 | AB31: Instagram screenshots
A32: 31 | C32: 10 | D32: H1 | E32: H: Industry booking-software landing pages (/for/*) | F32: Landing | G32: Refresh | H32: Turf Booking Software: Online Slot Booking + UPI Advance, 0% Commission | I32: /for/sports-turf | J32: turf booking software | K32: Unverified | L32: n/a | M32: turf booking system, box cricket booking software, turf management software | N32: Commercial | O32: Conversion | P32: 2 | Q32: 5 | R32: 5 | S32: 4 | T32: 2 | U32: =ROUND((Scoring!$D$3*P32+Scoring!$E$3*Q32+Scoring!$F$3*R32+Scoring!$G$3*S32+Scoring!$H$3*T32)/5*100,0) | V32: =IF(U32>=75,"Tier 1",IF(U32>=65,"Tier 2",IF(U32>=55,"Tier 3","Exclude"))) | W32: Publish now | X32: Peak/off-peak pricing, UPI advance, WhatsApp booking link and zero commission vs marketplaces (Playo, Khelomore). | Y32: A very weak SERP: turfbox.in, pitchbooking, sigosoft, a dayschedule forum post and a cyberzio guide (1 Oct 2026). Rated High feasibility. | Z32: /for/sports-turf | AA32: A1, B2 | AB32: Turf owner case study
A33: 32 | C33: 11 | D33: A1 | E33: A: India pricing, alternatives & comparisons | F33: Pillar | G33: New | H33: Best Appointment Booking Apps in India (2026): ₹ Pricing, UPI & WhatsApp Compared | I33: /compare/best-appointment-booking-apps-india | J33: appointment scheduling app india | K33: Unverified | L33: n/a | M33: free appointment booking app india, appointment booking app india, best scheduling app india | N33: Commercial | O33: Consideration | P33: 3 | Q33: 3 | R33: 5 | S33: 4 | T33: 5 | U33: =ROUND((Scoring!$D$3*P33+Scoring!$E$3*Q33+Scoring!$F$3*R33+Scoring!$G$3*S33+Scoring!$H$3*T33)/5*100,0) | V33: =IF(U33>=75,"Tier 1",IF(U33>=65,"Tier 2",IF(U33>=55,"Tier 3","Exclude"))) | W33: Publish now | X33: An honest list that includes competitors (Zoho, Calendly, Topmate, Setmore, Cal.com, Picktime, Appointy, Book A Sloth). One table: ₹ monthly cost incl. 18% GST, UPI support, WhatsApp reminders, commission, GST invoice. Methodology box plus a 'last tested' date. | Y33: A US Square page is #1 for 'free appointment booking app india'. zapier, simplybook and zoho also rank. No result shows ₹ pricing or UPI support. | Z33: /pricing, /features/payments | AA33: A2, A3, A5, B1, C13, /pricing | AB33: A fresh test account on each tool; screenshots; a ₹ conversion with the date; a pricing-check log
A34: 33 | C34: 11 | D34: G8 | E34: G: Start & grow an independent practice in India (playbooks + pricing guides) | F34: Support | G34: New | H34: Doctor Consultation Fees in India: How to Set Yours (Specialty, City, Follow-Up Rules) | I34: /blog/doctor-consultation-fee-india | J34: consultation fee for doctors in india | K34: Unverified | L34: n/a | M34: how much should a new doctor charge for consultation, follow up consultation fee rules, online consultation fee for doctors | N34: Informational | O34: Consideration | P34: 3 | Q34: 4 | R34: 4 | S34: 4 | T34: 4 | U34: =ROUND((Scoring!$D$3*P34+Scoring!$E$3*Q34+Scoring!$F$3*R34+Scoring!$G$3*S34+Scoring!$H$3*T34)/5*100,0) | V34: =IF(U34>=75,"Tier 1",IF(U34>=65,"Tier 2",IF(U34>=55,"Tier 3","Exclude"))) | W34: Publish now | X34: Written for the doctor. Covers specialty × city ranges, follow-up norms and online vs in-clinic. Sources needed: NMC telemedicine guidelines. | Y34: Dominated by UGC: Facebook ×2, Reddit ×2, Quora. Only coveryou targets doctors. Rated High feasibility. | Z34: /for/doctors | AA34: H7, G1, D1 | AB34: Doctor reviewer; NMC sources
A35: 34 | C35: 11 | D35: H7 | E35: H: Industry booking-software landing pages (/for/*) | F35: Landing | G35: Consolidate | H35: Clinic Appointment Booking Software for India (Doctors, Solo Clinics) | I35: /for/doctors | J35: clinic appointment booking software india | K35: Unverified | L35: n/a | M35: appointment booking app for doctors, doctor appointment system, free doctor appointment booking software, doctor appointment app | N35: Commercial | O35: Conversion | P35: 3 | Q35: 3 | R35: 5 | S35: 3 | T35: 2 | U35: =ROUND((Scoring!$D$3*P35+Scoring!$E$3*Q35+Scoring!$F$3*R35+Scoring!$G$3*S35+Scoring!$H$3*T35)/5*100,0) | V35: =IF(U35>=75,"Tier 1",IF(U35>=65,"Tier 2",IF(U35>=55,"Tier 3","Exclude"))) | W35: Publish now | X35: 301 /for/doctors-india into /for/doctors. Honest positioning: booking, payments and reminders, not EMR. Include ₹ pricing. | Y35: zoho, docpulse, appointik.in, shmsolutions.in, doctorsapp.in and treatlly (25 Sep 2026) rank. Several small Indian sites. | Z35: /for/doctors | AA35: C1, D1, D2
A36: 35 | C36: 12 | D36: C12 | E36: C: Client message templates (WhatsApp, SMS, Hindi) | F36: Support | G36: New | H36: पेमेंट रिमाइंडर मैसेज (Payment Reminder Message in Hindi): WhatsApp Templates | I36: /blog/payment-reminder-message-hindi | J36: payment reminder message in hindi | K36: Unverified | L36: n/a | M36: payment reminder in hindi, paisa reminder message, udhaar reminder message | N36: Informational | O36: Consideration | P36: 2 | Q36: 5 | R36: 4 | S36: 5 | T36: 2 | U36: =ROUND((Scoring!$D$3*P36+Scoring!$E$3*Q36+Scoring!$F$3*R36+Scoring!$G$3*S36+Scoring!$H$3*T36)/5*100,0) | V36: =IF(U36>=75,"Tier 1",IF(U36>=65,"Tier 2",IF(U36>=55,"Tier 3","Exclude"))) | W36: Publish now | X36: Hindi-first page that links to C4. Covers shopkeeper and service-business variants. | Y36: 6 of 10 results are translate.google proxies. Rated High feasibility. | Z36: /features/payments | AA36: C4, C5 | AB36: Native Hindi writer
A37: 36 | C37: 12 | D37: C2 | E37: C: Client message templates (WhatsApp, SMS, Hindi) | F37: Support | G37: New | H37: Appointment Confirmation Message Templates (WhatsApp, SMS & Email with Payment Receipt) | I37: /blog/appointment-confirmation-message | J37: appointment confirmation message | K37: Unverified | L37: n/a | M37: booking confirmation message, appointment confirmation whatsapp message, consultation booking confirmation | N37: Informational | O37: Consideration | P37: 3 | Q37: 3 | R37: 5 | S37: 4 | T37: 3 | U37: =ROUND((Scoring!$D$3*P37+Scoring!$E$3*Q37+Scoring!$F$3*R37+Scoring!$G$3*S37+Scoring!$H$3*T37)/5*100,0) | V37: =IF(U37>=75,"Tier 1",IF(U37>=65,"Tier 2",IF(U37>=55,"Tier 3","Exclude"))) | W37: Publish now | X37: Service-business confirmations (not hotel/travel) that include the prepaid UPI receipt line, location or meeting link, and the cancellation-policy line. | Y37: formalert.in (small Indian site) is #7. The booking-confirmation SERP is hotel/travel-heavy (xola, mews). | Z37: /features/notifications | AA37: C1, C3, D2 | AB37: Screenshots of the Book A Sloth confirmation message
A38: 37 | C38: 12 | D38: F3 | E38: F: Scheduling concepts & glossary | F38: Template | G38: New | H38: Client Intake Form Questions for Coaches, Therapists & Consultants (Copy-Ready Templates) | I38: /templates/client-intake-form | J38: client intake form questions | K38: Unverified | L38: n/a | M38: intake form template, coaching intake form, therapy intake form questions, consultation form questions | N38: Informational | O38: Consideration | P38: 2 | Q38: 3 | R38: 5 | S38: 4 | T38: 4 | U38: =ROUND((Scoring!$D$3*P38+Scoring!$E$3*Q38+Scoring!$F$3*R38+Scoring!$G$3*S38+Scoring!$H$3*T38)/5*100,0) | V38: =IF(U38>=75,"Tier 1",IF(U38>=65,"Tier 2",IF(U38>=55,"Tier 3","Exclude"))) | W38: Publish now | X38: Question banks by profession, with a privacy note (DPDP Act basics) and a link to the booking-page intake feature. | Y38: Not checked. | Z38: /features/booking-pages | AA38: F2, C7, /glossary/intake-form | AB38: DPDP Act reference
A39: 38 | C39: 13 | D39: G5 | E39: G: Start & grow an independent practice in India (playbooks + pricing guides) | F39: Support | G39: New | H39: How to Start Online Yoga Classes in India: Batches, Pricing, UPI & Zoom Setup | I39: /blog/how-to-start-online-yoga-classes | J39: how to start yoga classes online | K39: Unverified | L39: n/a | M39: online yoga classes business, how much to charge for online yoga class india, yoga teacher income india | N39: Informational | O39: Consideration | P39: 2 | Q39: 4 | R39: 5 | S39: 4 | T39: 3 | U39: =ROUND((Scoring!$D$3*P39+Scoring!$E$3*Q39+Scoring!$F$3*R39+Scoring!$G$3*S39+Scoring!$H$3*T39)/5*100,0) | V39: =IF(U39>=75,"Tier 1",IF(U39>=65,"Tier 2",IF(U39>=55,"Tier 3","Exclude"))) | W39: Publish now | X39: Results are mostly non-India or about equipment. Covers India pricing, monthly UPI batches and Zoom links over WhatsApp. | Y39: sevensundaysyoga, sampoornayoga, YouTube ×3, Reddit. Rated High feasibility. | Z39: /for/yoga-instructors | AA39: H6, G1, C5
A40: 39 | C40: 13 | D40: H6 | E40: H: Industry booking-software landing pages (/for/*) | F40: Landing | G40: New | H40: Yoga Class Booking: Batches, Monthly UPI Fees & WhatsApp Reminders | I40: /for/yoga-instructors | J40: yoga class booking app | K40: Unverified | L40: n/a | M40: yoga studio booking software, online yoga class booking | N40: Commercial | O40: Conversion | P40: 2 | Q40: 3 | R40: 5 | S40: 4 | T40: 2 | U40: =ROUND((Scoring!$D$3*P40+Scoring!$E$3*Q40+Scoring!$F$3*R40+Scoring!$G$3*S40+Scoring!$H$3*T40)/5*100,0) | V40: =IF(U40>=75,"Tier 1",IF(U40>=65,"Tier 2",IF(U40>=55,"Tier 3","Exclude"))) | W40: Publish now | X40: Nothing India-specific ranks. Covers monthly batches, UPI and Instagram/WhatsApp. | Y40: lunacal, Momoyoga and yogobooking rank (global small SaaS). | Z40: /for/yoga-instructors | AA40: G5, C5
A41: 40 | C41: 13 | D41: L3 | E41: L: Booking-link how-tos (Instagram, Google, website) | F41: Support | G41: New | H41: How to Add a 'Book Now' Button to Your Google Business Profile | I41: /blog/book-button-google-business-profile | J41: booking button | K41: 210 | L41: 23 | M41: google business profile booking link, book online button google, reserve with google india | N41: Informational | O41: Consideration | P41: 2 | Q41: 4 | R41: 5 | S41: 3 | T41: 3 | U41: =ROUND((Scoring!$D$3*P41+Scoring!$E$3*Q41+Scoring!$F$3*R41+Scoring!$G$3*S41+Scoring!$H$3*T41)/5*100,0) | V41: =IF(U41>=75,"Tier 1",IF(U41>=65,"Tier 2",IF(U41>=55,"Tier 3","Exclude"))) | W41: Publish now | X41: Step-by-step with screenshots. Local-SEO tie-in for host profiles. | Y41: Setmore's GBP booking-link post ranks #3 for 'booking button' (210/KD23). | Z41: /features/booking-pages | AA41: L1, C8 | AB41: GBP screenshots
A42: 41 | C42: 13 | D42: E3 | E42: E: Interview & meeting message templates (traffic cluster) | F42: Support | G42: Refresh | H42: Meeting Invitation Templates: Email, WhatsApp, SMS, Hindi & Society/RWA Notices | I42: /blog/meeting-invitation-templates | J42: meeting invitation | K42: 720 | L42: 25 | M42: meeting invitation message, meeting notice format, sms invitation for meeting, meeting invitation email template, apartment association meeting invitation, how to ask for availability for a meeting example, when can we meet | N42: Informational | O42: Awareness | P42: 4 | Q42: 4 | R42: 3 | S42: 3 | T42: 2 | U42: =ROUND((Scoring!$D$3*P42+Scoring!$E$3*Q42+Scoring!$F$3*R42+Scoring!$G$3*S42+Scoring!$H$3*T42)/5*100,0) | V42: =IF(U42>=75,"Tier 1",IF(U42>=65,"Tier 2",IF(U42>=55,"Tier 3","Exclude"))) | W42: Publish now | X42: Add Hindi, RWA/society and school formats, plus a 'how to ask for availability' section that absorbs that keyword (no separate page). | Y42: meettuesday (#1, about 800 words, untranslated Dutch rows). Calendly ranks #1 for 'meeting invitation email template' and #3 for 'meeting invitation in marathi'. | Z42: /features/booking-pages | AA42: C11, F2, E1
C43: Backlog | D43: A10 | E43: A: India pricing, alternatives & comparisons | F43: Comparison | G43: New | H43: Topmate vs SuperProfile vs Book A Sloth: Fees, Payouts & Booking Features | I43: /compare/topmate-vs-superprofile | J43: topmate vs superprofile | K43: Unverified | L43: n/a | M43: superprofile pricing india, topmate or superprofile | N43: Commercial | O43: Consideration | P43: 2 | Q43: 4 | R43: 4 | S43: 4 | T43: 4 | U43: =ROUND((Scoring!$D$3*P43+Scoring!$E$3*Q43+Scoring!$F$3*R43+Scoring!$G$3*S43+Scoring!$H$3*T43)/5*100,0) | V43: =IF(U43>=75,"Tier 1",IF(U43>=65,"Tier 2",IF(U43>=55,"Tier 3","Exclude"))) | W43: Later | X43: A Reddit thread ranks #2, so the SERP is open. Compare on ₹ fees, payout timing and booking vs storefront features. | Y43: Reddit r/IndiaContentCreators thread is #2. SuperProfile's /in pricing shows ₹99 then ₹499. | Z43: /pricing | AA43: A4, A5 | AB43: Pricing captures
C44: Backlog | D44: G9 | E44: G: Start & grow an independent practice in India (playbooks + pricing guides) | F44: Support | G44: New | H44: Dietitian & Nutritionist Consultation Fees in India (Packages, Per-Session, Online) | I44: /blog/dietitian-consultation-fees-india | J44: how much does a dietitian charge per consultation in india | K44: Unverified | L44: n/a | M44: nutritionist consultation fees in india, dietitian package price, online diet consultation fees | N44: Informational | O44: Consideration | P44: 2 | Q44: 3 | R44: 5 | S44: 4 | T44: 4 | U44: =ROUND((Scoring!$D$3*P44+Scoring!$E$3*Q44+Scoring!$F$3*R44+Scoring!$G$3*S44+Scoring!$H$3*T44)/5*100,0) | V44: =IF(U44>=75,"Tier 1",IF(U44>=65,"Tier 2",IF(U44>=55,"Tier 3","Exclude"))) | W44: Later | X44: Seen as a forum question ('is ₹20000 for a 6-month package reasonable'). Data-led with package examples. | Y44: Not checked directly. Observed as Reddit and nnwa.in questions. | Z44: /for/nutritionists | AA44: G1, /for/nutritionists | AB44: Nutritionist pricing data
C45: Backlog | D45: G4c | E45: G: Start & grow an independent practice in India (playbooks + pricing guides) | F45: Support | G45: New | H45: Tuition Fees Per Hour in India (2026): By Class, Subject, City, Online vs Home | I45: /blog/tuition-fees-per-hour-india | J45: tuition fees per hour in india | K45: Unverified | L45: n/a | M45: home tuition fees per month, online tuition fees per hour, home tuition fee for class 10 | N45: Informational | O45: Consideration | P45: 3 | Q45: 3 | R45: 4 | S45: 3 | T45: 5 | U45: =ROUND((Scoring!$D$3*P45+Scoring!$E$3*Q45+Scoring!$F$3*R45+Scoring!$G$3*S45+Scoring!$H$3*T45)/5*100,0) | V45: =IF(U45>=75,"Tier 1",IF(U45>=65,"Tier 2",IF(U45>=55,"Tier 3","Exclude"))) | W45: Later | X45: Table-led and data-backed. The competing pages are already fresh (2026), so differentiate on Book A Sloth tutor data. | Y45: tuitionsinindia, superprof, Reddit, urbanpro, Quora. Rated Med-High feasibility. | Z45: /for/tutors | AA45: G4, G1 | AB45: Tutor pricing data
C46: Backlog | D46: B4 | E46: B: Getting paid: UPI, payment links, advance payments & GST | F46: Tool | G46: New | H46: Free GST Invoice Format for Freelancers & Consultants (Generator + Templates) | I46: /tools/invoice-generator | J46: invoice format for freelancers india | K46: Unverified | L46: n/a | M46: freelancer invoice template india, gst invoice format for services, consultant invoice format | N46: Transactional | O46: Consideration | P46: 3 | Q46: 3 | R46: 4 | S46: 4 | T46: 3 | U46: =ROUND((Scoring!$D$3*P46+Scoring!$E$3*Q46+Scoring!$F$3*R46+Scoring!$G$3*S46+Scoring!$H$3*T46)/5*100,0) | V46: =IF(U46>=75,"Tier 1",IF(U46>=65,"Tier 2",IF(U46>=55,"Tier 3","Exclude"))) | W46: Publish now | X46: A working generator that creates a PDF with GSTIN, SAC and place of supply. Template pages alone lose to tool pages. | Y46: Not fully checked. Tool and template sites dominate invoice SERPs. | Z46: /features/payments | AA46: B3, B1 | AB46: Dev: client-side PDF generator
C47: Backlog | D47: C7 | E47: C: Client message templates (WhatsApp, SMS, Hindi) | F47: Support | G47: New | H47: Welcome Message for New Clients: Onboarding Templates for Coaches, Therapists & Salons | I47: /blog/welcome-message-for-new-client | J47: welcome message for new client | K47: Unverified | L47: n/a | M47: client onboarding message, welcome message to customer, new client welcome email | N47: Informational | O47: Consideration | P47: 2 | Q47: 4 | R47: 4 | S47: 4 | T47: 3 | U47: =ROUND((Scoring!$D$3*P47+Scoring!$E$3*Q47+Scoring!$F$3*R47+Scoring!$G$3*S47+Scoring!$H$3*T47)/5*100,0) | V47: =IF(U47>=75,"Tier 1",IF(U47>=65,"Tier 2",IF(U47>=55,"Tier 3","Exclude"))) | W47: Publish now | X47: Service onboarding: intake-form link, policy line, payment and what to expect. On WhatsApp and email. | Y47: pinterest, textline and adobe rank; chatmitra (10 days old) also ranks. | Z47: /features/client-management | AA47: F3, C8, D2
C48: Backlog | D48: C8 | E48: C: Client message templates (WhatsApp, SMS, Hindi) | F48: Support | G48: New | H48: Thank-You Messages After a Session + How to Ask for a Google Review (Templates) | I48: /blog/thank-you-message-review-request | J48: thank you message for client after service | K48: Unverified | L48: n/a | M48: feedback message for customer, review request message, how to ask for google reviews on whatsapp | N48: Informational | O48: Consideration | P48: 3 | Q48: 3 | R48: 4 | S48: 4 | T48: 3 | U48: =ROUND((Scoring!$D$3*P48+Scoring!$E$3*Q48+Scoring!$F$3*R48+Scoring!$G$3*S48+Scoring!$H$3*T48)/5*100,0) | V48: =IF(U48>=75,"Tier 1",IF(U48>=65,"Tier 2",IF(U48>=55,"Tier 3","Exclude"))) | W48: Publish now | X48: Pairs the thank-you with a review request plus a Google review link, for Indian local businesses. Links to the Book A Sloth reviews feature. | Y48: zendesk/in, miocommerce and avochato rank. Setmore ranks #10 for 'how to get google reviews' (210/KD57). | Z48: /features/reviews | AA48: C7, L3, /features/reviews
C49: Backlog | D49: G10 | E49: G: Start & grow an independent practice in India (playbooks + pricing guides) | F49: Support | G49: New | H49: How to Start a Photography Business in India: Packages, Advance Bookings, Contracts & GST | I49: /blog/how-to-start-photography-business-india | J49: how to start a photography business in india | K49: Unverified | L49: n/a | M49: photography business plan india, photographer charges in india, documents needed to start photography business | N49: Informational | O49: Awareness | P49: 2 | Q49: 4 | R49: 4 | S49: 4 | T49: 3 | U49: =ROUND((Scoring!$D$3*P49+Scoring!$E$3*Q49+Scoring!$F$3*R49+Scoring!$G$3*S49+Scoring!$H$3*T49)/5*100,0) | V49: =IF(U49>=75,"Tier 1",IF(U49>=65,"Tier 2",IF(U49>=55,"Tier 3","Exclude"))) | W49: Later | X49: Covers booking with advance payment, contracts and GST, which current results skip. | Y49: YouTube ×2, Reddit r/IndiaBusiness, indiafilings and small sites. Rated High feasibility. | Z49: /for/photographers | AA49: H9, B2, B4
C50: Backlog | D50: G4b | E50: G: Start & grow an independent practice in India (playbooks + pricing guides) | F50: Support | G50: New | H50: How to Get Students for Home Tuition (Without Paying Directory Commission) | I50: /blog/how-to-get-students-for-home-tuition | J50: how to get students for home tuition | K50: Unverified | L50: n/a | M50: how to find students for home tuition, how to promote tuition classes, home tuition marketing ideas | N50: Informational | O50: Awareness | P50: 2 | Q50: 4 | R50: 4 | S50: 4 | T50: 3 | U50: =ROUND((Scoring!$D$3*P50+Scoring!$E$3*Q50+Scoring!$F$3*R50+Scoring!$G$3*S50+Scoring!$H$3*T50)/5*100,0) | V50: =IF(U50>=75,"Tier 1",IF(U50>=65,"Tier 2",IF(U50>=55,"Tier 3","Exclude"))) | W50: Publish now | X50: Local channels (society WhatsApp groups, Google Business Profile, a booking link in the bio, referrals) instead of paid directories. | Y50: Directory-led: Quora, Reddit r/delhi, small directories. Rated High feasibility. | Z50: /for/tutors | AA50: G4, L3, L1
C51: Backlog | D51: G7 | E51: G: Start & grow an independent practice in India (playbooks + pricing guides) | F51: Support | G51: New | H51: How to Get Paying Clients as a Life Coach in India (After Certification) | I51: /blog/life-coach-clients-india | J51: how to become a life coach in india | K51: Unverified | L51: n/a | M51: how to get coaching clients india, life coach business india, how to market coaching services | N51: Informational | O51: Awareness | P51: 2 | Q51: 3 | R51: 5 | S51: 4 | T51: 3 | U51: =ROUND((Scoring!$D$3*P51+Scoring!$E$3*Q51+Scoring!$F$3*R51+Scoring!$G$3*S51+Scoring!$H$3*T51)/5*100,0) | V51: =IF(U51>=75,"Tier 1",IF(U51>=65,"Tier 2",IF(U51>=55,"Tier 3","Exclude"))) | W51: Later | X51: Course sellers own the certification intent, so target the 'after certification' long tails. | Y51: Course sellers dominate (iisdt, igmpi, erickson). Rated Med feasibility. | Z51: /for/life-coaches | AA51: G6, G0, L1
C52: Backlog | D52: H2 | E52: H: Industry booking-software landing pages (/for/*) | F52: Landing | G52: Refresh | H52: Salon Booking Software in India: Appointments, UPI Deposits & WhatsApp Reminders | I52: /for/salon | J52: salon booking software india | K52: Unverified | L52: n/a | M52: salon booking apps, free software for salon, hair salon booking software, salon appointment book app, beauty parlour software | N52: Commercial | O52: Conversion | P52: 3 | Q52: 3 | R52: 5 | S52: 3 | T52: 2 | U52: =ROUND((Scoring!$D$3*P52+Scoring!$E$3*Q52+Scoring!$F$3*R52+Scoring!$G$3*S52+Scoring!$H$3*T52)/5*100,0) | V52: =IF(U52>=75,"Tier 1",IF(U52>=65,"Tier 2",IF(U52>=55,"Tier 3","Exclude"))) | W52: Publish now | X52: Owner-side intent: deposits against no-shows, festive and bridal bookings, staff calendars. | Y52: Setmore ranks #1 for 'salon booking apps' (480/KD24). 'salon booking app india' is consumer intent (Luzo, YesMadam). | Z52: /for/salon | AA52: C1, D2, C6
C53: Backlog | D53: B3 | E53: B: Getting paid: UPI, payment links, advance payments & GST | F53: Support | G53: New | H53: GST for Freelancers, Coaches & Consultants in India: Threshold, 18% Rate, SAC Codes & Invoices | I53: /blog/gst-for-freelancers-consultants-india | J53: gst for freelancers in india | K53: Unverified | L53: n/a | M53: gst on consultancy services, gst registration for freelancers, gst on coaching services, gst threshold for services | N53: Informational | O53: Awareness | P53: 3 | Q53: 2 | R53: 4 | S53: 4 | T53: 5 | U53: =ROUND((Scoring!$D$3*P53+Scoring!$E$3*Q53+Scoring!$F$3*R53+Scoring!$G$3*S53+Scoring!$H$3*T53)/5*100,0) | V53: =IF(U53>=75,"Tier 1",IF(U53>=65,"Tier 2",IF(U53>=55,"Tier 3","Exclude"))) | W53: Later | X53: DEFERRED: YMYL and crowded; ranking pages disagree on 5% vs 18%. Answer-first threshold table (₹20L / ₹10L special-category states), SAC 9983/9992 examples, export of services under LUT, invoice must-haves. Needs a named CA reviewer and links to cbic-gst.gov.in. | Y53: ownstreet.in, gstinvoices.in, Classplus and Quora rank. Strong YMYL signals are needed. | Z53: /tools/gst-calculator, /features/payments | AA53: B4, B1, /tools/gst-calculator, /glossary/gst-invoice | AB53: CA review and byline; government sources
C54: Backlog | D54: D3 | E54: D: No-shows, cancellations & booking policies | F54: Glossary | G54: Refresh | H54: Double Booking: What It Is and How to Prevent It (Calendar Sync Explained) | I54: /glossary/double-booking | J54: double booking | K54: 260 | L54: 26 | M54: what is double booking, how to avoid double booking, calendar sync | N54: Informational | O54: Awareness | P54: 2 | Q54: 4 | R54: 4 | S54: 3 | T54: 4 | U54: =ROUND((Scoring!$D$3*P54+Scoring!$E$3*Q54+Scoring!$F$3*R54+Scoring!$G$3*S54+Scoring!$H$3*T54)/5*100,0) | V54: =IF(U54>=75,"Tier 1",IF(U54>=65,"Tier 2",IF(U54>=55,"Tier 3","Exclude"))) | W54: Publish now | X54: Expand the glossary entry to 300-500 words. Link to /blog/two-bookings-one-slot as first-hand engineering proof. | Y54: Setmore support is #5 (260/KD26). | Z54: /features/google-calendar | AA54: F1, /features/google-calendar
C55: Backlog | D55: H4 | E55: H: Industry booking-software landing pages (/for/*) | F55: Landing | G55: New | H55: Booking App for Makeup Artists: Bridal Bookings, Advance Payments & Calendar | I55: /for/makeup-artists | J55: makeup artist app | K55: 170 | L55: 20 | M55: makeup artist booking app, bridal makeup booking | N55: Commercial | O55: Conversion | P55: 1 | Q55: 4 | R55: 5 | S55: 4 | T55: 2 | U55: =ROUND((Scoring!$D$3*P55+Scoring!$E$3*Q55+Scoring!$F$3*R55+Scoring!$G$3*S55+Scoring!$H$3*T55)/5*100,0) | V55: =IF(U55>=75,"Tier 1",IF(U55>=65,"Tier 2",IF(U55>=55,"Tier 3","Exclude"))) | W55: Publish now | X55: Bridal deposit flow and date holds. | Y55: Setmore ranks #1 for 'makeup artist app' (170/KD20). Instagram ranks #1 for 'makeup artist in nagpur'. | Z55: /for/makeup-artists | AA55: B2, L1
C56: Backlog | D56: I1 | E56: I: Local marketplace pages (host profiles + profession × city) | F56: Programmatic | G56: Refresh | H56: Host profile SEO template (all public profiles) | I56: /{username} | J56: {name} {profession} in {city} | K56: Unverified | L56: n/a | M56: {profession} in {locality}, {profession} near me | N56: Local | O56: Conversion | P56: 4 | Q56: 3 | R56: 4 | S56: 3 | T56: 1 | U56: =ROUND((Scoring!$D$3*P56+Scoring!$E$3*Q56+Scoring!$F$3*R56+Scoring!$G$3*S56+Scoring!$H$3*T56)/5*100,0) | V56: =IF(U56>=75,"Tier 1",IF(U56>=65,"Tier 2",IF(U56>=55,"Tier 3","Exclude"))) | W56: Publish now | X56: Title: '{Name}: {Profession} in {City} | Book & Pay Online'. Unique 150+ word bio, credentials (RCI/IAP etc.), service area, ₹ fees, live slots, real reviews, Person or LocalBusiness schema. NOINDEX profiles failing the gate (random usernames like /ivory-harbor-gkqzl, no bio, no active service). | Y56: Platform profiles rank for hyper-local terms: amritaspa.setmore.com is #3 for 'spa in malviya nagar'; a carehospitals profile is #1 and a physiodesk profile #8 for local queries. | Z56: /explore | AA56: I2 | AB56: Dev: quality-gate rules + schema
C57: Backlog | D57: I2 | E57: I: Local marketplace pages (host profiles + profession × city) | F57: Programmatic | G57: New | H57: Profession × city pages, e.g. /services/psychologist/nagpur | I57: /services/{profession}/{city} | J57: psychologist in nagpur | K57: Unverified | L57: n/a | M57: therapist in nagpur, nutritionist in nagpur, physiotherapist home visit nagpur, makeup artist in nagpur | N57: Local | O57: Conversion | P57: 4 | Q57: 3 | R57: 4 | S57: 3 | T57: 1 | U57: =ROUND((Scoring!$D$3*P57+Scoring!$E$3*Q57+Scoring!$F$3*R57+Scoring!$G$3*S57+Scoring!$H$3*T57)/5*100,0) | V57: =IF(U57>=75,"Tier 1",IF(U57>=65,"Tier 2",IF(U57>=55,"Tier 3","Exclude"))) | W57: Later | X57: Build only where ≥5 active, verified hosts exist (start with Nagpur, where current hosts cluster). Each page needs a host list with filters, a local FAQ unique to the city and real reviews. Otherwise noindex. | Y57: therapyroute is #5 for 'therapist in nagpur' with only 6 listings; Soulup's city collection is #2. Lawyer and CA city SERPs are marketplace-owned: skip them. | Z57: /services | AA57: I1, H5 | AB57: Supply threshold check per city
C58: Backlog | D58: A6 | E58: A: India pricing, alternatives & comparisons | F58: Comparison | G58: Consolidate | H58: Zoho Bookings Alternative for Indian Freelancers & Clinics | I58: /compare/zoho-bookings-alternative | J58: zoho bookings alternative | K58: Unverified | L58: n/a | M58: zoho bookings pricing india, zoho bookings vs calendly | N58: Commercial | O58: Conversion | P58: 2 | Q58: 3 | R58: 5 | S58: 3 | T58: 3 | U58: =ROUND((Scoring!$D$3*P58+Scoring!$E$3*Q58+Scoring!$F$3*R58+Scoring!$G$3*S58+Scoring!$H$3*T58)/5*100,0) | V58: =IF(U58>=75,"Tier 1",IF(U58>=65,"Tier 2",IF(U58>=55,"Tier 3","Exclude"))) | W58: Later | X58: Merge /lp/zoho-bookings-alternative here. Angle: Zoho's 33 industry pages carry no ₹, UPI or GST signals. | Y58: gartner, zoho ×3, koalendar, capterra.in and a Reddit thread rank. | Z58: /pricing | AA58: A1, A3 | AB58: Feature matrix
C59: Backlog | D59: A7 | E59: A: India pricing, alternatives & comparisons | F59: Comparison | G59: New | H59: Cal.com vs Calendly for Indian Users: Payments, UPI, Self-Hosting & ₹ Cost | I59: /compare/cal-com-vs-calendly | J59: cal.com vs calendly | K59: Unverified | L59: n/a | M59: cal com pricing india, cal.com upi | N59: Commercial | O59: Consideration | P59: 2 | Q59: 3 | R59: 4 | S59: 4 | T59: 4 | U59: =ROUND((Scoring!$D$3*P59+Scoring!$E$3*Q59+Scoring!$F$3*R59+Scoring!$G$3*S59+Scoring!$H$3*T59)/5*100,0) | V59: =IF(U59>=75,"Tier 1",IF(U59>=65,"Tier 2",IF(U59>=55,"Tier 3","Exclude"))) | W59: Later | X59: No India angle exists in the SERP. Cover INR cost, the payment-app reality (Stripe only), and when a self-hosted install makes sense. | Y59: cal.com ×3, efficient.app, youcanbook.me, zeeg, Reddit and onecal (Nov 2023) rank. | Z59: /compare | AA59: A2, A3, A1 | AB59: Test accounts
C60: Backlog | D60: G11 | E60: G: Start & grow an independent practice in India (playbooks + pricing guides) | F60: Support | G60: New | H60: How to Get Clients as a Freelancer in India (Local + Online Playbook) | I60: /blog/how-to-get-clients-freelancer-india | J60: how to get clients as a freelancer in india | K60: Unverified | L60: n/a | M60: how to get local clients for freelancing, freelancing clients india, how to find clients online india | N60: Informational | O60: Awareness | P60: 3 | Q60: 4 | R60: 3 | S60: 3 | T60: 3 | U60: =ROUND((Scoring!$D$3*P60+Scoring!$E$3*Q60+Scoring!$F$3*R60+Scoring!$G$3*S60+Scoring!$H$3*T60)/5*100,0) | V60: =IF(U60>=75,"Tier 1",IF(U60>=65,"Tier 2",IF(U60>=55,"Tier 3","Exclude"))) | W60: Later | X60: India-specific channels (WhatsApp, LinkedIn, referrals) plus a booking link as the conversion step. | Y60: Reddit ×2, Quora ×2, freelancer.in, small sites. Rated High feasibility. | Z60: /for/freelancers | AA60: B1, L1, G0
C61: Backlog | D61: K2 | E61: K: Expert & creator monetisation | F61: Support | G61: Refresh | H61: How to Become a Paid Mentor in India (1:1, Online) | I61: /blog/how-to-become-paid-mentor | J61: how to become a paid mentor | K61: Unverified | L61: n/a | M61: how to earn money as a mentor in india, paid mentorship platform, mentorship business | N61: Informational | O61: Consideration | P61: 2 | Q61: 4 | R61: 4 | S61: 3 | T61: 3 | U61: =ROUND((Scoring!$D$3*P61+Scoring!$E$3*Q61+Scoring!$F$3*R61+Scoring!$G$3*S61+Scoring!$H$3*T61)/5*100,0) | V61: =IF(U61>=75,"Tier 1",IF(U61>=65,"Tier 2",IF(U61>=55,"Tier 3","Exclude"))) | W61: Publish now | X61: 'how to earn money as a mentor in india' is rated High feasibility, and no result covers self-hosted mentorship. Add pricing data and a payout example. | Y61: Not checked. | Z61: /be-a-sloth | AA61: A5, G0
C62: Backlog | D62: L2 | E62: L: Booking-link how-tos (Instagram, Google, website) | F62: Support | G62: New | H62: Google Calendar Appointment Schedule: Free Booking Page Setup + Limits for Indian Businesses | I62: /blog/google-calendar-appointment-schedule | J62: google calendar appointment schedule | K62: Unverified | L62: n/a | M62: google calendar booking page free, google appointment booking | N62: Informational | O62: Consideration | P62: 3 | Q62: 3 | R62: 4 | S62: 3 | T62: 3 | U62: =ROUND((Scoring!$D$3*P62+Scoring!$E$3*Q62+Scoring!$F$3*R62+Scoring!$G$3*S62+Scoring!$H$3*T62)/5*100,0) | V62: =IF(U62>=75,"Tier 1",IF(U62>=65,"Tier 2",IF(U62>=55,"Tier 3","Exclude"))) | W62: Later | X62: A neutral how-to, then the limits that matter in India: paid booking needs Stripe, and there is no WhatsApp or UPI. | Y62: Google Workspace, support.google, YouTube, zapier and koalendar rank. | Z62: /features/google-calendar | AA62: L1, A1, /features/google-calendar
C63: Backlog | D63: C11 | E63: C: Client message templates (WhatsApp, SMS, Hindi) | F63: Support | G63: New | H63: मीटिंग निमंत्रण संदेश (Meeting Invitation Message in Hindi): WhatsApp, Letter & Email Formats | I63: /blog/meeting-invitation-message-hindi | J63: meeting invitation in hindi | K63: Unverified | L63: n/a | M63: meeting invitation message in hindi, meeting ka message, बैठक निमंत्रण | N63: Informational | O63: Awareness | P63: 2 | Q63: 5 | R63: 2 | S63: 5 | T63: 2 | U63: =ROUND((Scoring!$D$3*P63+Scoring!$E$3*Q63+Scoring!$F$3*R63+Scoring!$G$3*S63+Scoring!$H$3*T63)/5*100,0) | V63: =IF(U63>=75,"Tier 1",IF(U63>=65,"Tier 2",IF(U63>=55,"Tier 3","Exclude"))) | W63: Later | X63: Native Devanagari plus Hinglish versions. Google currently ranks translate.google proxies of English pages for this query. | Y63: 6 of 10 results are machine-translation proxies or Pinterest. Rated High feasibility. | Z63: /features/booking-pages | AA63: E3, C12 | AB63: Native Hindi writer
C64: Backlog | D64: H3 | E64: H: Industry booking-software landing pages (/for/*) | F64: Landing | G64: New | H64: Booking App for Barbers: Online Appointments + UPI (Free Plan) | I64: /for/barbers | J64: barber app | K64: 390 | L64: 19 | M64: barber website, barber shop site, barber booking app | N64: Commercial | O64: Conversion | P64: 2 | Q64: 3 | R64: 5 | S64: 3 | T64: 2 | U64: =ROUND((Scoring!$D$3*P64+Scoring!$E$3*Q64+Scoring!$F$3*R64+Scoring!$G$3*S64+Scoring!$H$3*T64)/5*100,0) | V64: =IF(U64>=75,"Tier 1",IF(U64>=65,"Tier 2",IF(U64>=55,"Tier 3","Exclude"))) | W64: Publish now | X64: A separate page from salon, because Setmore ranks with a dedicated barber page. | Y64: Setmore ranks #4 for 'barber app' (390/KD19) and #12 for 'barber website' (110/KD27). | Z64: /for/barbers | AA64: H2
C65: Backlog | D65: H8 | E65: H: Industry booking-software landing pages (/for/*) | F65: Landing | G65: Refresh | H65: Tutor Booking & Fee Collection: Trial Classes, Batches, Monthly UPI | I65: /for/tutors | J65: tutor management software | K65: 110 | L65: n/a | M65: tuition management app, online tuition booking, home tutor app | N65: Commercial | O65: Conversion | P65: 2 | Q65: 3 | R65: 5 | S65: 3 | T65: 2 | U65: =ROUND((Scoring!$D$3*P65+Scoring!$E$3*Q65+Scoring!$F$3*R65+Scoring!$G$3*S65+Scoring!$H$3*T65)/5*100,0) | V65: =IF(U65>=75,"Tier 1",IF(U65>=65,"Tier 2",IF(U65>=55,"Tier 3","Exclude"))) | W65: Publish now | X65: Trial or demo-class booking plus monthly UPI fee collection. Book A Sloth isn't an ERP, so say so. | Y65: Tiny Indian sites rank (tuitiondesk.in). Searchers want an ERP, so the page needs a careful angle. | Z65: /for/tutors | AA65: C5, G4
C66: Backlog | D66: H9 | E66: H: Industry booking-software landing pages (/for/*) | F66: Landing | G66: Refresh | H66: Photographer Booking: Shoot Packages, Deposits & GST Invoices | I66: /for/photographers | J66: photographer booking app | K66: Unverified | L66: n/a | M66: photography booking software, photo shoot booking | N66: Commercial | O66: Conversion | P66: 2 | Q66: 3 | R66: 5 | S66: 3 | T66: 2 | U66: =ROUND((Scoring!$D$3*P66+Scoring!$E$3*Q66+Scoring!$F$3*R66+Scoring!$G$3*S66+Scoring!$H$3*T66)/5*100,0) | V66: =IF(U66>=75,"Tier 1",IF(U66>=65,"Tier 2",IF(U66>=55,"Tier 3","Exclude"))) | W66: Later | X66: Package booking with UPI deposit and GST invoice. | Y66: POD apps, simplybook and Reddit rank. | Z66: /for/photographers | AA66: B2, B4
C67: Backlog | D67: B5 | E67: B: Getting paid: UPI, payment links, advance payments & GST | F67: Comparison | G67: New | H67: Best Payment Gateway for Freelancers & Small Service Businesses in India (Fees Compared) | I67: /compare/payment-gateway-for-freelancers-india | J67: payment gateway for freelancers india | K67: Unverified | L67: n/a | M67: razorpay vs cashfree for freelancers, razorpay for individuals, payment link without gst | N67: Commercial | O67: Consideration | P67: 2 | Q67: 3 | R67: 3 | S67: 4 | T67: 4 | U67: =ROUND((Scoring!$D$3*P67+Scoring!$E$3*Q67+Scoring!$F$3*R67+Scoring!$G$3*S67+Scoring!$H$3*T67)/5*100,0) | V67: =IF(U67>=75,"Tier 1",IF(U67>=65,"Tier 2",IF(U67>=55,"Tier 3","Exclude"))) | W67: Later | X67: Compare fees, KYC needs for individuals (no GST), settlement time and payment links. Book A Sloth handles KYC after first earnings, which is a unique angle. | Y67: Not checked. | Z67: /features/payments | AA67: B1, /blog/kyc-only-after-you-earn | AB67: Fee table with sources
C68: Backlog | D68: F6 | E68: F: Scheduling concepts & glossary | F68: Feature | G68: Refresh | H68: Book-a-Call Link: Let Clients Schedule a Call With You (Free) | I68: /features/booking-pages | J68: schedule a call | K68: 720 | L68: 21 | M68: book a call, schedule a call link, 30 minute call link | N68: Transactional | O68: Conversion | P68: 3 | Q68: 2 | R68: 5 | S68: 2 | T68: 2 | U68: =ROUND((Scoring!$D$3*P68+Scoring!$E$3*Q68+Scoring!$F$3*R68+Scoring!$G$3*S68+Scoring!$H$3*T68)/5*100,0) | V68: =IF(U68>=75,"Tier 1",IF(U68>=65,"Tier 2",IF(U68>=55,"Tier 3","Exclude"))) | W68: Later | X68: Retitle and tighten the existing feature page for 'schedule a call' / 'book a call'. Calendly's homepage ranks #1-2, so expectations are modest. | Y68: Calendly homepage ranks #1-2 (720/KD21, 260/KD23). | Z68: /features/booking-pages | AA68: L1, A1
C69: Backlog | D69: A8 | E69: A: India pricing, alternatives & comparisons | F69: Comparison | G69: Consolidate | H69: Setmore Alternative for India (UPI, WhatsApp, GST) | I69: /compare/setmore-alternative | J69: setmore alternative | K69: Unverified | L69: n/a | M69: setmore vs calendly, setmore india | N69: Commercial | O69: Conversion | P69: 1 | Q69: 3 | R69: 5 | S69: 3 | T69: 2 | U69: =ROUND((Scoring!$D$3*P69+Scoring!$E$3*Q69+Scoring!$F$3*R69+Scoring!$G$3*S69+Scoring!$H$3*T69)/5*100,0) | V69: =IF(U69>=75,"Tier 1",IF(U69>=65,"Tier 2",IF(U69>=55,"Tier 3","Exclude"))) | W69: Later | X69: Merge /lp/setmore-alternative here. Setmore's own blog uses only US examples, and Setmore booking pages ask clients to pay by BHIM UPI by hand. | Y69: Not checked in detail. | Z69: /pricing | AA69: A1 | AB69: Feature matrix
C70: Backlog | D70: E2 | E70: E: Interview & meeting message templates (traffic cluster) | F70: Support | G70: Refresh | H70: How to Acknowledge an Interview Email (Accept, Decline, Ask for Details) | I70: /blog/how-to-acknowledge-interview-email | J70: how to acknowledge interview email | K70: 320 | L70: 13 | M70: i will attend the interview, confirmation mail for interview, interview confirmation email, i confirm that i will attend the interview sample, how to acknowledge the interview mail | N70: Informational | O70: Awareness | P70: 3 | Q70: 4 | R70: 2 | S70: 3 | T70: 2 | U70: =ROUND((Scoring!$D$3*P70+Scoring!$E$3*Q70+Scoring!$F$3*R70+Scoring!$G$3*S70+Scoring!$H$3*T70)/5*100,0) | V70: =IF(U70>=75,"Tier 1",IF(U70>=65,"Tier 2",IF(U70>=55,"Tier 3","Exclude"))) | W70: Publish now | X70: Add decline, 'need more details' and WhatsApp/SMS acknowledgement templates, plus Indian call-letter context. | Y70: robertwalters.com.sg #1 (has a decline template); Reddit, Quora and foundit appear in results 11-20. | Z70: /features/booking-pages | AA70: E1
C71: Backlog | D71: H10 | E71: H: Industry booking-software landing pages (/for/*) | F71: Landing | G71: New | H71: Booking App for Massage Therapists & Spas (Home Visits, Deposits) | I71: /for/massage-therapists | J71: body massage app | K71: 320 | L71: 30 | M71: online massage app, app for massage at home, spa booking software | N71: Commercial | O71: Conversion | P71: 2 | Q71: 3 | R71: 4 | S71: 3 | T71: 1 | U71: =ROUND((Scoring!$D$3*P71+Scoring!$E$3*Q71+Scoring!$F$3*R71+Scoring!$G$3*S71+Scoring!$H$3*T71)/5*100,0) | V71: =IF(U71>=75,"Tier 1",IF(U71>=65,"Tier 2",IF(U71>=55,"Tier 3","Exclude"))) | W71: Later | X71: Professional framing only, because the query set includes adult-adjacent terms. Merge spa intent into /for/spa. | Y71: Setmore ranks #9 for 'body massage app' (320/KD30) and #2 for 'online massage app' (170/KD24). | Z71: /for/spa | AA71: H2
C72: Backlog | D72: F5 | E72: F: Scheduling concepts & glossary | F72: Support | G72: New | H72: Types of Meetings: 12 Formats and When to Use Each (with Booking Tips) | I72: /blog/types-of-meetings | J72: types of meeting | K72: 1000 | L72: 28 | M72: different types of meetings, meeting cycle, internal vs external meeting | N72: Informational | O72: Awareness | P72: 3 | Q72: 3 | R72: 2 | S72: 2 | T72: 4 | U72: =ROUND((Scoring!$D$3*P72+Scoring!$E$3*Q72+Scoring!$F$3*R72+Scoring!$G$3*S72+Scoring!$H$3*T72)/5*100,0) | V72: =IF(U72>=75,"Tier 1",IF(U72>=65,"Tier 2",IF(U72>=55,"Tier 3","Exclude"))) | W72: Later | X72: Low buyer fit but citable. Publish only after Tier 1 is done. | Y72: Calendly ranks #22 (1,000/KD28). | Z72: /features/booking-pages | AA72: F1
C73: Backlog | D73: E5 | E73: E: Interview & meeting message templates (traffic cluster) | F73: Template | G73: Refresh | H73: Interview Schedule Template (Free Google Sheet + Excel) | I73: /blog/interview-schedule-template | J73: interview schedule template | K73: 210 | L73: 27 | M73: interview schedule template word, interview schedule format, campus placement schedule | N73: Transactional | O73: Awareness | P73: 2 | Q73: 3 | R73: 2 | S73: 3 | T73: 2 | U73: =ROUND((Scoring!$D$3*P73+Scoring!$E$3*Q73+Scoring!$F$3*R73+Scoring!$G$3*S73+Scoring!$H$3*T73)/5*100,0) | V73: =IF(U73>=75,"Tier 1",IF(U73>=65,"Tier 2",IF(U73>=55,"Tier 3","Exclude"))) | W73: Later | X73: Ship real downloadable files. The SERP wants documents, not articles. | Y73: template.net, smartsheet PDF and oracle docs rank. | Z73: /features/booking-pages | AA73: E1 | AB73: Google Sheet + .xlsx
C74: Backlog | D74: I3 | E74: I: Local marketplace pages (host profiles + profession × city) | F74: Fix | G74: Refresh | H74: Fix /services/{profession} titles and copy ('Book a AI Engineer' → 'Book an AI Engineer') | I74: /services/{profession} | J74: {profession} online consultation | K74: Unverified | L74: n/a | M74: book a psychologist online, career coach online india | N74: Commercial | O74: Conversion | P74: 2 | Q74: 2 | R74: 4 | S74: 2 | T74: 1 | U74: =ROUND((Scoring!$D$3*P74+Scoring!$E$3*Q74+Scoring!$F$3*R74+Scoring!$G$3*S74+Scoring!$H$3*T74)/5*100,0) | V74: =IF(U74>=75,"Tier 1",IF(U74>=65,"Tier 2",IF(U74>=55,"Tier 3","Exclude"))) | W74: Publish now | X74: Grammar fix, unique intro per profession, live host count, FAQ. | Y74: n/a | Z74: /services | AA74: I2
C75: Backlog | D75: K1 | E75: K: Expert & creator monetisation | F75: Support | G75: Refresh | H75: How to Make Money From Home in India (2026): Real Ways | I75: /blog/how-to-make-money-from-home-india | J75: how to make money from home in india | K75: 480 | L75: 14 | M75: how to earn money from home in india, earn money online india | N75: Informational | O75: Awareness | P75: 3 | Q75: 2 | R75: 2 | S75: 2 | T75: 2 | U75: =ROUND((Scoring!$D$3*P75+Scoring!$E$3*Q75+Scoring!$F$3*R75+Scoring!$G$3*S75+Scoring!$H$3*T75)/5*100,0) | V75: =IF(U75>=75,"Tier 1",IF(U75>=65,"Tier 2",IF(U75>=55,"Tier 3","Exclude"))) | W75: Publish now | X75: Saturated, broad SERP (indeed, idfc, coursera). Light refresh only. Already published. Add a 'sell your expertise: 1:1 calls' section with real host earnings. | Y75: Topmate's homepage ranks #1 (480/KD14) and #1 for 'earn money from home in india' (390/KD30). | Z75: /be-a-sloth | AA75: K2, G0

Sheet Keyword Database
A1: Keyword | B1: Role | C1: Page primary keyword | D1: Supporting keywords (for primary rows) | E1: India volume | F1: Volume source & date | G1: KD | H1: KD source | I1: Search intent | J1: SERP competition (observed 2026-10-10) | K1: Competitor positions (export) | L1: Ranking opportunity / angle | M1: Business relevance | N1: Funnel stage | O1: AI citation potential | P1: AI rationale | Q1: Content type | R1: Priority score | S1: Tier | T1: Recommended URL | U1: Article ID | V1: Cluster | W1: Action | X1: Semrush SERP features
A2: appointment scheduling app india | B2: Primary | C2: appointment scheduling app india | D2: free appointment booking app india, appointment booking app india, best scheduling app india | E2: Unverified | F2: Unverified: validate in Semrush India / Google Keyword Planner | G2: n/a | H2: n/a | I2: Commercial | J2: A US Square page is #1 for 'free appointment booking app india'. zapier, simplybook and zoho also rank. No result shows ₹ pricing or UPI support. | L2: An honest list that includes competitors (Zoho, Calendly, Topmate, Setmore, Cal.com, Picktime, Appointy, Book A Sloth). One table: ₹ monthly cost incl. 18% GST, UPI support, WhatsApp reminders, commission, GST invoice. Methodology box plus a 'last tested' date. | M2: High | N2: Consideration | O2: High | P2: Pricing and comparison facts in ₹ that no current source gives | Q2: Pillar guide | R2: 77 | S2: Tier 1 | T2: /compare/best-appointment-booking-apps-india | U2: A1 | V2: A: India pricing, alternatives & comparisons | W2: New
A3: online booking website | B3: Supporting (from competitor data) | C3: appointment scheduling app india | E3: 390 | F3: Semrush India DB via competitor Organic Positions exports (calendly.com 2026-09-10, topmate.io 2026-09-10, setmore.com 2026-09-11) | G3: 40 | H3: Semrush | I3: informational | J3: A US Square page is #1 for 'free appointment booking app india'. zapier, simplybook and zoho also rank. No result shows ₹ pricing or UPI support. | K3: calendly #12; setmore #4 | L3: An honest list that includes competitors (Zoho, Calendly, Topmate, Setmore, Cal.com, Picktime, Appointy, Book A Sloth). One table: ₹ monthly cost incl. 18% GST, UPI support, WhatsApp reminders, commission, GST invoice. Methodology box plus a 'last tested' date. | M3: High | N3: Consideration | O3: High | P3: Pricing and comparison facts in ₹ that no current source gives | Q3: Pillar guide | R3: 77 | S3: Tier 1 | T3: /compare/best-appointment-booking-apps-india | U3: A1 | V3: A: India pricing, alternatives & comparisons | W3: New | X3: Sitelinks, Reviews, Video, People also ask, Related searches, AI overview
A4: schedule service | B4: Supporting (from competitor data) | C4: appointment scheduling app india | E4: 320 | F4: Semrush India DB via competitor Organic Positions exports (calendly.com 2026-09-10, topmate.io 2026-09-10, setmore.com 2026-09-11) | G4: 30 | H4: Semrush | I4: informational | J4: A US Square page is #1 for 'free appointment booking app india'. zapier, simplybook and zoho also rank. No result shows ₹ pricing or UPI support. | K4: setmore #39 | L4: An honest list that includes competitors (Zoho, Calendly, Topmate, Setmore, Cal.com, Picktime, Appointy, Book A Sloth). One table: ₹ monthly cost incl. 18% GST, UPI support, WhatsApp reminders, commission, GST invoice. Methodology box plus a 'last tested' date. | M4: High | N4: Consideration | O4: High | P4: Pricing and comparison facts in ₹ that no current source gives | Q4: Pillar guide | R4: 77 | S4: Tier 1 | T4: /compare/best-appointment-booking-apps-india | U4: A1 | V4: A: India pricing, alternatives & comparisons | W4: New | X4: Reviews, Video, People also ask, Related searches, AI overview
A5: service scheduling software | B5: Supporting (from competitor data) | C5: appointment scheduling app india | E5: 320 | F5: Semrush India DB via competitor Organic Positions exports (calendly.com 2026-09-10, topmate.io 2026-09-10, setmore.com 2026-09-11) | G5: 30 | H5: Semrush | I5: commercial | J5: A US Square page is #1 for 'free appointment booking app india'. zapier, simplybook and zoho also rank. No result shows ₹ pricing or UPI support. | K5: setmore #24 | L5: An honest list that includes competitors (Zoho, Calendly, Topmate, Setmore, Cal.com, Picktime, Appointy, Book A Sloth). One table: ₹ monthly cost incl. 18% GST, UPI support, WhatsApp reminders, commission, GST invoice. Methodology box plus a 'last tested' date. | M5: High | N5: Consideration | O5: High | P5: Pricing and comparison facts in ₹ that no current source gives | Q5: Pillar guide | R5: 77 | S5: Tier 1 | T5: /compare/best-appointment-booking-apps-india | U5: A1 | V5: A: India pricing, alternatives & comparisons | W5: New | X5: Sitelinks, Reviews, Video, Related searches, AI overview
A6: book session | B6: Supporting (from competitor data) | C6: appointment scheduling app india | E6: 210 | F6: Semrush India DB via competitor Organic Positions exports (calendly.com 2026-09-10, topmate.io 2026-09-10, setmore.com 2026-09-11) | G6: 21 | H6: Semrush | I6: informational | J6: A US Square page is #1 for 'free appointment booking app india'. zapier, simplybook and zoho also rank. No result shows ₹ pricing or UPI support. | K6: setmore #5 | L6: An honest list that includes competitors (Zoho, Calendly, Topmate, Setmore, Cal.com, Picktime, Appointy, Book A Sloth). One table: ₹ monthly cost incl. 18% GST, UPI support, WhatsApp reminders, commission, GST invoice. Methodology box plus a 'last tested' date. | M6: High | N6: Consideration | O6: High | P6: Pricing and comparison facts in ₹ that no current source gives | Q6: Pillar guide | R6: 77 | S6: Tier 1 | T6: /compare/best-appointment-booking-apps-india | U6: A1 | V6: A: India pricing, alternatives & comparisons | W6: New | X6: Reviews, Video, Video Carousel, People also ask, Related searches, AI overview
A7: booking start now | B7: Supporting (from competitor data) | C7: appointment scheduling app india | E7: 140 | F7: Semrush India DB via competitor Organic Positions exports (calendly.com 2026-09-10, topmate.io 2026-09-10, setmore.com 2026-09-11) | G7: 29 | H7: Semrush | I7: informational | J7: A US Square page is #1 for 'free appointment booking app india'. zapier, simplybook and zoho also rank. No result shows ₹ pricing or UPI support. | K7: calendly #27; setmore #3 | L7: An honest list that includes competitors (Zoho, Calendly, Topmate, Setmore, Cal.com, Picktime, Appointy, Book A Sloth). One table: ₹ monthly cost incl. 18% GST, UPI support, WhatsApp reminders, commission, GST invoice. Methodology box plus a 'last tested' date. | M7: High | N7: Consideration | O7: High | P7: Pricing and comparison facts in ₹ that no current source gives | Q7: Pillar guide | R7: 77 | S7: Tier 1 | T7: /compare/best-appointment-booking-apps-india | U7: A1 | V7: A: India pricing, alternatives & comparisons | W7: New | X7: Reviews, Video, People also ask, Related searches
A8: online booking system | B8: Supporting (from competitor data) | C8: appointment scheduling app india | E8: 140 | F8: Semrush India DB via competitor Organic Positions exports (calendly.com 2026-09-10, topmate.io 2026-09-10, setmore.com 2026-09-11) | G8: 35 | H8: Semrush | I8: informational | J8: A US Square page is #1 for 'free appointment booking app india'. zapier, simplybook and zoho also rank. No result shows ₹ pricing or UPI support. | K8: calendly #15; setmore #63 | L8: An honest list that includes competitors (Zoho, Calendly, Topmate, Setmore, Cal.com, Picktime, Appointy, Book A Sloth). One table: ₹ monthly cost incl. 18% GST, UPI support, WhatsApp reminders, commission, GST invoice. Methodology box plus a 'last tested' date. | M8: High | N8: Consideration | O8: High | P8: Pricing and comparison facts in ₹ that no current source gives | Q8: Pillar guide | R8: 77 | S8: Tier 1 | T8: /compare/best-appointment-booking-apps-india | U8: A1 | V8: A: India pricing, alternatives & comparisons | W8: New | X8: Reviews, Video, Video Carousel, Related searches, AI overview
A9: booking process | B9: Supporting (from competitor data) | C9: appointment scheduling app india | E9: 140 | F9: Semrush India DB via competitor Organic Positions exports (calendly.com 2026-09-10, topmate.io 2026-09-10, setmore.com 2026-09-11) | G9: 31 | H9: Semrush | I9: informational | J9: A US Square page is #1 for 'free appointment booking app india'. zapier, simplybook and zoho also rank. No result shows ₹ pricing or UPI support. | K9: calendly #40 | L9: An honest list that includes competitors (Zoho, Calendly, Topmate, Setmore, Cal.com, Picktime, Appointy, Book A Sloth). One table: ₹ monthly cost incl. 18% GST, UPI support, WhatsApp reminders, commission, GST invoice. Methodology box plus a 'last tested' date. | M9: High | N9: Consideration | O9: High | P9: Pricing and comparison facts in ₹ that no current source gives | Q9: Pillar guide | R9: 77 | S9: Tier 1 | T9: /compare/best-appointment-booking-apps-india | U9: A1 | V9: A: India pricing, alternatives & comparisons | W9: New | X9: Sitelinks, Reviews, Video, Video Carousel, People also ask, Related searches, Discussions and forums, AI overview
A10: automated scheduling | B10: Supporting (from competitor data) | C10: appointment scheduling app india | E10: 110 | F10: Semrush India DB via competitor Organic Positions exports (calendly.com 2026-09-10, topmate.io 2026-09-10, setmore.com 2026-09-11) | G10: 31 | H10: Semrush | I10: informational | J10: A US Square page is #1 for 'free appointment booking app india'. zapier, simplybook and zoho also rank. No result shows ₹ pricing or UPI support. | K10: calendly #1 | L10: An honest list that includes competitors (Zoho, Calendly, Topmate, Setmore, Cal.com, Picktime, Appointy, Book A Sloth). One table: ₹ monthly cost incl. 18% GST, UPI support, WhatsApp reminders, commission, GST invoice. Methodology box plus a 'last tested' date. | M10: High | N10: Consideration | O10: High | P10: Pricing and comparison facts in ₹ that no current source gives | Q10: Pillar guide | R10: 77 | S10: Tier 1 | T10: /compare/best-appointment-booking-apps-india | U10: A1 | V10: A: India pricing, alternatives & comparisons | W10: New | X10: Reviews, People also ask, Related searches, AI overview
A11: booking planner | B11: Supporting (from competitor data) | C11: appointment scheduling app india | E11: 110 | F11: Semrush India DB via competitor Organic Positions exports (calendly.com 2026-09-10, topmate.io 2026-09-10, setmore.com 2026-09-11) | G11: 39 | H11: Semrush | I11: informational | J11: A US Square page is #1 for 'free appointment booking app india'. zapier, simplybook and zoho also rank. No result shows ₹ pricing or UPI support. | K11: calendly #51 | L11: An honest list that includes competitors (Zoho, Calendly, Topmate, Setmore, Cal.com, Picktime, Appointy, Book A Sloth). One table: ₹ monthly cost incl. 18% GST, UPI support, WhatsApp reminders, commission, GST invoice. Methodology box plus a 'last tested' date. | M11: High | N11: Consideration | O11: High | P11: Pricing and comparison facts in ₹ that no current source gives | Q11: Pillar guide | R11: 77 | S11: Tier 1 | T11: /compare/best-appointment-booking-apps-india | U11: A1 | V11: A: India pricing, alternatives & comparisons | W11: New | X11: Sitelinks, Reviews, Video, Video Carousel, Related searches, AI overview
A12: staff booking | B12: Supporting (from competitor data) | C12: appointment scheduling app india | E12: 110 | F12: Semrush India DB via competitor Organic Positions exports (calendly.com 2026-09-10, topmate.io 2026-09-10, setmore.com 2026-09-11) | G12: 26 | H12: Semrush | I12: informational | J12: A US Square page is #1 for 'free appointment booking app india'. zapier, simplybook and zoho also rank. No result shows ₹ pricing or UPI support. | K12: setmore #9 | L12: An honest list that includes competitors (Zoho, Calendly, Topmate, Setmore, Cal.com, Picktime, Appointy, Book A Sloth). One table: ₹ monthly cost incl. 18% GST, UPI support, WhatsApp reminders, commission, GST invoice. Methodology box plus a 'last tested' date. | M12: High | N12: Consideration | O12: High | P12: Pricing and comparison facts in ₹ that no current source gives | Q12: Pillar guide | R12: 77 | S12: Tier 1 | T12: /compare/best-appointment-booking-apps-india | U12: A1 | V12: A: India pricing, alternatives & comparisons | W12: New | X12: Sitelinks, Reviews, Video, Video Carousel, People also ask, Related searches, AI overview
A13: free appointment booking app india | B13: Supporting | C13: appointment scheduling app india | E13: Unverified | F13: Unverified: validate in Semrush India / Google Keyword Planner | G13: n/a | H13: n/a | I13: Commercial | J13: A US Square page is #1 for 'free appointment booking app india'. zapier, simplybook and zoho also rank. No result shows ₹ pricing or UPI support. | L13: An honest list that includes competitors (Zoho, Calendly, Topmate, Setmore, Cal.com, Picktime, Appointy, Book A Sloth). One table: ₹ monthly cost incl. 18% GST, UPI support, WhatsApp reminders, commission, GST invoice. Methodology box plus a 'last tested' date. | M13: High | N13: Consideration | O13: High | P13: Pricing and comparison facts in ₹ that no current source gives | Q13: Pillar guide | R13: 77 | S13: Tier 1 | T13: /compare/best-appointment-booking-apps-india | U13: A1 | V13: A: India pricing, alternatives & comparisons | W13: New
A14: appointment booking app india | B14: Supporting | C14: appointment scheduling app india | E14: Unverified | F14: Unverified: validate in Semrush India / Google Keyword Planner | G14: n/a | H14: n/a | I14: Commercial | J14: A US Square page is #1 for 'free appointment booking app india'. zapier, simplybook and zoho also rank. No result shows ₹ pricing or UPI support. | L14: An honest list that includes competitors (Zoho, Calendly, Topmate, Setmore, Cal.com, Picktime, Appointy, Book A Sloth). One table: ₹ monthly cost incl. 18% GST, UPI support, WhatsApp reminders, commission, GST invoice. Methodology box plus a 'last tested' date. | M14: High | N14: Consideration | O14: High | P14: Pricing and comparison facts in ₹ that no current source gives | Q14: Pillar guide | R14: 77 | S14: Tier 1 | T14: /compare/best-appointment-booking-apps-india | U14: A1 | V14: A: India pricing, alternatives & comparisons | W14: New
A15: best scheduling app india | B15: Supporting | C15: appointment scheduling app india | E15: Unverified | F15: Unverified: validate in Semrush India / Google Keyword Planner | G15: n/a | H15: n/a | I15: Commercial | J15: A US Square page is #1 for 'free appointment booking app india'. zapier, simplybook and zoho also rank. No result shows ₹ pricing or UPI support. | L15: An honest list that includes competitors (Zoho, Calendly, Topmate, Setmore, Cal.com, Picktime, Appointy, Book A Sloth). One table: ₹ monthly cost incl. 18% GST, UPI support, WhatsApp reminders, commission, GST invoice. Methodology box plus a 'last tested' date. | M15: High | N15: Consideration | O15: High | P15: Pricing and comparison facts in ₹ that no current source gives | Q15: Pillar guide | R15: 77 | S15: Tier 1 | T15: /compare/best-appointment-booking-apps-india | U15: A1 | V15: A: India pricing, alternatives & comparisons | W15: New
A16: topmate vs superprofile | B16: Primary | C16: topmate vs superprofile | D16: superprofile pricing india, topmate or superprofile | E16: Unverified | F16: Unverified: validate in Semrush India / Google Keyword Planner | G16: n/a | H16: n/a | I16: Commercial | J16: Reddit r/IndiaContentCreators thread is #2. SuperProfile's /in pricing shows ₹99 then ₹499. | L16: A Reddit thread ranks #2, so the SERP is open. Compare on ₹ fees, payout timing and booking vs storefront features. | M16: High | N16: Consideration | O16: High | P16: Pricing and comparison facts in ₹ that no current source gives | Q16: Comparison page | R16: 70 | S16: Tier 2 | T16: /compare/topmate-vs-superprofile | U16: A10 | V16: A: India pricing, alternatives & comparisons | W16: New
A17: superprofile pricing india | B17: Supporting | C17: topmate vs superprofile | E17: Unverified | F17: Unverified: validate in Semrush India / Google Keyword Planner | G17: n/a | H17: n/a | I17: Commercial | J17: Reddit r/IndiaContentCreators thread is #2. SuperProfile's /in pricing shows ₹99 then ₹499. | L17: A Reddit thread ranks #2, so the SERP is open. Compare on ₹ fees, payout timing and booking vs storefront features. | M17: High | N17: Consideration | O17: High | P17: Pricing and comparison facts in ₹ that no current source gives | Q17: Comparison page | R17: 70 | S17: Tier 2 | T17: /compare/topmate-vs-superprofile | U17: A10 | V17: A: India pricing, alternatives & comparisons | W17: New
A18: topmate or superprofile | B18: Supporting | C18: topmate vs superprofile | E18: Unverified | F18: Unverified: validate in Semrush India / Google Keyword Planner | G18: n/a | H18: n/a | I18: Commercial | J18: Reddit r/IndiaContentCreators thread is #2. SuperProfile's /in pricing shows ₹99 then ₹499. | L18: A Reddit thread ranks #2, so the SERP is open. Compare on ₹ fees, payout timing and booking vs storefront features. | M18: High | N18: Consideration | O18: High | P18: Pricing and comparison facts in ₹ that no current source gives | Q18: Comparison page | R18: 70 | S18: Tier 2 | T18: /compare/topmate-vs-superprofile | U18: A10 | V18: A: India pricing, alternatives & comparisons | W18: New
A19: booking platform fee calculator | B19: Primary | C19: booking platform fee calculator | D19: topmate fee calculator, commission calculator for creators | E19: Unverified | F19: Unverified: validate in Semrush India / Google Keyword Planner | G19: n/a | H19: n/a | I19: Commercial | J19: No calculator ranks for these fee queries. | L19: Extend the existing /earnings-calculator to compare platforms side by side, and link it from A2, A4 and A5. A calculator is a citable, linkable asset. | M19: High | N19: Consideration | O19: High | P19: Pricing and comparison facts in ₹ that no current source gives | Q19: Free tool | R19: 75 | S19: Tier 1 | T19: /earnings-calculator | U19: A11 | V19: A: India pricing, alternatives & comparisons | W19: Refresh
A20: topmate fee calculator | B20: Supporting | C20: booking platform fee calculator | E20: Unverified | F20: Unverified: validate in Semrush India / Google Keyword Planner | G20: n/a | H20: n/a | I20: Commercial | J20: No calculator ranks for these fee queries. | L20: Extend the existing /earnings-calculator to compare platforms side by side, and link it from A2, A4 and A5. A calculator is a citable, linkable asset. | M20: High | N20: Consideration | O20: High | P20: Pricing and comparison facts in ₹ that no current source gives | Q20: Free tool | R20: 75 | S20: Tier 1 | T20: /earnings-calculator | U20: A11 | V20: A: India pricing, alternatives & comparisons | W20: Refresh
A21: commission calculator for creators | B21: Supporting | C21: booking platform fee calculator | E21: Unverified | F21: Unverified: validate in Semrush India / Google Keyword Planner | G21: n/a | H21: n/a | I21: Commercial | J21: No calculator ranks for these fee queries. | L21: Extend the existing /earnings-calculator to compare platforms side by side, and link it from A2, A4 and A5. A calculator is a citable, linkable asset. | M21: High | N21: Consideration | O21: High | P21: Pricing and comparison facts in ₹ that no current source gives | Q21: Free tool | R21: 75 | S21: Tier 1 | T21: /earnings-calculator | U21: A11 | V21: A: India pricing, alternatives & comparisons | W21: Refresh
A22: calendly pricing in india | B22: Primary | C22: calendly pricing in india | D22: is calendly free, calendly free plan limits, calendly price in rupees, calendly razorpay | E22: Unverified | F22: Unverified: validate in Semrush India / Google Keyword Planner | G22: n/a | H22: n/a | I22: Commercial | J22: All 10 results quote USD: calendly ×3, zoho, koalendar, withorb, cloudeagle, capterra.in, zeeg, tidycal. | L22: The only page that answers in INR: each USD plan converted at a dated rate, plus 18% GST (reverse charge for businesses), plus the ~3.5% card forex markup. Explains that Calendly takes payments only via Stripe/PayPal, so it has no UPI. Ends with a total-cost table. | M22: High | N22: Consideration | O22: High | P22: Pricing and comparison facts in ₹ that no current source gives | Q22: Guide / template list | R22: 85 | S22: Tier 1 | T22: /compare/calendly-pricing-india | U22: A2 | V22: A: India pricing, alternatives & comparisons | W22: New
A23: is calendly free | B23: Supporting | C23: calendly pricing in india | E23: Unverified | F23: Unverified: validate in Semrush India / Google Keyword Planner | G23: n/a | H23: n/a | I23: Commercial | J23: All 10 results quote USD: calendly ×3, zoho, koalendar, withorb, cloudeagle, capterra.in, zeeg, tidycal. | L23: The only page that answers in INR: each USD plan converted at a dated rate, plus 18% GST (reverse charge for businesses), plus the ~3.5% card forex markup. Explains that Calendly takes payments only via Stripe/PayPal, so it has no UPI. Ends with a total-cost table. | M23: High | N23: Consideration | O23: High | P23: Pricing and comparison facts in ₹ that no current source gives | Q23: Guide / template list | R23: 85 | S23: Tier 1 | T23: /compare/calendly-pricing-india | U23: A2 | V23: A: India pricing, alternatives & comparisons | W23: New
A24: calendly free plan limits | B24: Supporting | C24: calendly pricing in india | E24: Unverified | F24: Unverified: validate in Semrush India / Google Keyword Planner | G24: n/a | H24: n/a | I24: Commercial | J24: All 10 results quote USD: calendly ×3, zoho, koalendar, withorb, cloudeagle, capterra.in, zeeg, tidycal. | L24: The only page that answers in INR: each USD plan converted at a dated rate, plus 18% GST (reverse charge for businesses), plus the ~3.5% card forex markup. Explains that Calendly takes payments only via Stripe/PayPal, so it has no UPI. Ends with a total-cost table. | M24: High | N24: Consideration | O24: High | P24: Pricing and comparison facts in ₹ that no current source gives | Q24: Guide / template list | R24: 85 | S24: Tier 1 | T24: /compare/calendly-pricing-india | U24: A2 | V24: A: India pricing, alternatives & comparisons | W24: New
A25: calendly price in rupees | B25: Supporting | C25: calendly pricing in india | E25: Unverified | F25: Unverified: validate in Semrush India / Google Keyword Planner | G25: n/a | H25: n/a | I25: Commercial | J25: All 10 results quote USD: calendly ×3, zoho, koalendar, withorb, cloudeagle, capterra.in, zeeg, tidycal. | L25: The only page that answers in INR: each USD plan converted at a dated rate, plus 18% GST (reverse charge for businesses), plus the ~3.5% card forex markup. Explains that Calendly takes payments only via Stripe/PayPal, so it has no UPI. Ends with a total-cost table. | M25: High | N25: Consideration | O25: High | P25: Pricing and comparison facts in ₹ that no current source gives | Q25: Guide / template list | R25: 85 | S25: Tier 1 | T25: /compare/calendly-pricing-india | U25: A2 | V25: A: India pricing, alternatives & comparisons | W25: New
A26: calendly razorpay | B26: Supporting | C26: calendly pricing in india | E26: Unverified | F26: Unverified: validate in Semrush India / Google Keyword Planner | G26: n/a | H26: n/a | I26: Commercial | J26: All 10 results quote USD: calendly ×3, zoho, koalendar, withorb, cloudeagle, capterra.in, zeeg, tidycal. | L26: The only page that answers in INR: each USD plan converted at a dated rate, plus 18% GST (reverse charge for businesses), plus the ~3.5% card forex markup. Explains that Calendly takes payments only via Stripe/PayPal, so it has no UPI. Ends with a total-cost table. | M26: High | N26: Consideration | O26: High | P26: Pricing and comparison facts in ₹ that no current source gives | Q26: Guide / template list | R26: 85 | S26: Tier 1 | T26: /compare/calendly-pricing-india | U26: A2 | V26: A: India pricing, alternatives & comparisons | W26: New
A27: calendly alternative india | B27: Primary | C27: calendly alternative india | D27: calendly alternative, calendly alternatives free, free calendly alternative, calendly upi | E27: Unverified | F27: Unverified: validate in Semrush India / Google Keyword Planner | G27: n/a | H27: n/a | I27: Commercial | J27: zoho, capterra.in, zyncro.in, swiq.services, calenq.ai and bookyourcalendar.com rank: tiny Indian startups with exact-match pages. Reddit is #5 for the global 'calendly alternative'. | L27: Merge /lp/calendly-alternative into this page. Add proof the identical 'UPI+GST' competitor pages lack: a feature matrix, a 5-step migration walkthrough with screenshots, ₹ cost maths, and a dated 'last updated'. | M27: High | N27: Conversion | O27: High | P27: Pricing and comparison facts in ₹ that no current source gives | Q27: Comparison page | R27: 80 | S27: Tier 1 | T27: /compare/calendly-alternative-india | U27: A3 | V27: A: India pricing, alternatives & comparisons | W27: Consolidate
A28: calendly alternative | B28: Supporting | C28: calendly alternative india | E28: Unverified | F28: Unverified: validate in Semrush India / Google Keyword Planner | G28: n/a | H28: n/a | I28: Commercial | J28: zoho, capterra.in, zyncro.in, swiq.services, calenq.ai and bookyourcalendar.com rank: tiny Indian startups with exact-match pages. Reddit is #5 for the global 'calendly alternative'. | L28: Merge /lp/calendly-alternative into this page. Add proof the identical 'UPI+GST' competitor pages lack: a feature matrix, a 5-step migration walkthrough with screenshots, ₹ cost maths, and a dated 'last updated'. | M28: High | N28: Conversion | O28: High | P28: Pricing and comparison facts in ₹ that no current source gives | Q28: Comparison page | R28: 80 | S28: Tier 1 | T28: /compare/calendly-alternative-india | U28: A3 | V28: A: India pricing, alternatives & comparisons | W28: Consolidate
A29: calendly alternatives free | B29: Supporting | C29: calendly alternative india | E29: Unverified | F29: Unverified: validate in Semrush India / Google Keyword Planner | G29: n/a | H29: n/a | I29: Commercial | J29: zoho, capterra.in, zyncro.in, swiq.services, calenq.ai and bookyourcalendar.com rank: tiny Indian startups with exact-match pages. Reddit is #5 for the global 'calendly alternative'. | L29: Merge /lp/calendly-alternative into this page. Add proof the identical 'UPI+GST' competitor pages lack: a feature matrix, a 5-step migration walkthrough with screenshots, ₹ cost maths, and a dated 'last updated'. | M29: High | N29: Conversion | O29: High | P29: Pricing and comparison facts in ₹ that no current source gives | Q29: Comparison page | R29: 80 | S29: Tier 1 | T29: /compare/calendly-alternative-india | U29: A3 | V29: A: India pricing, alternatives & comparisons | W29: Consolidate
A30: free calendly alternative | B30: Supporting | C30: calendly alternative india | E30: Unverified | F30: Unverified: validate in Semrush India / Google Keyword Planner | G30: n/a | H30: n/a | I30: Commercial | J30: zoho, capterra.in, zyncro.in, swiq.services, calenq.ai and bookyourcalendar.com rank: tiny Indian startups with exact-match pages. Reddit is #5 for the global 'calendly alternative'. | L30: Merge /lp/calendly-alternative into this page. Add proof the identical 'UPI+GST' competitor pages lack: a feature matrix, a 5-step migration walkthrough with screenshots, ₹ cost maths, and a dated 'last updated'. | M30: High | N30: Conversion | O30: High | P30: Pricing and comparison facts in ₹ that no current source gives | Q30: Comparison page | R30: 80 | S30: Tier 1 | T30: /compare/calendly-alternative-india | U30: A3 | V30: A: India pricing, alternatives & comparisons | W30: Consolidate
A31: calendly upi | B31: Supporting | C31: calendly alternative india | E31: Unverified | F31: Unverified: validate in Semrush India / Google Keyword Planner | G31: n/a | H31: n/a | I31: Commercial | J31: zoho, capterra.in, zyncro.in, swiq.services, calenq.ai and bookyourcalendar.com rank: tiny Indian startups with exact-match pages. Reddit is #5 for the global 'calendly alternative'. | L31: Merge /lp/calendly-alternative into this page. Add proof the identical 'UPI+GST' competitor pages lack: a feature matrix, a 5-step migration walkthrough with screenshots, ₹ cost maths, and a dated 'last updated'. | M31: High | N31: Conversion | O31: High | P31: Pricing and comparison facts in ₹ that no current source gives | Q31: Comparison page | R31: 80 | S31: Tier 1 | T31: /compare/calendly-alternative-india | U31: A3 | V31: A: India pricing, alternatives & comparisons | W31: Consolidate
A32: topmate commission | B32: Primary | C32: topmate commission | D32: topmate charges, topmate pricing, topmate fees, topmate payout | E32: Unverified | F32: Unverified: validate in Semrush India / Google Keyword Planner | G32: n/a | H32: n/a | I32: Commercial | J32: The top 10 includes topmate's own pages, linkedin, an eximpe blog, medium, reddit and swadeshiapps. Small explainer sites rank. | L32: A worked example: 10% own-link and 20% marketplace fee (per topmate.io), plus the payment gateway fee, plus GST on the fee. Embeds a calculator (see A11). Factual and neutral, with sources. | M32: High | N32: Consideration | O32: High | P32: Pricing and comparison facts in ₹ that no current source gives | Q32: Guide / template list | R32: 80 | S32: Tier 1 | T32: /compare/topmate-commission | U32: A4 | V32: A: India pricing, alternatives & comparisons | W32: New
A33: topmate charges | B33: Supporting | C33: topmate commission | E33: Unverified | F33: Unverified: validate in Semrush India / Google Keyword Planner | G33: n/a | H33: n/a | I33: Commercial | J33: The top 10 includes topmate's own pages, linkedin, an eximpe blog, medium, reddit and swadeshiapps. Small explainer sites rank. | L33: A worked example: 10% own-link and 20% marketplace fee (per topmate.io), plus the payment gateway fee, plus GST on the fee. Embeds a calculator (see A11). Factual and neutral, with sources. | M33: High | N33: Consideration | O33: High | P33: Pricing and comparison facts in ₹ that no current source gives | Q33: Guide / template list | R33: 80 | S33: Tier 1 | T33: /compare/topmate-commission | U33: A4 | V33: A: India pricing, alternatives & comparisons | W33: New
A34: topmate pricing | B34: Supporting | C34: topmate commission | E34: Unverified | F34: Unverified: validate in Semrush India / Google Keyword Planner | G34: n/a | H34: n/a | I34: Commercial | J34: The top 10 includes topmate's own pages, linkedin, an eximpe blog, medium, reddit and swadeshiapps. Small explainer sites rank. | L34: A worked example: 10% own-link and 20% marketplace fee (per topmate.io), plus the payment gateway fee, plus GST on the fee. Embeds a calculator (see A11). Factual and neutral, with sources. | M34: High | N34: Consideration | O34: High | P34: Pricing and comparison facts in ₹ that no current source gives | Q34: Guide / template list | R34: 80 | S34: Tier 1 | T34: /compare/topmate-commission | U34: A4 | V34: A: India pricing, alternatives & comparisons | W34: New
A35: topmate fees | B35: Supporting | C35: topmate commission | E35: Unverified | F35: Unverified: validate in Semrush India / Google Keyword Planner | G35: n/a | H35: n/a | I35: Commercial | J35: The top 10 includes topmate's own pages, linkedin, an eximpe blog, medium, reddit and swadeshiapps. Small explainer sites rank. | L35: A worked example: 10% own-link and 20% marketplace fee (per topmate.io), plus the payment gateway fee, plus GST on the fee. Embeds a calculator (see A11). Factual and neutral, with sources. | M35: High | N35: Consideration | O35: High | P35: Pricing and comparison facts in ₹ that no current source gives | Q35: Guide / template list | R35: 80 | S35: Tier 1 | T35: /compare/topmate-commission | U35: A4 | V35: A: India pricing, alternatives & comparisons | W35: New
A36: topmate payout | B36: Supporting | C36: topmate commission | E36: Unverified | F36: Unverified: validate in Semrush India / Google Keyword Planner | G36: n/a | H36: n/a | I36: Commercial | J36: The top 10 includes topmate's own pages, linkedin, an eximpe blog, medium, reddit and swadeshiapps. Small explainer sites rank. | L36: A worked example: 10% own-link and 20% marketplace fee (per topmate.io), plus the payment gateway fee, plus GST on the fee. Embeds a calculator (see A11). Factual and neutral, with sources. | M36: High | N36: Consideration | O36: High | P36: Pricing and comparison facts in ₹ that no current source gives | Q36: Guide / template list | R36: 80 | S36: Tier 1 | T36: /compare/topmate-commission | U36: A4 | V36: A: India pricing, alternatives & comparisons | W36: New
A37: topmate alternative | B37: Primary | C37: topmate alternative | D37: topmate alternatives, topmate vs book a sloth, topmate competitors | E37: Unverified | F37: Unverified: validate in Semrush India / Google Keyword Planner | G37: n/a | H37: n/a | I37: Commercial | J37: adplist, mintlink.in (19 Aug 2026), an x.com tweet, virtup, ownstreet.in and kreato.co.in rank. Tiny Indian sites dominate. | L37: 301 /blog/topmate-alternative and /lp/topmate-vs-bookasloth here. Aim it at professionals (therapists, consultants) rather than creators. Include a ₹ fee comparison and a profile-migration walkthrough. | M37: High | N37: Conversion | O37: High | P37: Pricing and comparison facts in ₹ that no current source gives | Q37: Comparison page | R37: 80 | S37: Tier 1 | T37: /compare/topmate-alternative | U37: A5 | V37: A: India pricing, alternatives & comparisons | W37: Consolidate
A38: topmate alternatives | B38: Supporting | C38: topmate alternative | E38: Unverified | F38: Unverified: validate in Semrush India / Google Keyword Planner | G38: n/a | H38: n/a | I38: Commercial | J38: adplist, mintlink.in (19 Aug 2026), an x.com tweet, virtup, ownstreet.in and kreato.co.in rank. Tiny Indian sites dominate. | L38: 301 /blog/topmate-alternative and /lp/topmate-vs-bookasloth here. Aim it at professionals (therapists, consultants) rather than creators. Include a ₹ fee comparison and a profile-migration walkthrough. | M38: High | N38: Conversion | O38: High | P38: Pricing and comparison facts in ₹ that no current source gives | Q38: Comparison page | R38: 80 | S38: Tier 1 | T38: /compare/topmate-alternative | U38: A5 | V38: A: India pricing, alternatives & comparisons | W38: Consolidate
A39: topmate vs book a sloth | B39: Supporting | C39: topmate alternative | E39: Unverified | F39: Unverified: validate in Semrush India / Google Keyword Planner | G39: n/a | H39: n/a | I39: Commercial | J39: adplist, mintlink.in (19 Aug 2026), an x.com tweet, virtup, ownstreet.in and kreato.co.in rank. Tiny Indian sites dominate. | L39: 301 /blog/topmate-alternative and /lp/topmate-vs-bookasloth here. Aim it at professionals (therapists, consultants) rather than creators. Include a ₹ fee comparison and a profile-migration walkthrough. | M39: High | N39: Conversion | O39: High | P39: Pricing and comparison facts in ₹ that no current source gives | Q39: Comparison page | R39: 80 | S39: Tier 1 | T39: /compare/topmate-alternative | U39: A5 | V39: A: India pricing, alternatives & comparisons | W39: Consolidate
A40: topmate competitors | B40: Supporting | C40: topmate alternative | E40: Unverified | F40: Unverified: validate in Semrush India / Google Keyword Planner | G40: n/a | H40: n/a | I40: Commercial | J40: adplist, mintlink.in (19 Aug 2026), an x.com tweet, virtup, ownstreet.in and kreato.co.in rank. Tiny Indian sites dominate. | L40: 301 /blog/topmate-alternative and /lp/topmate-vs-bookasloth here. Aim it at professionals (therapists, consultants) rather than creators. Include a ₹ fee comparison and a profile-migration walkthrough. | M40: High | N40: Conversion | O40: High | P40: Pricing and comparison facts in ₹ that no current source gives | Q40: Comparison page | R40: 80 | S40: Tier 1 | T40: /compare/topmate-alternative | U40: A5 | V40: A: India pricing, alternatives & comparisons | W40: Consolidate
A41: zoho bookings alternative | B41: Primary | C41: zoho bookings alternative | D41: zoho bookings pricing india, zoho bookings vs calendly | E41: Unverified | F41: Unverified: validate in Semrush India / Google Keyword Planner | G41: n/a | H41: n/a | I41: Commercial | J41: gartner, zoho ×3, koalendar, capterra.in and a Reddit thread rank. | L41: Merge /lp/zoho-bookings-alternative here. Angle: Zoho's 33 industry pages carry no ₹, UPI or GST signals. | M41: High | N41: Conversion | O41: Medium | P41: Pricing and comparison facts in ₹ that no current source gives | Q41: Comparison page | R41: 65 | S41: Tier 2 | T41: /compare/zoho-bookings-alternative | U41: A6 | V41: A: India pricing, alternatives & comparisons | W41: Consolidate
A42: zoho bookings pricing india | B42: Supporting | C42: zoho bookings alternative | E42: Unverified | F42: Unverified: validate in Semrush India / Google Keyword Planner | G42: n/a | H42: n/a | I42: Commercial | J42: gartner, zoho ×3, koalendar, capterra.in and a Reddit thread rank. | L42: Merge /lp/zoho-bookings-alternative here. Angle: Zoho's 33 industry pages carry no ₹, UPI or GST signals. | M42: High | N42: Conversion | O42: Medium | P42: Pricing and comparison facts in ₹ that no current source gives | Q42: Comparison page | R42: 65 | S42: Tier 2 | T42: /compare/zoho-bookings-alternative | U42: A6 | V42: A: India pricing, alternatives & comparisons | W42: Consolidate
A43: zoho bookings vs calendly | B43: Supporting | C43: zoho bookings alternative | E43: Unverified | F43: Unverified: validate in Semrush India / Google Keyword Planner | G43: n/a | H43: n/a | I43: Commercial | J43: gartner, zoho ×3, koalendar, capterra.in and a Reddit thread rank. | L43: Merge /lp/zoho-bookings-alternative here. Angle: Zoho's 33 industry pages carry no ₹, UPI or GST signals. | M43: High | N43: Conversion | O43: Medium | P43: Pricing and comparison facts in ₹ that no current source gives | Q43: Comparison page | R43: 65 | S43: Tier 2 | T43: /compare/zoho-bookings-alternative | U43: A6 | V43: A: India pricing, alternatives & comparisons | W43: Consolidate
A44: cal.com vs calendly | B44: Primary | C44: cal.com vs calendly | D44: cal com pricing india, cal.com upi | E44: Unverified | F44: Unverified: validate in Semrush India / Google Keyword Planner | G44: n/a | H44: n/a | I44: Commercial | J44: cal.com ×3, efficient.app, youcanbook.me, zeeg, Reddit and onecal (Nov 2023) rank. | L44: No India angle exists in the SERP. Cover INR cost, the payment-app reality (Stripe only), and when a self-hosted install makes sense. | M44: High | N44: Consideration | O44: High | P44: Pricing and comparison facts in ₹ that no current source gives | Q44: Comparison page | R44: 65 | S44: Tier 2 | T44: /compare/cal-com-vs-calendly | U44: A7 | V44: A: India pricing, alternatives & comparisons | W44: New
A45: cal com pricing india | B45: Supporting | C45: cal.com vs calendly | E45: Unverified | F45: Unverified: validate in Semrush India / Google Keyword Planner | G45: n/a | H45: n/a | I45: Commercial | J45: cal.com ×3, efficient.app, youcanbook.me, zeeg, Reddit and onecal (Nov 2023) rank. | L45: No India angle exists in the SERP. Cover INR cost, the payment-app reality (Stripe only), and when a self-hosted install makes sense. | M45: High | N45: Consideration | O45: High | P45: Pricing and comparison facts in ₹ that no current source gives | Q45: Comparison page | R45: 65 | S45: Tier 2 | T45: /compare/cal-com-vs-calendly | U45: A7 | V45: A: India pricing, alternatives & comparisons | W45: New
A46: cal.com upi | B46: Supporting | C46: cal.com vs calendly | E46: Unverified | F46: Unverified: validate in Semrush India / Google Keyword Planner | G46: n/a | H46: n/a | I46: Commercial | J46: cal.com ×3, efficient.app, youcanbook.me, zeeg, Reddit and onecal (Nov 2023) rank. | L46: No India angle exists in the SERP. Cover INR cost, the payment-app reality (Stripe only), and when a self-hosted install makes sense. | M46: High | N46: Consideration | O46: High | P46: Pricing and comparison facts in ₹ that no current source gives | Q46: Comparison page | R46: 65 | S46: Tier 2 | T46: /compare/cal-com-vs-calendly | U46: A7 | V46: A: India pricing, alternatives & comparisons | W46: New
A47: setmore alternative | B47: Primary | C47: setmore alternative | D47: setmore vs calendly, setmore india | E47: Unverified | F47: Unverified: validate in Semrush India / Google Keyword Planner | G47: n/a | H47: n/a | I47: Commercial | J47: Not checked in detail. | L47: Merge /lp/setmore-alternative here. Setmore's own blog uses only US examples, and Setmore booking pages ask clients to pay by BHIM UPI by hand. | M47: High | N47: Conversion | O47: Low | P47: Pricing and comparison facts in ₹ that no current source gives | Q47: Comparison page | R47: 58 | S47: Tier 3 | T47: /compare/setmore-alternative | U47: A8 | V47: A: India pricing, alternatives & comparisons | W47: Consolidate
A48: setmore vs calendly | B48: Supporting | C48: setmore alternative | E48: Unverified | F48: Unverified: validate in Semrush India / Google Keyword Planner | G48: n/a | H48: n/a | I48: Commercial | J48: Not checked in detail. | L48: Merge /lp/setmore-alternative here. Setmore's own blog uses only US examples, and Setmore booking pages ask clients to pay by BHIM UPI by hand. | M48: High | N48: Conversion | O48: Low | P48: Pricing and comparison facts in ₹ that no current source gives | Q48: Comparison page | R48: 58 | S48: Tier 3 | T48: /compare/setmore-alternative | U48: A8 | V48: A: India pricing, alternatives & comparisons | W48: Consolidate
A49: setmore india | B49: Supporting | C49: setmore alternative | E49: Unverified | F49: Unverified: validate in Semrush India / Google Keyword Planner | G49: n/a | H49: n/a | I49: Commercial | J49: Not checked in detail. | L49: Merge /lp/setmore-alternative here. Setmore's own blog uses only US examples, and Setmore booking pages ask clients to pay by BHIM UPI by hand. | M49: High | N49: Conversion | O49: Low | P49: Pricing and comparison facts in ₹ that no current source gives | Q49: Comparison page | R49: 58 | S49: Tier 3 | T49: /compare/setmore-alternative | U49: A8 | V49: A: India pricing, alternatives & comparisons | W49: Consolidate
A50: calendly upi payment | B50: Primary | C50: calendly upi payment | D50: calendly razorpay integration, calendly paid events india, calendly payment india | E50: Unverified | F50: Unverified: validate in Semrush India / Google Keyword Planner | G50: n/a | H50: n/a | I50: Informational | J50: 'calendly razorpay integration' returns only connector pages (Zoho Flow, Integrately, Pabbly, Zapier, Albato) plus a dev.to post on 'the Razorpay gap'. | L50: Answer first: not natively (Stripe/PayPal only). Then compare the Zapier/Pabbly/Integrately connectors with a manual UPI-ID workflow and a native-UPI booking tool, covering cost, failure points and refunds. | M50: High | N50: Consideration | O50: High | P50: Pricing and comparison facts in ₹ that no current source gives | Q50: Guide / template list | R50: 80 | S50: Tier 1 | T50: /blog/calendly-upi-payments | U50: A9 | V50: A: India pricing, alternatives & comparisons | W50: New
A51: calendly razorpay integration | B51: Supporting | C51: calendly upi payment | E51: Unverified | F51: Unverified: validate in Semrush India / Google Keyword Planner | G51: n/a | H51: n/a | I51: Informational | J51: 'calendly razorpay integration' returns only connector pages (Zoho Flow, Integrately, Pabbly, Zapier, Albato) plus a dev.to post on 'the Razorpay gap'. | L51: Answer first: not natively (Stripe/PayPal only). Then compare the Zapier/Pabbly/Integrately connectors with a manual UPI-ID workflow and a native-UPI booking tool, covering cost, failure points and refunds. | M51: High | N51: Consideration | O51: High | P51: Pricing and comparison facts in ₹ that no current source gives | Q51: Guide / template list | R51: 80 | S51: Tier 1 | T51: /blog/calendly-upi-payments | U51: A9 | V51: A: India pricing, alternatives & comparisons | W51: New
A52: calendly paid events india | B52: Supporting | C52: calendly upi payment | E52: Unverified | F52: Unverified: validate in Semrush India / Google Keyword Planner | G52: n/a | H52: n/a | I52: Informational | J52: 'calendly razorpay integration' returns only connector pages (Zoho Flow, Integrately, Pabbly, Zapier, Albato) plus a dev.to post on 'the Razorpay gap'. | L52: Answer first: not natively (Stripe/PayPal only). Then compare the Zapier/Pabbly/Integrately connectors with a manual UPI-ID workflow and a native-UPI booking tool, covering cost, failure points and refunds. | M52: High | N52: Consideration | O52: High | P52: Pricing and comparison facts in ₹ that no current source gives | Q52: Guide / template list | R52: 80 | S52: Tier 1 | T52: /blog/calendly-upi-payments | U52: A9 | V52: A: India pricing, alternatives & comparisons | W52: New
A53: calendly payment india | B53: Supporting | C53: calendly upi payment | E53: Unverified | F53: Unverified: validate in Semrush India / Google Keyword Planner | G53: n/a | H53: n/a | I53: Informational | J53: 'calendly razorpay integration' returns only connector pages (Zoho Flow, Integrately, Pabbly, Zapier, Albato) plus a dev.to post on 'the Razorpay gap'. | L53: Answer first: not natively (Stripe/PayPal only). Then compare the Zapier/Pabbly/Integrately connectors with a manual UPI-ID workflow and a native-UPI booking tool, covering cost, failure points and refunds. | M53: High | N53: Consideration | O53: High | P53: Pricing and comparison facts in ₹ that no current source gives | Q53: Guide / template list | R53: 80 | S53: Tier 1 | T53: /blog/calendly-upi-payments | U53: A9 | V53: A: India pricing, alternatives & comparisons | W53: New
A54: how to collect payment from clients online india | B54: Primary | C54: how to collect payment from clients online india | D54: how to accept upi payments for business, payment link for freelancers, how to take online consultation fees, accept payment without website | E54: Unverified | F54: Unverified: validate in Semrush India / Google Keyword Planner | G54: n/a | H54: n/a | I54: Informational | J54: Fintech blogs (Razorpay, Cashfree, Instamojo) and Quora threads rank. Instamojo titles still say 2024. | L54: Compares UPI ID/QR, payment links, gateway checkout and pay-at-booking on fees, auto-confirmation, refunds and GST invoices. Includes a decision table by profession. Razorpay's blog covers payment links but never booking. | M54: High | N54: Consideration | O54: High | P54: Step-by-step payment methods with fee tables | Q54: Pillar guide | R54: 80 | S54: Tier 1 | T54: /blog/collect-payments-from-clients-india | U54: B1 | V54: B: Getting paid: UPI, payment links, advance payments & GST | W54: New
A55: how to accept upi payments for business | B55: Supporting | C55: how to collect payment from clients online india | E55: Unverified | F55: Unverified: validate in Semrush India / Google Keyword Planner | G55: n/a | H55: n/a | I55: Informational | J55: Fintech blogs (Razorpay, Cashfree, Instamojo) and Quora threads rank. Instamojo titles still say 2024. | L55: Compares UPI ID/QR, payment links, gateway checkout and pay-at-booking on fees, auto-confirmation, refunds and GST invoices. Includes a decision table by profession. Razorpay's blog covers payment links but never booking. | M55: High | N55: Consideration | O55: High | P55: Step-by-step payment methods with fee tables | Q55: Pillar guide | R55: 80 | S55: Tier 1 | T55: /blog/collect-payments-from-clients-india | U55: B1 | V55: B: Getting paid: UPI, payment links, advance payments & GST | W55: New
A56: payment link for freelancers | B56: Supporting | C56: how to collect payment from clients online india | E56: Unverified | F56: Unverified: validate in Semrush India / Google Keyword Planner | G56: n/a | H56: n/a | I56: Informational | J56: Fintech blogs (Razorpay, Cashfree, Instamojo) and Quora threads rank. Instamojo titles still say 2024. | L56: Compares UPI ID/QR, payment links, gateway checkout and pay-at-booking on fees, auto-confirmation, refunds and GST invoices. Includes a decision table by profession. Razorpay's blog covers payment links but never booking. | M56: High | N56: Consideration | O56: High | P56: Step-by-step payment methods with fee tables | Q56: Pillar guide | R56: 80 | S56: Tier 1 | T56: /blog/collect-payments-from-clients-india | U56: B1 | V56: B: Getting paid: UPI, payment links, advance payments & GST | W56: New
A57: how to take online consultation fees | B57: Supporting | C57: how to collect payment from clients online india | E57: Unverified | F57: Unverified: validate in Semrush India / Google Keyword Planner | G57: n/a | H57: n/a | I57: Informational | J57: Fintech blogs (Razorpay, Cashfree, Instamojo) and Quora threads rank. Instamojo titles still say 2024. | L57: Compares UPI ID/QR, payment links, gateway checkout and pay-at-booking on fees, auto-confirmation, refunds and GST invoices. Includes a decision table by profession. Razorpay's blog covers payment links but never booking. | M57: High | N57: Consideration | O57: High | P57: Step-by-step payment methods with fee tables | Q57: Pillar guide | R57: 80 | S57: Tier 1 | T57: /blog/collect-payments-from-clients-india | U57: B1 | V57: B: Getting paid: UPI, payment links, advance payments & GST | W57: New
A58: accept payment without website | B58: Supporting | C58: how to collect payment from clients online india | E58: Unverified | F58: Unverified: validate in Semrush India / Google Keyword Planner | G58: n/a | H58: n/a | I58: Informational | J58: Fintech blogs (Razorpay, Cashfree, Instamojo) and Quora threads rank. Instamojo titles still say 2024. | L58: Compares UPI ID/QR, payment links, gateway checkout and pay-at-booking on fees, auto-confirmation, refunds and GST invoices. Includes a decision table by profession. Razorpay's blog covers payment links but never booking. | M58: High | N58: Consideration | O58: High | P58: Step-by-step payment methods with fee tables | Q58: Pillar guide | R58: 80 | S58: Tier 1 | T58: /blog/collect-payments-from-clients-india | U58: B1 | V58: B: Getting paid: UPI, payment links, advance payments & GST | W58: New
A59: advance payment for appointment | B59: Primary | C59: advance payment for appointment | D59: booking deposit, prepaid appointments, advance booking payment, how to take booking amount | E59: Unverified | F59: Unverified: validate in Semrush India / Google Keyword Planner | G59: n/a | H59: n/a | I59: Informational | J59: Not checked; no strong ranking page was observed for related queries. | L59: Covers deposit vs full prepay, how much to charge by profession, policy wording and refunds. Link to the build-in-public story /blog/advance-payments-without-the-screenshot-dance as first-hand proof. | M59: High | N59: Consideration | O59: High | P59: Step-by-step payment methods with fee tables | Q59: Guide / template list | R59: 78 | S59: Tier 1 | T59: /blog/advance-payment-for-appointments | U59: B2 | V59: B: Getting paid: UPI, payment links, advance payments & GST | W59: New
A60: booking deposit | B60: Supporting | C60: advance payment for appointment | E60: Unverified | F60: Unverified: validate in Semrush India / Google Keyword Planner | G60: n/a | H60: n/a | I60: Informational | J60: Not checked; no strong ranking page was observed for related queries. | L60: Covers deposit vs full prepay, how much to charge by profession, policy wording and refunds. Link to the build-in-public story /blog/advance-payments-without-the-screenshot-dance as first-hand proof. | M60: High | N60: Consideration | O60: High | P60: Step-by-step payment methods with fee tables | Q60: Guide / template list | R60: 78 | S60: Tier 1 | T60: /blog/advance-payment-for-appointments | U60: B2 | V60: B: Getting paid: UPI, payment links, advance payments & GST | W60: New
A61: prepaid appointments | B61: Supporting | C61: advance payment for appointment | E61: Unverified | F61: Unverified: validate in Semrush India / Google Keyword Planner | G61: n/a | H61: n/a | I61: Informational | J61: Not checked; no strong ranking page was observed for related queries. | L61: Covers deposit vs full prepay, how much to charge by profession, policy wording and refunds. Link to the build-in-public story /blog/advance-payments-without-the-screenshot-dance as first-hand proof. | M61: High | N61: Consideration | O61: High | P61: Step-by-step payment methods with fee tables | Q61: Guide / template list | R61: 78 | S61: Tier 1 | T61: /blog/advance-payment-for-appointments | U61: B2 | V61: B: Getting paid: UPI, payment links, advance payments & GST | W61: New
A62: advance booking payment | B62: Supporting | C62: advance payment for appointment | E62: Unverified | F62: Unverified: validate in Semrush India / Google Keyword Planner | G62: n/a | H62: n/a | I62: Informational | J62: Not checked; no strong ranking page was observed for related queries. | L62: Covers deposit vs full prepay, how much to charge by profession, policy wording and refunds. Link to the build-in-public story /blog/advance-payments-without-the-screenshot-dance as first-hand proof. | M62: High | N62: Consideration | O62: High | P62: Step-by-step payment methods with fee tables | Q62: Guide / template list | R62: 78 | S62: Tier 1 | T62: /blog/advance-payment-for-appointments | U62: B2 | V62: B: Getting paid: UPI, payment links, advance payments & GST | W62: New
A63: how to take booking amount | B63: Supporting | C63: advance payment for appointment | E63: Unverified | F63: Unverified: validate in Semrush India / Google Keyword Planner | G63: n/a | H63: n/a | I63: Informational | J63: Not checked; no strong ranking page was observed for related queries. | L63: Covers deposit vs full prepay, how much to charge by profession, policy wording and refunds. Link to the build-in-public story /blog/advance-payments-without-the-screenshot-dance as first-hand proof. | M63: High | N63: Consideration | O63: High | P63: Step-by-step payment methods with fee tables | Q63: Guide / template list | R63: 78 | S63: Tier 1 | T63: /blog/advance-payment-for-appointments | U63: B2 | V63: B: Getting paid: UPI, payment links, advance payments & GST | W63: New
A64: gst for freelancers in india | B64: Primary | C64: gst for freelancers in india | D64: gst on consultancy services, gst registration for freelancers, gst on coaching services, gst threshold for services | E64: Unverified | F64: Unverified: validate in Semrush India / Google Keyword Planner | G64: n/a | H64: n/a | I64: Informational | J64: ownstreet.in, gstinvoices.in, Classplus and Quora rank. Strong YMYL signals are needed. | L64: DEFERRED: YMYL and crowded; ranking pages disagree on 5% vs 18%. Answer-first threshold table (₹20L / ₹10L special-category states), SAC 9983/9992 examples, export of services under LUT, invoice must-haves. Needs a named CA reviewer and links to cbic-gst.gov.in. | M64: High | N64: Awareness | O64: High | P64: Step-by-step payment methods with fee tables | Q64: Guide / template list | R64: 67 | S64: Tier 2 | T64: /blog/gst-for-freelancers-consultants-india | U64: B3 | V64: B: Getting paid: UPI, payment links, advance payments & GST | W64: New
A65: gst on consultancy services | B65: Supporting | C65: gst for freelancers in india | E65: Unverified | F65: Unverified: validate in Semrush India / Google Keyword Planner | G65: n/a | H65: n/a | I65: Informational | J65: ownstreet.in, gstinvoices.in, Classplus and Quora rank. Strong YMYL signals are needed. | L65: DEFERRED: YMYL and crowded; ranking pages disagree on 5% vs 18%. Answer-first threshold table (₹20L / ₹10L special-category states), SAC 9983/9992 examples, export of services under LUT, invoice must-haves. Needs a named CA reviewer and links to cbic-gst.gov.in. | M65: High | N65: Awareness | O65: High | P65: Step-by-step payment methods with fee tables | Q65: Guide / template list | R65: 67 | S65: Tier 2 | T65: /blog/gst-for-freelancers-consultants-india | U65: B3 | V65: B: Getting paid: UPI, payment links, advance payments & GST | W65: New
A66: gst registration for freelancers | B66: Supporting | C66: gst for freelancers in india | E66: Unverified | F66: Unverified: validate in Semrush India / Google Keyword Planner | G66: n/a | H66: n/a | I66: Informational | J66: ownstreet.in, gstinvoices.in, Classplus and Quora rank. Strong YMYL signals are needed. | L66: DEFERRED: YMYL and crowded; ranking pages disagree on 5% vs 18%. Answer-first threshold table (₹20L / ₹10L special-category states), SAC 9983/9992 examples, export of services under LUT, invoice must-haves. Needs a named CA reviewer and links to cbic-gst.gov.in. | M66: High | N66: Awareness | O66: High | P66: Step-by-step payment methods with fee tables | Q66: Guide / template list | R66: 67 | S66: Tier 2 | T66: /blog/gst-for-freelancers-consultants-india | U66: B3 | V66: B: Getting paid: UPI, payment links, advance payments & GST | W66: New
A67: gst on coaching services | B67: Supporting | C67: gst for freelancers in india | E67: Unverified | F67: Unverified: validate in Semrush India / Google Keyword Planner | G67: n/a | H67: n/a | I67: Informational | J67: ownstreet.in, gstinvoices.in, Classplus and Quora rank. Strong YMYL signals are needed. | L67: DEFERRED: YMYL and crowded; ranking pages disagree on 5% vs 18%. Answer-first threshold table (₹20L / ₹10L special-category states), SAC 9983/9992 examples, export of services under LUT, invoice must-haves. Needs a named CA reviewer and links to cbic-gst.gov.in. | M67: High | N67: Awareness | O67: High | P67: Step-by-step payment methods with fee tables | Q67: Guide / template list | R67: 67 | S67: Tier 2 | T67: /blog/gst-for-freelancers-consultants-india | U67: B3 | V67: B: Getting paid: UPI, payment links, advance payments & GST | W67: New
A68: gst threshold for services | B68: Supporting | C68: gst for freelancers in india | E68: Unverified | F68: Unverified: validate in Semrush India / Google Keyword Planner | G68: n/a | H68: n/a | I68: Informational | J68: ownstreet.in, gstinvoices.in, Classplus and Quora rank. Strong YMYL signals are needed. | L68: DEFERRED: YMYL and crowded; ranking pages disagree on 5% vs 18%. Answer-first threshold table (₹20L / ₹10L special-category states), SAC 9983/9992 examples, export of services under LUT, invoice must-haves. Needs a named CA reviewer and links to cbic-gst.gov.in. | M68: High | N68: Awareness | O68: High | P68: Step-by-step payment methods with fee tables | Q68: Guide / template list | R68: 67 | S68: Tier 2 | T68: /blog/gst-for-freelancers-consultants-india | U68: B3 | V68: B: Getting paid: UPI, payment links, advance payments & GST | W68: New
A69: invoice format for freelancers india | B69: Primary | C69: invoice format for freelancers india | D69: freelancer invoice template india, gst invoice format for services, consultant invoice format | E69: Unverified | F69: Unverified: validate in Semrush India / Google Keyword Planner | G69: n/a | H69: n/a | I69: Transactional | J69: Not fully checked. Tool and template sites dominate invoice SERPs. | L69: A working generator that creates a PDF with GSTIN, SAC and place of supply. Template pages alone lose to tool pages. | M69: High | N69: Consideration | O69: Medium | P69: Step-by-step payment methods with fee tables | Q69: Free tool | R69: 68 | S69: Tier 2 | T69: /tools/invoice-generator | U69: B4 | V69: B: Getting paid: UPI, payment links, advance payments & GST | W69: New
A70: freelancer invoice template india | B70: Supporting | C70: invoice format for freelancers india | E70: Unverified | F70: Unverified: validate in Semrush India / Google Keyword Planner | G70: n/a | H70: n/a | I70: Transactional | J70: Not fully checked. Tool and template sites dominate invoice SERPs. | L70: A working generator that creates a PDF with GSTIN, SAC and place of supply. Template pages alone lose to tool pages. | M70: High | N70: Consideration | O70: Medium | P70: Step-by-step payment methods with fee tables | Q70: Free tool | R70: 68 | S70: Tier 2 | T70: /tools/invoice-generator | U70: B4 | V70: B: Getting paid: UPI, payment links, advance payments & GST | W70: New
A71: gst invoice format for services | B71: Supporting | C71: invoice format for freelancers india | E71: Unverified | F71: Unverified: validate in Semrush India / Google Keyword Planner | G71: n/a | H71: n/a | I71: Transactional | J71: Not fully checked. Tool and template sites dominate invoice SERPs. | L71: A working generator that creates a PDF with GSTIN, SAC and place of supply. Template pages alone lose to tool pages. | M71: High | N71: Consideration | O71: Medium | P71: Step-by-step payment methods with fee tables | Q71: Free tool | R71: 68 | S71: Tier 2 | T71: /tools/invoice-generator | U71: B4 | V71: B: Getting paid: UPI, payment links, advance payments & GST | W71: New
A72: consultant invoice format | B72: Supporting | C72: invoice format for freelancers india | E72: Unverified | F72: Unverified: validate in Semrush India / Google Keyword Planner | G72: n/a | H72: n/a | I72: Transactional | J72: Not fully checked. Tool and template sites dominate invoice SERPs. | L72: A working generator that creates a PDF with GSTIN, SAC and place of supply. Template pages alone lose to tool pages. | M72: High | N72: Consideration | O72: Medium | P72: Step-by-step payment methods with fee tables | Q72: Free tool | R72: 68 | S72: Tier 2 | T72: /tools/invoice-generator | U72: B4 | V72: B: Getting paid: UPI, payment links, advance payments & GST | W72: New
A73: payment gateway for freelancers india | B73: Primary | C73: payment gateway for freelancers india | D73: razorpay vs cashfree for freelancers, razorpay for individuals, payment link without gst | E73: Unverified | F73: Unverified: validate in Semrush India / Google Keyword Planner | G73: n/a | H73: n/a | I73: Commercial | J73: Not checked. | L73: Compare fees, KYC needs for individuals (no GST), settlement time and payment links. Book A Sloth handles KYC after first earnings, which is a unique angle. | M73: Medium | N73: Consideration | O73: High | P73: Step-by-step payment methods with fee tables | Q73: Comparison page | R73: 60 | S73: Tier 3 | T73: /compare/payment-gateway-for-freelancers-india | U73: B5 | V73: B: Getting paid: UPI, payment links, advance payments & GST | W73: New
A74: razorpay vs cashfree for freelancers | B74: Supporting | C74: payment gateway for freelancers india | E74: Unverified | F74: Unverified: validate in Semrush India / Google Keyword Planner | G74: n/a | H74: n/a | I74: Commercial | J74: Not checked. | L74: Compare fees, KYC needs for individuals (no GST), settlement time and payment links. Book A Sloth handles KYC after first earnings, which is a unique angle. | M74: Medium | N74: Consideration | O74: High | P74: Step-by-step payment methods with fee tables | Q74: Comparison page | R74: 60 | S74: Tier 3 | T74: /compare/payment-gateway-for-freelancers-india | U74: B5 | V74: B: Getting paid: UPI, payment links, advance payments & GST | W74: New
A75: razorpay for individuals | B75: Supporting | C75: payment gateway for freelancers india | E75: Unverified | F75: Unverified: validate in Semrush India / Google Keyword Planner | G75: n/a | H75: n/a | I75: Commercial | J75: Not checked. | L75: Compare fees, KYC needs for individuals (no GST), settlement time and payment links. Book A Sloth handles KYC after first earnings, which is a unique angle. | M75: Medium | N75: Consideration | O75: High | P75: Step-by-step payment methods with fee tables | Q75: Comparison page | R75: 60 | S75: Tier 3 | T75: /compare/payment-gateway-for-freelancers-india | U75: B5 | V75: B: Getting paid: UPI, payment links, advance payments & GST | W75: New
A76: payment link without gst | B76: Supporting | C76: payment gateway for freelancers india | E76: Unverified | F76: Unverified: validate in Semrush India / Google Keyword Planner | G76: n/a | H76: n/a | I76: Commercial | J76: Not checked. | L76: Compare fees, KYC needs for individuals (no GST), settlement time and payment links. Book A Sloth handles KYC after first earnings, which is a unique angle. | M76: Medium | N76: Consideration | O76: High | P76: Step-by-step payment methods with fee tables | Q76: Comparison page | R76: 60 | S76: Tier 3 | T76: /compare/payment-gateway-for-freelancers-india | U76: B5 | V76: B: Getting paid: UPI, payment links, advance payments & GST | W76: New
A77: how to ask client for payment | B77: Primary | C77: how to ask client for payment | D77: how to ask client for payment politely, payment follow up email, polite payment reminder email | E77: 720 | F77: Semrush India DB via competitor Organic Positions exports (calendly.com 2026-09-10, topmate.io 2026-09-10, setmore.com 2026-09-11) | G77: 15 | H77: Semrush | I77: informational | J77: #1 is neat.com (2022, US). Calendly community ranks #15 for 'how to ask client for payment' (720/KD15). Book A Sloth is not in the top 20. | K77: calendly #15 | L77: Add a phone script, a 'pause work' template and the MSME Act 45-day payment rule. It is already the only India-specific result. | M77: High | N77: Awareness | O77: Medium | P77: Step-by-step payment methods with fee tables | Q77: Guide / template list | R77: 65 | S77: Tier 2 | T77: /blog/how-to-ask-client-for-payment-politely | U77: B6 | V77: B: Getting paid: UPI, payment links, advance payments & GST | W77: Refresh | X77: Sitelinks, Reviews, Video, Video Carousel, People also ask, Related searches, Short videos, AI overview
A78: how to ask client for payment politely | B78: Supporting | C78: how to ask client for payment | E78: Unverified | F78: Unverified: validate in Semrush India / Google Keyword Planner | G78: n/a | H78: n/a | I78: Informational | J78: #1 is neat.com (2022, US). Calendly community ranks #15 for 'how to ask client for payment' (720/KD15). Book A Sloth is not in the top 20. | L78: Add a phone script, a 'pause work' template and the MSME Act 45-day payment rule. It is already the only India-specific result. | M78: High | N78: Awareness | O78: Medium | P78: Step-by-step payment methods with fee tables | Q78: Guide / template list | R78: 65 | S78: Tier 2 | T78: /blog/how-to-ask-client-for-payment-politely | U78: B6 | V78: B: Getting paid: UPI, payment links, advance payments & GST | W78: Refresh
A79: payment follow up email | B79: Supporting | C79: how to ask client for payment | E79: Unverified | F79: Unverified: validate in Semrush India / Google Keyword Planner | G79: n/a | H79: n/a | I79: Informational | J79: #1 is neat.com (2022, US). Calendly community ranks #15 for 'how to ask client for payment' (720/KD15). Book A Sloth is not in the top 20. | L79: Add a phone script, a 'pause work' template and the MSME Act 45-day payment rule. It is already the only India-specific result. | M79: High | N79: Awareness | O79: Medium | P79: Step-by-step payment methods with fee tables | Q79: Guide / template list | R79: 65 | S79: Tier 2 | T79: /blog/how-to-ask-client-for-payment-politely | U79: B6 | V79: B: Getting paid: UPI, payment links, advance payments & GST | W79: Refresh
A80: polite payment reminder email | B80: Supporting | C80: how to ask client for payment | E80: Unverified | F80: Unverified: validate in Semrush India / Google Keyword Planner | G80: n/a | H80: n/a | I80: Informational | J80: #1 is neat.com (2022, US). Calendly community ranks #15 for 'how to ask client for payment' (720/KD15). Book A Sloth is not in the top 20. | L80: Add a phone script, a 'pause work' template and the MSME Act 45-day payment rule. It is already the only India-specific result. | M80: High | N80: Awareness | O80: Medium | P80: Step-by-step payment methods with fee tables | Q80: Guide / template list | R80: 65 | S80: Tier 2 | T80: /blog/how-to-ask-client-for-payment-politely | U80: B6 | V80: B: Getting paid: UPI, payment links, advance payments & GST | W80: Refresh
A81: whatsapp message templates for business | B81: Primary | C81: whatsapp message templates for business | D81: business message templates, client message templates, whatsapp templates for clinic | E81: Unverified | F81: Unverified: validate in Semrush India / Google Keyword Planner | G81: n/a | H81: n/a | I81: Informational | J81: Hub page. It earns rankings mainly through internal links. | L81: A hub that indexes every template page by job (confirm, remind, reschedule, cancel, get paid, thank, review) and by profession. No URL moves: existing /blog template posts stay where they are. | M81: High | N81: Awareness | O81: Medium | P81: Copy-ready templates; assistants paraphrase them but cite less often | Q81: Pillar guide | R81: 68 | S81: Tier 2 | T81: /templates | U81: C0 | V81: C: Client message templates (WhatsApp, SMS, Hindi) | W81: New
A82: business message templates | B82: Supporting | C82: whatsapp message templates for business | E82: Unverified | F82: Unverified: validate in Semrush India / Google Keyword Planner | G82: n/a | H82: n/a | I82: Informational | J82: Hub page. It earns rankings mainly through internal links. | L82: A hub that indexes every template page by job (confirm, remind, reschedule, cancel, get paid, thank, review) and by profession. No URL moves: existing /blog template posts stay where they are. | M82: High | N82: Awareness | O82: Medium | P82: Copy-ready templates; assistants paraphrase them but cite less often | Q82: Pillar guide | R82: 68 | S82: Tier 2 | T82: /templates | U82: C0 | V82: C: Client message templates (WhatsApp, SMS, Hindi) | W82: New
A83: client message templates | B83: Supporting | C83: whatsapp message templates for business | E83: Unverified | F83: Unverified: validate in Semrush India / Google Keyword Planner | G83: n/a | H83: n/a | I83: Informational | J83: Hub page. It earns rankings mainly through internal links. | L83: A hub that indexes every template page by job (confirm, remind, reschedule, cancel, get paid, thank, review) and by profession. No URL moves: existing /blog template posts stay where they are. | M83: High | N83: Awareness | O83: Medium | P83: Copy-ready templates; assistants paraphrase them but cite less often | Q83: Pillar guide | R83: 68 | S83: Tier 2 | T83: /templates | U83: C0 | V83: C: Client message templates (WhatsApp, SMS, Hindi) | W83: New
A84: whatsapp templates for clinic | B84: Supporting | C84: whatsapp message templates for business | E84: Unverified | F84: Unverified: validate in Semrush India / Google Keyword Planner | G84: n/a | H84: n/a | I84: Informational | J84: Hub page. It earns rankings mainly through internal links. | L84: A hub that indexes every template page by job (confirm, remind, reschedule, cancel, get paid, thank, review) and by profession. No URL moves: existing /blog template posts stay where they are. | M84: High | N84: Awareness | O84: Medium | P84: Copy-ready templates; assistants paraphrase them but cite less often | Q84: Pillar guide | R84: 68 | S84: Tier 2 | T84: /templates | U84: C0 | V84: C: Client message templates (WhatsApp, SMS, Hindi) | W84: New
A85: whatsapp reminder message for appointment | B85: Primary | C85: whatsapp reminder message for appointment | D85: appointment reminder message, whatsapp reminder, doctor appointment message, salon appointment reminder message, daily text reminders | E85: Unverified | F85: Unverified: validate in Semrush India / Google Keyword Planner | G85: n/a | H85: n/a | I85: Informational | J85: chati.ai (#1, about 900 words, 30 one-liners), wati and aisensy rank. Calendly community is #9 for 'whatsapp reminder' (590/KD24). Book A Sloth is not in the top 20. | L85: Go from about 10 to 30+ templates: per-trade sets (doctor with token/OPD timing, salon festive and bridal, tutor, coach), Hindi, a reminder-timing table, and a workflow for the free WhatsApp Business app vs automation. | M85: High | N85: Consideration | O85: Medium | P85: Copy-ready templates; assistants paraphrase them but cite less often | Q85: Guide / template list | R85: 78 | S85: Tier 1 | T85: /blog/appointment-reminder-templates | U85: C1 | V85: C: Client message templates (WhatsApp, SMS, Hindi) | W85: Refresh
A86: whatsapp reminder | B86: Supporting | C86: whatsapp reminder message for appointment | E86: 590 | F86: Semrush India DB via competitor Organic Positions exports (calendly.com 2026-09-10, topmate.io 2026-09-10, setmore.com 2026-09-11) | G86: 24 | H86: Semrush | I86: informational | J86: chati.ai (#1, about 900 words, 30 one-liners), wati and aisensy rank. Calendly community is #9 for 'whatsapp reminder' (590/KD24). Book A Sloth is not in the top 20. | K86: calendly #9 | L86: Go from about 10 to 30+ templates: per-trade sets (doctor with token/OPD timing, salon festive and bridal, tutor, coach), Hindi, a reminder-timing table, and a workflow for the free WhatsApp Business app vs automation. | M86: High | N86: Consideration | O86: Medium | P86: Copy-ready templates; assistants paraphrase them but cite less often | Q86: Guide / template list | R86: 78 | S86: Tier 1 | T86: /blog/appointment-reminder-templates | U86: C1 | V86: C: Client message templates (WhatsApp, SMS, Hindi) | W86: Refresh | X86: Sitelinks, Reviews, Video, Video Carousel, People also ask, Related searches, AI overview
A87: daily text reminders | B87: Supporting | C87: whatsapp reminder message for appointment | E87: 260 | F87: Semrush India DB via competitor Organic Positions exports (calendly.com 2026-09-10, topmate.io 2026-09-10, setmore.com 2026-09-11) | G87: 20 | H87: Semrush | I87: informational | J87: chati.ai (#1, about 900 words, 30 one-liners), wati and aisensy rank. Calendly community is #9 for 'whatsapp reminder' (590/KD24). Book A Sloth is not in the top 20. | K87: calendly #28 | L87: Go from about 10 to 30+ templates: per-trade sets (doctor with token/OPD timing, salon festive and bridal, tutor, coach), Hindi, a reminder-timing table, and a workflow for the free WhatsApp Business app vs automation. | M87: High | N87: Consideration | O87: Medium | P87: Copy-ready templates; assistants paraphrase them but cite less often | Q87: Guide / template list | R87: 78 | S87: Tier 1 | T87: /blog/appointment-reminder-templates | U87: C1 | V87: C: Client message templates (WhatsApp, SMS, Hindi) | W87: Refresh | X87: Sitelinks, Reviews, Video, Video Carousel, People also ask, Related searches
A88: appointment reminder message | B88: Supporting | C88: whatsapp reminder message for appointment | E88: Unverified | F88: Unverified: validate in Semrush India / Google Keyword Planner | G88: n/a | H88: n/a | I88: Informational | J88: chati.ai (#1, about 900 words, 30 one-liners), wati and aisensy rank. Calendly community is #9 for 'whatsapp reminder' (590/KD24). Book A Sloth is not in the top 20. | L88: Go from about 10 to 30+ templates: per-trade sets (doctor with token/OPD timing, salon festive and bridal, tutor, coach), Hindi, a reminder-timing table, and a workflow for the free WhatsApp Business app vs automation. | M88: High | N88: Consideration | O88: Medium | P88: Copy-ready templates; assistants paraphrase them but cite less often | Q88: Guide / template list | R88: 78 | S88: Tier 1 | T88: /blog/appointment-reminder-templates | U88: C1 | V88: C: Client message templates (WhatsApp, SMS, Hindi) | W88: Refresh
A89: doctor appointment message | B89: Supporting | C89: whatsapp reminder message for appointment | E89: Unverified | F89: Unverified: validate in Semrush India / Google Keyword Planner | G89: n/a | H89: n/a | I89: Informational | J89: chati.ai (#1, about 900 words, 30 one-liners), wati and aisensy rank. Calendly community is #9 for 'whatsapp reminder' (590/KD24). Book A Sloth is not in the top 20. | L89: Go from about 10 to 30+ templates: per-trade sets (doctor with token/OPD timing, salon festive and bridal, tutor, coach), Hindi, a reminder-timing table, and a workflow for the free WhatsApp Business app vs automation. | M89: High | N89: Consideration | O89: Medium | P89: Copy-ready templates; assistants paraphrase them but cite less often | Q89: Guide / template list | R89: 78 | S89: Tier 1 | T89: /blog/appointment-reminder-templates | U89: C1 | V89: C: Client message templates (WhatsApp, SMS, Hindi) | W89: Refresh
A90: salon appointment reminder message | B90: Supporting | C90: whatsapp reminder message for appointment | E90: Unverified | F90: Unverified: validate in Semrush India / Google Keyword Planner | G90: n/a | H90: n/a | I90: Informational | J90: chati.ai (#1, about 900 words, 30 one-liners), wati and aisensy rank. Calendly community is #9 for 'whatsapp reminder' (590/KD24). Book A Sloth is not in the top 20. | L90: Go from about 10 to 30+ templates: per-trade sets (doctor with token/OPD timing, salon festive and bridal, tutor, coach), Hindi, a reminder-timing table, and a workflow for the free WhatsApp Business app vs automation. | M90: High | N90: Consideration | O90: Medium | P90: Copy-ready templates; assistants paraphrase them but cite less often | Q90: Guide / template list | R90: 78 | S90: Tier 1 | T90: /blog/appointment-reminder-templates | U90: C1 | V90: C: Client message templates (WhatsApp, SMS, Hindi) | W90: Refresh
A91: meeting invitation in hindi | B91: Primary | C91: meeting invitation in hindi | D91: meeting invitation message in hindi, meeting ka message, बैठक निमंत्रण | E91: Unverified | F91: Unverified: validate in Semrush India / Google Keyword Planner | G91: n/a | H91: n/a | I91: Informational | J91: 6 of 10 results are machine-translation proxies or Pinterest. Rated High feasibility. | L91: Native Devanagari plus Hinglish versions. Google currently ranks translate.google proxies of English pages for this query. | M91: Low | N91: Awareness | O91: Low | P91: Copy-ready templates; assistants paraphrase them but cite less often | Q91: Guide / template list | R91: 64 | S91: Tier 3 | T91: /blog/meeting-invitation-message-hindi | U91: C11 | V91: C: Client message templates (WhatsApp, SMS, Hindi) | W91: New
A92: meeting invitation message in hindi | B92: Supporting | C92: meeting invitation in hindi | E92: Unverified | F92: Unverified: validate in Semrush India / Google Keyword Planner | G92: n/a | H92: n/a | I92: Informational | J92: 6 of 10 results are machine-translation proxies or Pinterest. Rated High feasibility. | L92: Native Devanagari plus Hinglish versions. Google currently ranks translate.google proxies of English pages for this query. | M92: Low | N92: Awareness | O92: Low | P92: Copy-ready templates; assistants paraphrase them but cite less often | Q92: Guide / template list | R92: 64 | S92: Tier 3 | T92: /blog/meeting-invitation-message-hindi | U92: C11 | V92: C: Client message templates (WhatsApp, SMS, Hindi) | W92: New
A93: meeting ka message | B93: Supporting | C93: meeting invitation in hindi | E93: Unverified | F93: Unverified: validate in Semrush India / Google Keyword Planner | G93: n/a | H93: n/a | I93: Informational | J93: 6 of 10 results are machine-translation proxies or Pinterest. Rated High feasibility. | L93: Native Devanagari plus Hinglish versions. Google currently ranks translate.google proxies of English pages for this query. | M93: Low | N93: Awareness | O93: Low | P93: Copy-ready templates; assistants paraphrase them but cite less often | Q93: Guide / template list | R93: 64 | S93: Tier 3 | T93: /blog/meeting-invitation-message-hindi | U93: C11 | V93: C: Client message templates (WhatsApp, SMS, Hindi) | W93: New
A94: बैठक निमंत्रण | B94: Supporting | C94: meeting invitation in hindi | E94: Unverified | F94: Unverified: validate in Semrush India / Google Keyword Planner | G94: n/a | H94: n/a | I94: Informational | J94: 6 of 10 results are machine-translation proxies or Pinterest. Rated High feasibility. | L94: Native Devanagari plus Hinglish versions. Google currently ranks translate.google proxies of English pages for this query. | M94: Low | N94: Awareness | O94: Low | P94: Copy-ready templates; assistants paraphrase them but cite less often | Q94: Guide / template list | R94: 64 | S94: Tier 3 | T94: /blog/meeting-invitation-message-hindi | U94: C11 | V94: C: Client message templates (WhatsApp, SMS, Hindi) | W94: New
A95: payment reminder message in hindi | B95: Primary | C95: payment reminder message in hindi | D95: payment reminder in hindi, paisa reminder message, udhaar reminder message | E95: Unverified | F95: Unverified: validate in Semrush India / Google Keyword Planner | G95: n/a | H95: n/a | I95: Informational | J95: 6 of 10 results are translate.google proxies. Rated High feasibility. | L95: Hindi-first page that links to C4. Covers shopkeeper and service-business variants. | M95: High | N95: Consideration | O95: Low | P95: Copy-ready templates; assistants paraphrase them but cite less often | Q95: Guide / template list | R95: 74 | S95: Tier 2 | T95: /blog/payment-reminder-message-hindi | U95: C12 | V95: C: Client message templates (WhatsApp, SMS, Hindi) | W95: New
A96: payment reminder in hindi | B96: Supporting | C96: payment reminder message in hindi | E96: Unverified | F96: Unverified: validate in Semrush India / Google Keyword Planner | G96: n/a | H96: n/a | I96: Informational | J96: 6 of 10 results are translate.google proxies. Rated High feasibility. | L96: Hindi-first page that links to C4. Covers shopkeeper and service-business variants. | M96: High | N96: Consideration | O96: Low | P96: Copy-ready templates; assistants paraphrase them but cite less often | Q96: Guide / template list | R96: 74 | S96: Tier 2 | T96: /blog/payment-reminder-message-hindi | U96: C12 | V96: C: Client message templates (WhatsApp, SMS, Hindi) | W96: New
A97: paisa reminder message | B97: Supporting | C97: payment reminder message in hindi | E97: Unverified | F97: Unverified: validate in Semrush India / Google Keyword Planner | G97: n/a | H97: n/a | I97: Informational | J97: 6 of 10 results are translate.google proxies. Rated High feasibility. | L97: Hindi-first page that links to C4. Covers shopkeeper and service-business variants. | M97: High | N97: Consideration | O97: Low | P97: Copy-ready templates; assistants paraphrase them but cite less often | Q97: Guide / template list | R97: 74 | S97: Tier 2 | T97: /blog/payment-reminder-message-hindi | U97: C12 | V97: C: Client message templates (WhatsApp, SMS, Hindi) | W97: New
A98: udhaar reminder message | B98: Supporting | C98: payment reminder message in hindi | E98: Unverified | F98: Unverified: validate in Semrush India / Google Keyword Planner | G98: n/a | H98: n/a | I98: Informational | J98: 6 of 10 results are translate.google proxies. Rated High feasibility. | L98: Hindi-first page that links to C4. Covers shopkeeper and service-business variants. | M98: High | N98: Consideration | O98: Low | P98: Copy-ready templates; assistants paraphrase them but cite less often | Q98: Guide / template list | R98: 74 | S98: Tier 2 | T98: /blog/payment-reminder-message-hindi | U98: C12 | V98: C: Client message templates (WhatsApp, SMS, Hindi) | W98: New
A99: how to manage appointments on whatsapp | B99: Primary | C99: how to manage appointments on whatsapp | D99: whatsapp appointment booking, online booking vs whatsapp booking, whatsapp booking system for clinic, whatsapp business for doctors, does whatsapp have appointment booking | E99: Unverified | F99: Unverified: validate in Semrush India / Google Keyword Planner | G99: n/a | H99: n/a | I99: Informational | J99: WhatsApp API vendors dominate (infobip, gallabox, aisensy, respond.io). A Reddit r/indianstartups thread on WhatsApp scheduling ranks #5. | L99: An honest comparison of manual WhatsApp, a WhatsApp API bot and a booking link plus WhatsApp reminders, with time and no-show costs. Includes the hidden costs of the WhatsApp Business API (per-conversation pricing). | M99: High | N99: Consideration | O99: High | P99: Copy-ready templates; assistants paraphrase them but cite less often | Q99: Sub-pillar guide | R99: 78 | S99: Tier 1 | T99: /blog/manage-appointments-on-whatsapp | U99: C13 | V99: C: Client message templates (WhatsApp, SMS, Hindi) | W99: New
A100: whatsapp appointment booking | B100: Supporting | C100: how to manage appointments on whatsapp | E100: Unverified | F100: Unverified: validate in Semrush India / Google Keyword Planner | G100: n/a | H100: n/a | I100: Informational | J100: WhatsApp API vendors dominate (infobip, gallabox, aisensy, respond.io). A Reddit r/indianstartups thread on WhatsApp scheduling ranks #5. | L100: An honest comparison of manual WhatsApp, a WhatsApp API bot and a booking link plus WhatsApp reminders, with time and no-show costs. Includes the hidden costs of the WhatsApp Business API (per-conversation pricing). | M100: High | N100: Consideration | O100: High | P100: Copy-ready templates; assistants paraphrase them but cite less often | Q100: Sub-pillar guide | R100: 78 | S100: Tier 1 | T100: /blog/manage-appointments-on-whatsapp | U100: C13 | V100: C: Client message templates (WhatsApp, SMS, Hindi) | W100: New
...

Sheet Cluster Map
A1: Cluster map: one URL per intent
A2: Supporting keywords listed on a row are covered by that one page. Do not create separate posts for them (cannibalisation guard).
A4: Cluster | B4: Cluster name | C4: Role | D4: ID | E4: Title | F4: URL | G4: Primary keyword | H4: Volume / KD (verified) | I4: Intent | J4: Supporting keywords (same page, no separate articles) | K4: Product page supported | L4: Publish now / later / merge / skip
A5: A | B5: India pricing, alternatives & comparisons | C5: Pillar | D5: A1 | E5: Best Appointment Booking Apps in India (2026): ₹ Pricing, UPI & WhatsApp Compared | F5: /compare/best-appointment-booking-apps-india | G5: appointment scheduling app india | H5: Unverified | I5: Commercial | J5: free appointment booking app india, appointment booking app india, best scheduling app india | K5: /pricing, /features/payments | L5: Publish now (New)
A6: A | B6: India pricing, alternatives & comparisons | C6: Support | D6: A2 | E6: Calendly Pricing in India (2026): Plans in ₹, GST, Card Forex & the Free Plan Limits | F6: /compare/calendly-pricing-india | G6: calendly pricing in india | H6: Unverified | I6: Commercial | J6: is calendly free, calendly free plan limits, calendly price in rupees, calendly razorpay | K6: /pricing, /earnings-calculator | L6: Publish now (New)
A7: A | B7: India pricing, alternatives & comparisons | C7: Comparison | D7: A3 | E7: Calendly Alternative for India: Get Booked and Paid via UPI (Migration Guide) | F7: /compare/calendly-alternative-india | G7: calendly alternative india | H7: Unverified | I7: Commercial | J7: calendly alternative, calendly alternatives free, free calendly alternative, calendly upi | K7: /features/payments, /pricing | L7: Publish now (Consolidate)
A8: A | B8: India pricing, alternatives & comparisons | C8: Support | D8: A4 | E8: Topmate Commission & Fees Explained (2026): What You Actually Keep per ₹1,000 | F8: /compare/topmate-commission | G8: topmate commission | H8: Unverified | I8: Commercial | J8: topmate charges, topmate pricing, topmate fees, topmate payout | K8: /earnings-calculator, /pricing | L8: Publish now (New)
A9: A | B9: India pricing, alternatives & comparisons | C9: Comparison | D9: A5 | E9: Topmate Alternative for Consultants, Therapists & Coaches (0% Commission) | F9: /compare/topmate-alternative | G9: topmate alternative | H9: Unverified | I9: Commercial | J9: topmate alternatives, topmate vs book a sloth, topmate competitors | K9: /pricing, /features/booking-pages | L9: Publish now (Consolidate)
A10: A | B10: India pricing, alternatives & comparisons | C10: Support | D10: A9 | E10: Can You Take UPI Payments on Calendly? (And 3 Workarounds Indian Professionals Use) | F10: /blog/calendly-upi-payments | G10: calendly upi payment | H10: Unverified | I10: Informational | J10: calendly razorpay integration, calendly paid events india, calendly payment india | K10: /features/payments | L10: Publish now (New)
A11: A | B11: India pricing, alternatives & comparisons | C11: Tool | D11: A11 | E11: Booking Platform Fee Calculator (Topmate, Calendly, SuperProfile, Book A Sloth) | F11: /earnings-calculator | G11: booking platform fee calculator | H11: Unverified | I11: Commercial | J11: topmate fee calculator, commission calculator for creators | K11: /pricing | L11: Publish now (Refresh)
A12: A | B12: India pricing, alternatives & comparisons | C12: Comparison | D12: A10 | E12: Topmate vs SuperProfile vs Book A Sloth: Fees, Payouts & Booking Features | F12: /compare/topmate-vs-superprofile | G12: topmate vs superprofile | H12: Unverified | I12: Commercial | J12: superprofile pricing india, topmate or superprofile | K12: /pricing | L12: Later (New)
A13: A | B13: India pricing, alternatives & comparisons | C13: Comparison | D13: A6 | E13: Zoho Bookings Alternative for Indian Freelancers & Clinics | F13: /compare/zoho-bookings-alternative | G13: zoho bookings alternative | H13: Unverified | I13: Commercial | J13: zoho bookings pricing india, zoho bookings vs calendly | K13: /pricing | L13: Later (Consolidate)
A14: A | B14: India pricing, alternatives & comparisons | C14: Comparison | D14: A7 | E14: Cal.com vs Calendly for Indian Users: Payments, UPI, Self-Hosting & ₹ Cost | F14: /compare/cal-com-vs-calendly | G14: cal.com vs calendly | H14: Unverified | I14: Commercial | J14: cal com pricing india, cal.com upi | K14: /compare | L14: Later (New)
A15: A | B15: India pricing, alternatives & comparisons | C15: Comparison | D15: A8 | E15: Setmore Alternative for India (UPI, WhatsApp, GST) | F15: /compare/setmore-alternative | G15: setmore alternative | H15: Unverified | I15: Commercial | J15: setmore vs calendly, setmore india | K15: /pricing | L15: Later (Consolidate)
... A79: X | B79: Excluded themes | C79: - | D79: - | E79: - | F79: - | G79: - | H79: - | I79: - | J79: Instagram follower/likes growth (Topmate's top 25k visits), HR onboarding welcome messages, student planners, Salesforce/sales ops, vaccine slots, dental/coaching ERP head terms, lawyer/CA city pages, 'superprofile alternative' (searchers want Instagram DM automation), off-ICP 'digital marketing for X' posts. | K79: - | L79: Skip

Sheet 90-Day Calendar
A1: 90-day publishing calendar (weeks start Monday 2026-10-12)
A2: Cadence: about 3 pages a week (2 new + 1 refresh or consolidation). Mixes quick wins (refreshes, forum-dominated SERPs) with pillars that need data. Re-score in week 13 using GSC data.
A4: Week | B4: Week of | C4: Type | D4: ID | E4: Page | F4: Primary keyword | G4: Supporting | H4: Cluster | I4: Funnel | J4: Score | K4: Required links (to) + product page | L4: Research / assets / dependencies
A5: 1 | B5: 2026-10-12 | C5: Ops / technical | E5: 301 map live: /lp/calendly-alternative→/compare/calendly-alternative-india, /lp/topmate-vs-bookasloth + /blog/topmate-alternative→/compare/topmate-alternative, /lp/zoho-bookings-alternative, /lp/setmore-alternative→/compare/*, /for/doctors-india→/for/doctors. Host-profile noindex gate. Launch /compare and /templates hubs (existing pages only). GSC + GA4 baseline export. Start the pricing-data and no-show data pulls. | L5: Decide whether any /lp page is used for paid ads: if yes, keep it noindex with a canonical to /compare instead of a 301.
A6: 1 | B6: 2026-10-12 | C6: New | D6: A2 | E6: Calendly Pricing in India (2026): Plans in ₹, GST, Card Forex & the Free Plan Limits | F6: calendly pricing in india (unverified) | G6: is calendly free, calendly free plan limits, calendly price in rupees, calendly razorpay | H6: A: India pricing, alternatives & comparisons | I6: Consideration | J6: 85 | K6: A3, A1, A9, /pricing | product: /pricing, /earnings-calculator | L6: Calendly pricing screenshot, RBI reference rate with date, a card forex markup source | Decide whether any /lp page is used for paid ads: if yes, keep it noindex with a canonical to /compare instead of a 301.
A7: 1 | B7: 2026-10-12 | C7: Refresh | D7: C1 | E7: WhatsApp Appointment Reminder Templates: 30+ Messages for Clinics, Salons, Tutors & Coaches (English + Hindi) | F7: whatsapp reminder message for appointment (unverified) | G7: appointment reminder message, whatsapp reminder, doctor appointment message, salon appointment reminder message | H7: C: Client message templates (WhatsApp, SMS, Hindi) | I7: Consideration | J7: 78 | K7: C0, C2, D1, /glossary/whatsapp-reminder, /features/notifications | product: /features/notifications | L7: Hindi copy check by a native speaker
A8: 1 | B8: 2026-10-12 | C8: New | D8: C0 | E8: Free Message Templates for Service Businesses in India (WhatsApp, SMS, Email, Hindi) | F8: whatsapp message templates for business (unverified) | G8: business message templates, client message templates, whatsapp templates for clinic | H8: C: Client message templates (WhatsApp, SMS, Hindi) | I8: Awareness | J8: 68 | K8: C1, C2, C3, C4, C5, C6, C7, C8, C12, B6, E1, E3 | product: /features/notifications | L8: Hub design
A9: 2 | B9: 2026-10-19 | C9: Ops / technical | E9: 301 /blog/scheduling-terms-glossary→/glossary/buffer-time. Add DefinedTerm schema to /glossary. | L9: A3 depends on the A2 pricing table.
A10: 2 | B10: 2026-10-19 | C10: Consolidate | D10: A3 | E10: Calendly Alternative for India: Get Booked and Paid via UPI (Migration Guide) | F10: calendly alternative india (unverified) | G10: calendly alternative, calendly alternatives free, free calendly alternative, calendly upi | H10: A: India pricing, alternatives & comparisons | I10: Conversion | J10: 80 | K10: A2, A1, B1, /pricing | product: /features/payments, /pricing | L10: Migration screenshots; a 301 or noindex decision for the /lp page | A3 depends on the A2 pricing table.
A11: 2 | B11: 2026-10-19 | C11: New | D11: A9 | E11: Can You Take UPI Payments on Calendly? (And 3 Workarounds Indian Professionals Use) | F11: calendly upi payment (unverified) | G11: calendly razorpay integration, calendly paid events india, calendly payment india | H11: A: India pricing, alternatives & comparisons | I11: Consideration | J11: 80 | K11: A2, A3, B1, B2 | product: /features/payments | L11: Test a Zapier flow; screenshots
A12: 2 | B12: 2026-10-19 | C12: Consolidate | D12: F1 | E12: Scheduling Glossary: 40+ Booking Terms Explained (with Indian Examples) | F12: buffer time meaning (1300/KD20) | G12: buffer day, placeholder meeting meaning, 24 7 availability, lead time meaning | H12: F: Scheduling concepts & glossary | I12: Awareness | J12: 74 | K12: F4, D3, /features/availability | product: /features/availability | L12: 301 map; schema
A13: 3 | B13: 2026-10-26 | C13: Ops / technical | E13: Dev: platform comparison in /earnings-calculator. | L13: A11 needs about 2 dev days; A4 embeds it.
A14: 3 | B14: 2026-10-26 | C14: New | D14: F2 | E14: 'Please Share Anything That Will Help Prepare for Our Meeting': What to Write (30 Examples) | F14: please share anything that will help prepare for our meeting (2400/KD21) | G14: what to write in meeting notes before call, booking form notes examples, what to write when booking a consultation | H14: F: Scheduling concepts & glossary | I14: Awareness | J14: 83 | K14: F3, C7, /glossary/intake-form | product: /glossary/intake-form, /features/booking-pages | L14: A11 needs about 2 dev days; A4 embeds it.
A15: 3 | B15: 2026-10-26 | C15: New | D15: A4 | E15: Topmate Commission & Fees Explained (2026): What You Actually Keep per ₹1,000 | F15: topmate commission (unverified) | G15: topmate charges, topmate pricing, topmate fees, topmate payout | H15: A: India pricing, alternatives & comparisons | I15: Consideration | J15: 80 | K15: A5, A11, /glossary/commission, /glossary/platform-fee | product: /earnings-calculator, /pricing | L15: Topmate pricing page capture (dated); calculator
A16: 3 | B16: 2026-10-26 | C16: Refresh | D16: A11 | E16: Booking Platform Fee Calculator (Topmate, Calendly, SuperProfile, Book A Sloth) | F16: booking platform fee calculator (unverified) | G16: topmate fee calculator, commission calculator for creators | H16: A: India pricing, alternatives & comparisons | I16: Consideration | J16: 75 | K16: A4, A5, A2 | product: /pricing | L16: Dev work: fee inputs per platform with dated sources
A17: 3 | B17: 2026-10-26 | C17: New | D17: F4 | E17: New glossary entries: placeholder meeting, recurring meeting, soft booking, direct booking, preferred time, 24/7 availability, internal vs external meeting | F17: placeholder meeting (170/KD20) | G17: placeholder meeting meaning, recurring meeting, soft booking, direct booking | H17: F: Scheduling concepts & glossary | I17: Awareness | J17: 69 | K17: F1 | product: /features/availability
A18: 4 | B18: 2026-11-02 | C18: Consolidate | D18: A5 | E18: Topmate Alternative for Consultants, Therapists & Coaches (0% Commission) | F18: topmate alternative (unverified) | G18: topmate alternatives, topmate vs book a sloth, topmate competitors | H18: A: India pricing, alternatives & comparisons | I18: Conversion | J18: 80 | K18: A4, A10, A1, /earnings-calculator | product: /pricing, /features/booking-pages | L18: Fee comparison table; 301 map | A5 links to A4 and A11.
A19: 4 | B19: 2026-11-02 | C19: New | D19: B1 | E19: How to Collect Payments from Clients in India: UPI, Payment Links & Advance Booking (2026 Guide) | F19: how to collect payment from clients online india (unverified) | G19: how to accept upi payments for business, payment link for freelancers, how to take online consultation fees, accept payment without website | H19: B: Getting paid: UPI, payment links, advance payments & GST | I19: Consideration | J19: 80 | K19: B2, B3, B4, B6, A9, /glossary/upi, /glossary/payment-gateway | product: /features/payments | L19: Fee table with sources (Razorpay, Cashfree, PhonePe PG); screenshots of the Book A Sloth pay-at-booking flow
A20: 4 | B20: 2026-11-02 | C20: Refresh | D20: B6 | E20: How to Ask a Client for Payment Politely (Email, WhatsApp & Call Scripts) | F20: how to ask client for payment (720/KD15) | G20: how to ask client for payment politely, payment follow up email, polite payment reminder email | H20: B: Getting paid: UPI, payment links, advance payments & GST | I20: Awareness | J20: 65 | K20: C4, B1, B2 | product: /features/payments | L20: MSME Act section reference
A21: 5 | B21: 2026-11-09 | C21: New | D21: C4 | E21: Payment Reminder Messages for Clients: WhatsApp & Email Templates (Polite to Firm) | F21: payment reminder message (unverified) | G21: payment reminder message for client, payment due reminder whatsapp, overdue payment message | H21: C: Client message templates (WhatsApp, SMS, Hindi) | I21: Consideration | J21: 78 | K21: B6, C5, C12, B1 | product: /features/payments | L21: C4 links to B6 and B1.
A22: 5 | B22: 2026-11-09 | C22: New | D22: C13 | E22: How to Manage Appointments on WhatsApp (and When a Booking Link Saves You Hours) | F22: how to manage appointments on whatsapp (unverified) | G22: whatsapp appointment booking, online booking vs whatsapp booking, whatsapp booking system for clinic, whatsapp business for doctors | H22: C: Client message templates (WhatsApp, SMS, Hindi) | I22: Consideration | J22: 78 | K22: C1, C6, D1, A1 | product: /features/notifications, /features/booking-pages | L22: Book A Sloth host interview or case study
A23: 5 | B23: 2026-11-09 | C23: Refresh | D23: E1 | E23: Interview Calling Message: 25+ Templates (WhatsApp, SMS, Email, Hindi) | F23: interview calling message (110000/KD18) | G23: interview call message, interview invitation message, message for interview call, interview invitation sms | H23: E: Interview & meeting message templates (traffic cluster) | I23: Awareness | J23: 68 | K23: E2, E5, C1 | product: /features/booking-pages
A24: 6 | B24: 2026-11-16 | C24: Ops / technical | E24: Publish the pricing dataset (CSV) alongside G1. | L24: G1 needs listing data with n≥20 per profession, pulled from week 1.
A25: 6 | B25: 2026-11-16 | C25: New | D25: G1 | E25: How Much to Charge for a Consultation in India (2026): ₹ Rates by Profession | F25: how much to charge for consultation india (unverified) | G25: consultation charges in india, online consultation fees, how much to charge per hour consultant india, consultation fee kitna lena chahiye | H25: G: Start & grow an independent practice in India (playbooks + pricing guides) | I25: Consideration | J25: 90 | K25: G3, G6, G8, G9, G4c, A11 | product: /pricing, /earnings-calculator | L25: Book A Sloth listings data export (n by profession; publish only professions with n≥20) | G1 needs listing data with n≥20 per profession, pulled from week 1.
A26: 6 | B26: 2026-11-16 | C26: New | D26: G3 | E26: How Much Should a Personal Trainer Charge in India? Session, Monthly & Online Rate Card | F26: how much do personal trainers charge in india (unverified) | G26: personal trainer fees per month india, online personal trainer charges, personal trainer price per session delhi | H26: G: Start & grow an independent practice in India (playbooks + pricing guides) | I26: Consideration | J26: 83 | K26: G1, /blog/how-to-become-freelance-personal-trainer, /for/fitness | product: /for/fitness | L26: Book A Sloth trainer price data
A27: 6 | B27: 2026-11-16 | C27: New | D27: C6 | E27: WhatsApp Business Away Message: 40 Templates + How to Set It Up (Holidays, After-Hours, Busy) | F27: away message for business (480/KD12) | G27: away message whatsapp, best away message for whatsapp business, away message for business whatsapp, away from whatsapp | H27: C: Client message templates (WhatsApp, SMS, Hindi) | I27: Awareness | J27: 73 | K27: C13, C0, L1 | product: /features/booking-pages | L27: Setup screenshots
A28: 7 | B28: 2026-11-23 | C28: New | D28: B2 | E28: How to Take Advance Payment for Appointments (Without Chasing UPI Screenshots) | F28: advance payment for appointment (unverified) | G28: booking deposit, prepaid appointments, advance booking payment, how to take booking amount | H28: B: Getting paid: UPI, payment links, advance payments & GST | I28: Consideration | J28: 78 | K28: B1, D2, D1, /glossary/advance-payment | product: /features/payments | L28: Book A Sloth data: no-show rate prepaid vs unpaid (if sample allows) | D2 is the policy page that B2 and C3 link to.
A29: 7 | B29: 2026-11-23 | C29: New | D29: D2 | E29: Cancellation & No-Show Policy Templates for Appointments (₹ Examples for Clinics, Coaches & Salons) | F29: cancellation policy for appointments (unverified) | G29: no show policy template, late cancellation fee, cancellation policy template, refund policy for coaching | H29: D: No-shows, cancellations & booking policies | I29: Consideration | J29: 75 | K29: D1, B2, C3, /glossary/cancellation-policy | product: /features/payments | L29: Consumer-law note for refunds
A30: 7 | B30: 2026-11-23 | C30: New | D30: C3 | E30: Appointment Cancellation & Reschedule Messages: Templates for Businesses and Clients | F30: appointment cancellation message (unverified) | G30: reschedule meeting message, reschedule appointment, cancel appointment, rebook appointment | H30: C: Client message templates (WhatsApp, SMS, Hindi) | I30: Consideration | J30: 78 | K30: D2, C2, /glossary/reschedule | product: /features/notifications
A31: 8 | B31: 2026-11-30 | C31: New | D31: D1 | E31: How to Reduce No-Shows: A Playbook for Indian Clinics, Coaches, Tutors & Salons | F31: how to reduce no shows (unverified) | G31: how to reduce no shows in clinic, no show appointments, reduce missed appointments, patient no show | H31: D: No-shows, cancellations & booking policies | I31: Consideration | J31: 70 | K31: D2, C1, B2, /tools/no-show-cost-calculator, /glossary/no-show | product: /tools/no-show-cost-calculator, /features/notifications | L31: Book A Sloth data pull: no-show rates (min sample n≥200 bookings) | D1 needs no-show data by reminder type and prepaid status.
A32: 8 | B32: 2026-11-30 | C32: New | D32: G0 | E32: How to Start an Online Consultation Practice in India (Coaches, Therapists, Tutors, Trainers): Setup, Pricing, Payments & Rules | F32: how to start online consultation business (unverified) | G32: how to start coaching business in india, start online coaching india, how to start consulting business in india, 1:1 coaching business india | H32: G: Start & grow an independent practice in India (playbooks + pricing guides) | I32: Awareness | J32: 80 | K32: G1, G2, G4, G5, G6, B1, D2 | product: /be-a-sloth, /features/booking-pages | L32: Host interviews (2-3 quotes)
A33: 8 | B33: 2026-11-30 | C33: New | D33: C5 | E33: Tuition Fee Reminder Messages for Tutors & Coaching Classes (Hindi + English) | F33: tuition fee reminder message (unverified) | G33: fee reminder message, fee reminder message in hindi, monthly fee reminder for students | H33: C: Client message templates (WhatsApp, SMS, Hindi) | I33: Consideration | J33: 78 | K33: C4, /for/tutors, G4 | product: /for/tutors
A34: 9 | B34: 2026-12-07 | C34: Ops / technical | E34: New /for/therapists page goes live with G2. | L34: G2 needs a psychologist reviewer.
A35: 9 | B35: 2026-12-07 | C35: New | D35: G2 | E35: How to Start a Private Practice as a Psychologist or Counsellor in India (Operations Guide) | F35: how to start private practice psychologist india (unverified) | G35: how to start a counselling practice in india, how to get clients as a new psychologist in india, therapist fees in india, do counsellors need shop and establishment licence | H35: G: Start & grow an independent practice in India (playbooks + pricing guides) | I35: Consideration | J35: 78 | K35: H5, F3, D2, G1 | product: /for/therapists | L35: Reviewed by a practising RCI-registered psychologist | G2 needs a psychologist reviewer.
A36: 9 | B36: 2026-12-07 | C36: New | D36: H5 | E36: Booking & Payments for Psychologists and Therapists in India (Private, Prepaid Sessions) | F36: therapist booking software india (unverified) | G36: practice management for therapists india, online counselling booking, psychologist appointment software | H36: H: Industry booking-software landing pages (/for/*) | I36: Conversion | J36: 68 | K36: F3, D2, G2 | product: /for/therapists | L36: RCI-registration and privacy copy reviewed
A37: 9 | B37: 2026-12-07 | C37: New | D37: G4 | E37: How to Start Online Tuition in India (2026): Fees, Batches, UPI Collection & Parent Reminders | F37: how to start online tuition (unverified) | G37: how to start online tuition from home, online tuition business india, online tuition classes setup | H37: G: Start & grow an independent practice in India (playbooks + pricing guides) | I37: Consideration | J37: 78 | K37: C5, G4b, G4c, H8 | product: /for/tutors
A38: 10 | B38: 2026-12-14 | C38: New | D38: G6 | E38: How to Price Coaching Services in India (₹ Packages, Retainers & UPI Subscriptions) | F38: how to price coaching services (unverified) | G38: life coach fees in india, how much do life coaches charge in india, coaching packages pricing, career coach fees india | H38: G: Start & grow an independent practice in India (playbooks + pricing guides) | I38: Consideration | J38: 78 | K38: G1, G7, A11 | product: /for/life-coaches | L38: Coach pricing data
A39: 10 | B39: 2026-12-14 | C39: New | D39: L1 | E39: How to Add a Booking Link to Your Instagram Bio (and Get Paid Before the Session) | F39: booking link for instagram (unverified) | G39: instagram booking button, how to add book now button on instagram, link in bio for coaches, link in bio that takes payments | H39: L: Booking-link how-tos (Instagram, Google, website) | I39: Consideration | J39: 78 | K39: L3, C6, A1 | product: /features/booking-pages | L39: Instagram screenshots
A40: 10 | B40: 2026-12-14 | C40: Refresh | D40: H1 | E40: Turf Booking Software: Online Slot Booking + UPI Advance, 0% Commission | F40: turf booking software (unverified) | G40: turf booking system, box cricket booking software, turf management software | H40: H: Industry booking-software landing pages (/for/*) | I40: Conversion | J40: 76 | K40: A1, B2 | product: /for/sports-turf | L40: Turf owner case study
A41: 11 | B41: 2026-12-21 | C41: New | D41: A1 | E41: Best Appointment Booking Apps in India (2026): ₹ Pricing, UPI & WhatsApp Compared | F41: appointment scheduling app india (unverified) | G41: free appointment booking app india, appointment booking app india, best scheduling app india | H41: A: India pricing, alternatives & comparisons | I41: Consideration | J41: 77 | K41: A2, A3, A5, B1, C13, /pricing | product: /pricing, /features/payments | L41: A fresh test account on each tool; screenshots; a ₹ conversion with the date; a pricing-check log | A1 needs every competitor tested (weeks 6-10) and a dated pricing log. G8 needs a doctor reviewer.
A42: 11 | B42: 2026-12-21 | C42: New | D42: G8 | E42: Doctor Consultation Fees in India: How to Set Yours (Specialty, City, Follow-Up Rules) | F42: consultation fee for doctors in india (unverified) | G42: how much should a new doctor charge for consultation, follow up consultation fee rules, online consultation fee for doctors | H42: G: Start & grow an independent practice in India (playbooks + pricing guides) | I42: Consideration | J42: 75 | K42: H7, G1, D1 | product: /for/doctors | L42: Doctor reviewer; NMC sources
A43: 11 | B43: 2026-12-21 | C43: Consolidate | D43: H7 | E43: Clinic Appointment Booking Software for India (Doctors, Solo Clinics) | F43: clinic appointment booking software india (unverified) | G43: appointment booking app for doctors, doctor appointment system, free doctor appointment booking software, doctor appointment app | H43: H: Industry booking-software landing pages (/for/*) | I43: Conversion | J43: 68 | K43: C1, D1, D2 | product: /for/doctors
A44: 12 | B44: 2026-12-28 | C44: New | D44: C12 | E44: पेमेंट रिमाइंडर मैसेज (Payment Reminder Message in Hindi): WhatsApp Templates | F44: payment reminder message in hindi (unverified) | G44: payment reminder in hindi, paisa reminder message, udhaar reminder message | H44: C: Client message templates (WhatsApp, SMS, Hindi) | I44: Consideration | J44: 74 | K44: C4, C5 | product: /features/payments | L44: Native Hindi writer | C12 needs a native Hindi writer.
A45: 12 | B45: 2026-12-28 | C45: New | D45: C2 | E45: Appointment Confirmation Message Templates (WhatsApp, SMS & Email with Payment Receipt) | F45: appointment confirmation message (unverified) | G45: booking confirmation message, appointment confirmation whatsapp message, consultation booking confirmation | H45: C: Client message templates (WhatsApp, SMS, Hindi) | I45: Consideration | J45: 73 | K45: C1, C3, D2 | product: /features/notifications | L45: Screenshots of the Book A Sloth confirmation message
A46: 12 | B46: 2026-12-28 | C46: New | D46: F3 | E46: Client Intake Form Questions for Coaches, Therapists & Consultants (Copy-Ready Templates) | F46: client intake form questions (unverified) | G46: intake form template, coaching intake form, therapy intake form questions, consultation form questions | H46: F: Scheduling concepts & glossary | I46: Consideration | J46: 70 | K46: F2, C7, /glossary/intake-form | product: /features/booking-pages | L46: DPDP Act reference
A47: 13 | B47: 2027-01-04 | C47: Ops / technical | E47: Quarter review: re-score clusters with GSC data and refresh the volume data. | L47: Swap in Tier 2 pages that earn impressions earlier than expected.
A48: 13 | B48: 2027-01-04 | C48: New | D48: G5 | E48: How to Start Online Yoga Classes in India: Batches, Pricing, UPI & Zoom Setup | F48: how to start yoga classes online (unverified) | G48: online yoga classes business, how much to charge for online yoga class india, yoga teacher income india | H48: G: Start & grow an independent practice in India (playbooks + pricing guides) | I48: Consideration | J48: 73 | K48: H6, G1, C5 | product: /for/yoga-instructors | L48: Swap in Tier 2 pages that earn impressions earlier than expected.
A49: 13 | B49: 2027-01-04 | C49: New | D49: H6 | E49: Yoga Class Booking: Batches, Monthly UPI Fees & WhatsApp Reminders | F49: yoga class booking app (unverified) | G49: yoga studio booking software, online yoga class booking | H49: H: Industry booking-software landing pages (/for/*) | I49: Conversion | J49: 66 | K49: G5, C5 | product: /for/yoga-instructors
A50: 13 | B50: 2027-01-04 | C50: New | D50: L3 | E50: How to Add a 'Book Now' Button to Your Google Business Profile | F50: booking button (210/KD23) | G50: google business profile booking link, book online button google, reserve with google india | H50: L: Booking-link how-tos (Instagram, Google, website) | I50: Consideration | J50: 70 | K50: L1, C8 | product: /features/booking-pages | L50: GBP screenshots
